Workbook

Sheet Update guideline
A1: Page 1- For OPM
A38: Page 2 - For Requesters

Sheet Pivot Table 3
L1: Loading
L3: =K3/G3 -> 0
L4: =K4/G4 -> 1
L5: =K5/G5 -> 1
L6: =K6/G6 -> 1
L7: =K7/G7 -> 0
L8: =K8/G8 -> 0
L9: =K9/G9 -> 1
L10: =K10/G10 -> 1
L11: =K11/G11 -> 0
L12: =K12/G12 -> 0
L13: =K13/G13 -> 0
L14: =K14/G14 -> 0
... L168: =K168/G168 -> 1

Sheet G Project Timeline-OPM update
B1: Rule: MVA EQ in-house date will be 2weeks earlier than each stage Date of each stage = OPM release
G2: Update ngày construction finish
D3: Brand | G3: 1st stage | H3: 2nd stage | I3: 3rd stage | J3: 4th stage | K3: 5th stage | L3: 6th stage
D4: SKW | E4: Pre-MLB | F4: proto 0 | G4: P1.0 | H4: P1.1 | I4: EVT | J4: DVT | K4: PVT | L4: MP
B6: Project Year | C6: Project | D6: Phase | G6: Date | H6: Date | I6: Date | J6: Date | K6: Date | L6: Date | M6: OPM DRI | N6: Mail approved Budget
B7: P26 | C7: 4CS4 | D7: SMT | G7: - | H7: - | I7: - | J7: 46076 | K7: 46123 | L7: 46149 | M7: Doris- SMT OPM
B8: P26 | C8: 4CS4 | D8: FATP | G8: - | H8: - | I8: - | J8: 46090 | K8: 46135 | L8: 46149 | M8: OPM- Đức_Ryan
B9: P26 | C9: CGY4 | D9: SMT | G9: - | H9: - | I9: - | J9: 46076 | K9: 46125 | L9: 46149 | M9: Judy Tran
B10: P26 | C10: CGY4 | D10: FATP | G10: - | H10: - | I10: - | J10: 46090 | K10: 46135 | L10: 46149 | M10: thuy Sarah
B11: P26 | C11: PKK4 | D11: SMT | G11: - | H11: - | I11: - | J11: 46076 | K11: 46123 | L11: 46149 | M11: Huong Nguyen - Clara
B12: P26 | C12: PKK4 | D12: FATP | G12: - | H12: - | I12: - | J12: 46090 | K12: 46135 | L12: 46149 | M12: Luyện - Ben
B13: P26 Demo Line | C13: 4CS4 | D13: SMT | I13: 46072 | J13: 46072 | K13: 46123 | L13: 46156 | M13: Doris- SMT OPM
B14: P26 Demo Line | C14: 4CS4 | D14: FATP | I14: 46072 | J14: 46072 | K14: 46135 | L14: 46156 | M14: OPM- Đức_Ryan
B15: P26 Demo Line | C15: CGY4 | D15: SMT | I15: 46072 | J15: 46072 | K15: 46123 | L15: 46156 | M15: Judy Tran
B16: P26 Demo Line | C16: CGY4 | D16: FATP | I16: 46072 | J16: 46072 | K16: 46135 | L16: 46156 | M16: thuy Sarah
B17: P26 Demo Line | C17: PKK4 | D17: SMT | I17: 46072 | J17: 46072 | K17: 46123 | L17: 46156 | M17: Huong Nguyen - Clara
B18: P26 Demo Line | C18: PKK4 | D18: FATP | I18: 46072 | J18: 46072 | K18: 46135 | L18: 46156 | M18: Luyện - Ben
B19: P26 Zombie line | C19: 4CS4 | D19: Zombie | K19: 46165 | L19: 46202 | M19: Jenna Thanh Tam
B20: P26 Zombie line | C20: CGY4 | D20: Zombie | K20: 46165 | L20: 46202 | M20: OPM Hung Tom
B21: P26 Zombie line | C21: PKK4 | D21: Zombie | K21: 46165 | L21: 46202 | M21: Kayla Thùy Dương
B22: P26 Service line | C22: 4CS4 | D22: SMT | K22: 46144 | L22: 46149 | M22: Tiffany Tiên
B23: P26 Service line | C23: 4CS4 | D23: FATP | L23: 46160 | M23: Thomas OPM Thanh
B24: P26 Service line | C24: CGY4 | D24: SMT | K24: 46144 | L24: 46149 | M24: Tiffany Tiên
B25: P26 Service line | C25: CGY4 | D25: FATP | L25: 46160 | M25: Thomas OPM Thanh
B26: P26 Service line | C26: PKK4 | D26: SMT | K26: 46144 | L26: 46149 | M26: Tiffany Tiên
A27: Add | B27: P26 Service line | C27: PKK4 | D27: FATP | L27: 46160 | M27: Thomas OPM Thanh
A28: Repair-A Quan | B28: P27 | C28: WGO5 | D28: SMT | G28: 46172 | H28: 46208 | I28: 46285 | J28: 46419 | K28: 46124 | M28: Tina Nguyen - OPM SMT
A29: Packing-OPM | B29: P27 | C29: WGO5 | D29: FATP | G29: 46174 | H29: 46216 | I29: 46300 | J29: 46426 | K29: 46124 | M29: Katy Nguyen Thuy Duong
B30: P27 | C30: ASK5 | D30: SMT | G30: 46172 | H30: 46208 | I30: 46285 | J30: 46419 | K30: 46124 | M30: Tina Nguyen - OPM SMT
B31: P27 | C31: ASK5 | D31: FATP | G31: 46174 | H31: 46216 | I31: 46300 | J31: 46426 | K31: 46124 | M31: Linh Nguyen G-OPM
B32: P27 | C32: KSH5 | D32: SMT | G32: 46172 | H32: 46208 | I32: 46285 | J32: 46419 | K32: 46124 | M32: Tina Nguyen - OPM SMT
B33: P27 | C33: KSH5 | D33: FATP | G33: 46174 | H33: 46216 | I33: 46300 | J33: 46426 | K33: 46124 | M33: Anh Thảo -Tiffany
B34: F27 | C34: MCN5 | D34: SMT | E34: 46120 | F34: 46154 | G34: 46167 | H34: 46224 | I34: 46304 | J34: 46436 | K34: 46493 | M34: Minhi Nguyen - OPM SMT
B35: F27 | C35: MCN5 | D35: FATP | F35: 46140 | G35: 46167 | H35: 46223 | I35: 46305 | J35: 46437 | M35: Jessie Nguyen OPM
B36: P25 Service line | C36: MT5 | D36: FATP
B37: P25 Service line | C37: BZ5 | D37: FATP
B38: P25 Service line | C38: FL5 | D38: FATP
B39: P25 Service line | C39: MT5 | D39: SMT
B40: P25 Service line | C40: BZ5 | D40: SMT
B41: P25 Service line | C41: FL5 | D41: SMT

Sheet G Project MVA EQ Request 
A1: Date of Request | B1: Department | C1: Requester name | D1: Requester employee ID | E1: Email | F1: Phone | G1: Item | H1: Request equipment spec | I1: Price | J1: Quantity | K1: Total Cost | L1: Purpose | M1: Year Project | N1: Project | O1: Process | P1: Stage | Q1: Required Delivery Date (update by DRI) | R1: Given LT (days) (follow DRI update) | S1: Required Delivery Date follow Stage date (line open date - 14 days) | T1: Given LT (days) follow stage date | U1: Total Leadtime | V1: Request Deadline | W1: LT theo ngày request of DRI | X1: Late/ ontime | Y1: Action | Z1: Remark | AA1: Budget Status | AB1: Budget # | AC1: PR Status | AD1: PR # | AE1: PO Status | AF1: PO # | AG1: ETA (Plan) | AH1: DTA (Actual) | AI1: #PUR request No | AJ1: Pending reason (If have) | AK1: Action for delivery later than time Setup line | AL1: Qty Done Budget | AM1: Qty Done PR | AN1: Qty Done PO | AO1: Qty Recieved
A2: 46034 | B2: MFG | C2: To Thi Phuong Anh | D2: V1524505 | E2: Phuong Anh To | F2: 4327 | G2: Mini PC (Assy) | H2: =vlookup(G2,'Bidding list 26'!$B$4:$G$270,6,0) -> #N/A | I2: 7800000 | J2: 49 | K2: =I2*J2 -> 382200000 | L2: P26 Demo Line | M2: P26 Demo Line | N2: 4CS4 | O2: FATP | P2: DVT | Q2: 46065 | R2: =Q2-A2 -> 31 | S2: {=INDEX('G Project Timeline-OPM update'!$G$7:$L$35,MATCH(1,('G Project Timeline-OPM update'!$C$7:$C$35=N2)*('G Project Timeline-OPM update'!$B$7:$B$35=M2)*('G Project Timeline-OPM update'!$D$7:$D$35=O2),0),MATCH(P2,'G Project Timeline-OPM update'!$G$4:$L$4,0))-14} -> 46058 | T2: =S2-A2 -> 24 | U2: =IFERROR(VLOOKUP(G2,'Bidding list 26'!$B$2:$P$31,15,0),"") | V2: =S2-U2 -> 46058 | X2: =if(A2>V2,"Late", "On time") -> On time | Y2: New Buy | AA2: Done | AC2: Done | AE2: Done | AF2: 1FSHQ10118 | AH2: =vlookup(AF2,Sheet9!A:D,3,0) -> Đã nhận 11.03.2026 | AI2: EPR2601310006 | AL2: =if(AA2="Done",$J2,0) -> 49 | AM2: =if(AC2="Done",$J2,0) -> 49 | AN2: =if(AE2="Done",$J2,0) -> 49 | AO2: =if(AH2<>"",$J2,0) -> 49
A3: 46034 | B3: MFG | C3: To Thi Phuong Anh | D3: V1524505 | E3: Phuong Anh To | F3: 4327 | G3: Monitor (White)+ ARM | H3: =vlookup(G3,'Bidding list 26'!$B$4:$G$270,6,0) -> HKC MB24V7-W, 23.8 inch White, With Bracket Arm Warrior WA-MH0802 (White) | I3: 1815000 | J3: 49 | K3: =I3*J3 -> 88935000 | L3: P26 Demo Line | M3: P26 Demo Line | N3: 4CS4 | O3: FATP | P3: DVT | Q3: 46065 | R3: =Q3-A3 -> 31 | S3: {=INDEX('G Project Timeline-OPM update'!$G$7:$L$35,MATCH(1,('G Project Timeline-OPM update'!$C$7:$C$35=N3)*('G Project Timeline-OPM update'!$B$7:$B$35=M3)*('G Project Timeline-OPM update'!$D$7:$D$35=O3),0),MATCH(P3,'G Project Timeline-OPM update'!$G$4:$L$4,0))-14} -> 46058 | T3: =S3-A3 -> 24 | U3: =IFERROR(VLOOKUP(G3,'Bidding list 26'!$B$2:$P$31,15,0),"") -> 80 | V3: =S3-U3 -> 45978 | X3: =if(A3>V3,"Late", "On time") -> Late | Y3: New Buy | AA3: Done | AC3: Done | AE3: Done | AF3: 1FSHQ10079 | AH3: 46073 | AI3: EPR2601310007 | AL3: =if(AA3="Done",$J3,0) -> 49 | AM3: =if(AC3="Done",$J3,0) -> 49 | AN3: =if(AE3="Done",$J3,0) -> 49 | AO3: =if(AH3<>"",$J3,0) -> 49
A4: 46035 | B4: QA | C4: Ngô Thị Hoa | D4: V1524668 | E4: Hoa (Hana) | G4: Mini PC (Assy) | H4: =vlookup(G4,'Bidding list 26'!$B$4:$G$270,6,0) -> #N/A | I4: 7800000 | J4: 23 | K4: =I4*J4 -> 179400000 | L4: P26 Demo Line | M4: P26 Demo Line | N4: 4CS4 | O4: FATP | P4: EVT | Q4: 46065 | R4: =Q4-A4 -> 30 | S4: {=INDEX('G Project Timeline-OPM update'!$G$7:$L$35,MATCH(1,('G Project Timeline-OPM update'!$C$7:$C$35=N4)*('G Project Timeline-OPM update'!$B$7:$B$35=M4)*('G Project Timeline-OPM update'!$D$7:$D$35=O4),0),MATCH(P4,'G Project Timeline-OPM update'!$G$4:$L$4,0))-14} -> 46058 | T4: =S4-A4 -> 23 | U4: =IFERROR(VLOOKUP(G4,'Bidding list 26'!$B$2:$P$31,15,0),"") | V4: =S4-U4 -> 46058 | X4: =if(A4>V4,"Late", "On time") -> On time | Y4: New Buy | AA4: Done | AC4: Done | AE4: Done | AF4: 1FSHQ10118 | AH4: =vlookup(AF4,Sheet9!A:D,3,0) -> Đã nhận 11.03.2026 | AI4: EPR2602020001 | AL4: =if(AA4="Done",$J4,0) -> 23 | AM4: =if(AC4="Done",$J4,0) -> 23 | AN4: =if(AE4="Done",$J4,0) -> 23 | AO4: =if(AH4<>"",$J4,0) -> 23
A5: 46035 | B5: QA | C5: Ngô Thị Hoa | D5: V1524668 | E5: Hoa (Hana) | G5: Monitor (White)+ ARM | H5: =vlookup(G5,'Bidding list 26'!$B$4:$G$270,6,0) -> HKC MB24V7-W, 23.8 inch White, With Bracket Arm Warrior WA-MH0802 (White) | I5: 1815000 | J5: 23 | K5: =I5*J5 -> 41745000 | L5: P26 Demo Line | M5: P26 Demo Line | N5: 4CS4 | O5: FATP | P5: EVT | Q5: 46065 | R5: =Q5-A5 -> 30 | S5: {=INDEX('G Project Timeline-OPM update'!$G$7:$L$35,MATCH(1,('G Project Timeline-OPM update'!$C$7:$C$35=N5)*('G Project Timeline-OPM update'!$B$7:$B$35=M5)*('G Project Timeline-OPM update'!$D$7:$D$35=O5),0),MATCH(P5,'G Project Timeline-OPM update'!$G$4:$L$4,0))-14} -> 46058 | T5: =S5-A5 -> 23 | U5: =IFERROR(VLOOKUP(G5,'Bidding list 26'!$B$2:$P$31,15,0),"") -> 80 | V5: =S5-U5 -> 45978 | X5: =if(A5>V5,"Late", "On time") -> Late | Y5: New Buy | AA5: Done | AC5: Done | AE5: Done | AF5: 1FSHQ10079 | AH5: 46073 | AI5: EPR2602020002 | AL5: =if(AA5="Done",$J5,0) -> 23 | AM5: =if(AC5="Done",$J5,0) -> 23 | AN5: =if(AE5="Done",$J5,0) -> 23 | AO5: =if(AH5<>"",$J5,0) -> 23
A6: 46035 | B6: TE | C6: Nguyen Trung Kien | D6: V1524574 | E6: kiennt1@fih-foxconn.com | G6: Monitor (White)+ ARM | H6: =vlookup(G6,'Bidding list 26'!$B$4:$G$270,6,0) -> HKC MB24V7-W, 23.8 inch White, With Bracket Arm Warrior WA-MH0802 (White) | I6: 1815000 | J6: 6 | K6: =I6*J6 -> 10890000 | L6: P26 Demo Line | M6: P26 Demo Line | N6: 4CS4 | O6: FATP | P6: EVT | Q6: 46076 | R6: =Q6-A6 -> 41 | S6: {=INDEX('G Project Timeline-OPM update'!$G$7:$L$35,MATCH(1,('G Project Timeline-OPM update'!$C$7:$C$35=N6)*('G Project Timeline-OPM update'!$B$7:$B$35=M6)*('G Project Timeline-OPM update'!$D$7:$D$35=O6),0),MATCH(P6,'G Project Timeline-OPM update'!$G$4:$L$4,0))-14} -> 46058 | T6: =S6-A6 -> 23 | U6: =IFERROR(VLOOKUP(G6,'Bidding list 26'!$B$2:$P$31,15,0),"") -> 80 | V6: =S6-U6 -> 45978 | X6: =if(A6>V6,"Late", "On time") -> Late | Y6: New Buy | AA6: Done | AC6: Done | AE6: Done | AF6: 1FSHQ10079 | AH6: 46073 | AI6: EPR2602020003 | AL6: =if(AA6="Done",$J6,0) -> 6 | AM6: =if(AC6="Done",$J6,0) -> 6 | AN6: =if(AE6="Done",$J6,0) -> 6 | AO6: =if(AH6<>"",$J6,0) -> 6
A7: 46035 | B7: TE | C7: Nguyen Trung Kien | D7: V1524574 | E7: kiennt1@fih-foxconn.com | G7: Mini PC (Assy) | H7: =vlookup(G7,'Bidding list 26'!$B$4:$G$270,6,0) -> #N/A | I7: 7800000 | J7: 6 | K7: =I7*J7 -> 46800000 | L7: P26 Demo Line | M7: P26 Demo Line | N7: 4CS4 | O7: FATP | P7: EVT | Q7: 46076 | R7: =Q7-A7 -> 41 | S7: {=INDEX('G Project Timeline-OPM update'!$G$7:$L$35,MATCH(1,('G Project Timeline-OPM update'!$C$7:$C$35=N7)*('G Project Timeline-OPM update'!$B$7:$B$35=M7)*('G Project Timeline-OPM update'!$D$7:$D$35=O7),0),MATCH(P7,'G Project Timeline-OPM update'!$G$4:$L$4,0))-14} -> 46058 | T7: =S7-A7 -> 23 | U7: =IFERROR(VLOOKUP(G7,'Bidding list 26'!$B$2:$P$31,15,0),"") | V7: =S7-U7 -> 46058 | X7: =if(A7>V7,"Late", "On time") -> On time | Y7: New Buy | AA7: Done | AC7: Done | AE7: Done | AF7: 1FSHQ10118 | AH7: =vlookup(AF7,Sheet9!A:D,3,0) -> Đã nhận 11.03.2026 | AI7: EPR2602020004 | AL7: =if(AA7="Done",$J7,0) -> 6 | AM7: =if(AC7="Done",$J7,0) -> 6 | AN7: =if(AE7="Done",$J7,0) -> 6 | AO7: =if(AH7<>"",$J7,0) -> 6
A8: 46041 | B8: ENG3 | C8: Nguyen Van Huynh | D8: V1536667 | E8: Nguyễn Seven (Huỳnh) | F8: 4500 | G8: IPC+ | H8: =vlookup(G8,'Bidding list 26'!$B$4:$G$270,6,0) -> #N/A | I8: 14200000 | J8: 5 | K8: =I8*J8 -> 71000000 | L8: PC for Auto charging machine P26 | M8: P26 | N8: 4CS4 | O8: FATP | P8: DVT | Q8: 46052 | R8: =Q8-A8 -> 11 | S8: {=INDEX('G Project Timeline-OPM update'!$G$7:$L$35,MATCH(1,('G Project Timeline-OPM update'!$C$7:$C$35=N8)*('G Project Timeline-OPM update'!$B$7:$B$35=M8)*('G Project Timeline-OPM update'!$D$7:$D$35=O8),0),MATCH(P8,'G Project Timeline-OPM update'!$G$4:$L$4,0))-14} -> 46076 | T8: =S8-A8 -> 35 | U8: =IFERROR(VLOOKUP(G8,'Bidding list 26'!$B$2:$P$31,15,0),"") | V8: =S8-U8 -> 46076 | X8: =if(A8>V8,"Late", "On time") -> On time | Y8: New Buy | AA8: Done | AB8: FATP-NPI-P26-MVA2601-104OM | AC8: Done | AD8: 1FSHQ10126 | AE8: Done | AF8: 1FSHQ10126 | AH8: 46073 | AI8: EPR2601310001: Done | AL8: =if(AA8="Done",$J8,0) -> 5 | AM8: =if(AC8="Done",$J8,0) -> 5 | AN8: =if(AE8="Done",$J8,0) -> 5 | AO8: =if(AH8<>"",$J8,0) -> 5
A9: 46041 | B9: ENG3 | C9: Nguyen Van Huynh | D9: V1536667 | E9: Nguyễn Seven (Huỳnh) | F9: 4500 | G9: IPC+ | H9: =vlookup(G9,'Bidding list 26'!$B$4:$G$270,6,0) -> #N/A | I9: 14200000 | J9: 5 | K9: =I9*J9 -> 71000000 | L9: PC for Auto charging machine P26 | M9: P26 | N9: PKK4 | O9: FATP | P9: DVT | Q9: 46052 | R9: =Q9-A9 -> 11 | S9: {=INDEX('G Project Timeline-OPM update'!$G$7:$L$35,MATCH(1,('G Project Timeline-OPM update'!$C$7:$C$35=N9)*('G Project Timeline-OPM update'!$B$7:$B$35=M9)*('G Project Timeline-OPM update'!$D$7:$D$35=O9),0),MATCH(P9,'G Project Timeline-OPM update'!$G$4:$L$4,0))-14} -> 46076 | T9: =S9-A9 -> 35 | U9: =IFERROR(VLOOKUP(G9,'Bidding list 26'!$B$2:$P$31,15,0),"") | V9: =S9-U9 -> 46076 | X9: =if(A9>V9,"Late", "On time") -> On time | Y9: New Buy | AA9: Done | AB9: FATP-NPI-P26-MVA2601-104OM | AC9: Done | AD9: 1FSHQ10127 | AE9: Done | AF9: 1FSHQ10126 | AH9: 46073 | AI9: EPR2601310002: Done | AL9: =if(AA9="Done",$J9,0) -> 5 | AM9: =if(AC9="Done",$J9,0) -> 5 | AN9: =if(AE9="Done",$J9,0) -> 5 | AO9: =if(AH9<>"",$J9,0) -> 5
A10: 46041 | B10: ENG3 | C10: Nguyen Van Huynh | D10: V1536667 | E10: Nguyễn Seven (Huỳnh) | F10: 4500 | G10: IPC+ | H10: =vlookup(G10,'Bidding list 26'!$B$4:$G$270,6,0) -> #N/A | I10: 14200000 | J10: 5 | K10: =I10*J10 -> 71000000 | L10: PC for Auto charging machine P26 | M10: P26 | N10: CGY4 | O10: FATP | P10: DVT | Q10: 46052 | R10: =Q10-A10 -> 11 | S10: {=INDEX('G Project Timeline-OPM update'!$G$7:$L$35,MATCH(1,('G Project Timeline-OPM update'!$C$7:$C$35=N10)*('G Project Timeline-OPM update'!$B$7:$B$35=M10)*('G Project Timeline-OPM update'!$D$7:$D$35=O10),0),MATCH(P10,'G Project Timeline-OPM update'!$G$4:$L$4,0))-14} -> 46076 | T10: =S10-A10 -> 35 | U10: =IFERROR(VLOOKUP(G10,'Bidding list 26'!$B$2:$P$31,15,0),"") | V10: =S10-U10 -> 46076 | X10: =if(A10>V10,"Late", "On time") -> On time | Y10: New Buy | AA10: Done | AB10: FATP-NPI-P26-MVA2601-104OM | AC10: Done | AD10: 1FSHQ10128 | AE10: Done | AF10: 1FSHQ10126 | AH10: 46073 | AI10: EPR2601310003: Done | AL10: =if(AA10="Done",$J10,0) -> 5 | AM10: =if(AC10="Done",$J10,0) -> 5 | AN10: =if(AE10="Done",$J10,0) -> 5 | AO10: =if(AH10<>"",$J10,0) -> 5
A11: 46058 | B11: REL | C11: Laymu Chen | D11: 504000 | E11: LaymuTHChen@fih-foxconn.com | G11: IPC | H11: =vlookup(G11,'Bidding list 26'!$B$4:$G$270,6,0) -> #N/A | I11: 10870000 | J11: 2 | K11: =I11*J11 -> 21740000 | L11: P26 | M11: P26 | N11: 4CS4 | O11: SMT | P11: DVT | Q11: 46064 | R11: =Q11-A11 -> 6 | S11: {=INDEX('G Project Timeline-OPM update'!$G$7:$L$35,MATCH(1,('G Project Timeline-OPM update'!$C$7:$C$35=N11)*('G Project Timeline-OPM update'!$B$7:$B$35=M11)*('G Project Timeline-OPM update'!$D$7:$D$35=O11),0),MATCH(P11,'G Project Timeline-OPM update'!$G$4:$L$4,0))-14} -> 46062 | T11: =S11-A11 -> 4 | U11: =IFERROR(VLOOKUP(G11,'Bidding list 26'!$B$2:$P$31,15,0),"") | V11: =S11-U11 -> 46062 | X11: =if(A11>V11,"Late", "On time") -> On time | Y11: Leverage | AA11: Done | AC11: Done | AE11: Done | AH11: 46064 | AI11: EPR2602060002 : Done / tầm T7 trả | AK11: Tháng 7 trả? | AL11: =if(AA11="Done",$J11,0) -> 2 | AM11: =if(AC11="Done",$J11,0) -> 2 | AN11: =if(AE11="Done",$J11,0) -> 2 | AO11: =if(AH11<>"",$J11,0) -> 2
A12: 46058 | B12: REL | C12: Laymu Chen | D12: 504000 | E12: LaymuTHChen@fih-foxconn.com | G12: Monitor 2 | H12: =vlookup(G12,'Bidding list 26'!$B$4:$G$270,6,0) -> VA1903H-2, 19 inch, VGA cable + HDMI cable / Brand: VIEWSONIC | I12: 1240000 | J12: 7 | K12: =I12*J12 -> 8680000 | L12: P26 | M12: P26 | N12: 4CS4 | O12: SMT | P12: DVT | Q12: 46064 | R12: =Q12-A12 -> 6 | S12: {=INDEX('G Project Timeline-OPM update'!$G$7:$L$35,MATCH(1,('G Project Timeline-OPM update'!$C$7:$C$35=N12)*('G Project Timeline-OPM update'!$B$7:$B$35=M12)*('G Project Timeline-OPM update'!$D$7:$D$35=O12),0),MATCH(P12,'G Project Timeline-OPM update'!$G$4:$L$4,0))-14} -> 46062 | T12: =S12-A12 -> 4 | U12: =IFERROR(VLOOKUP(G12,'Bidding list 26'!$B$2:$P$31,15,0),"") -> 50 | V12: =S12-U12 -> 46012 | X12: =if(A12>V12,"Late", "On time") -> Late | Y12: Leverage | AA12: Done | AC12: Done | AE12: Done | AH12: 111807 | AI12: EPR2602060003 Done / tầm T7 trả | AK12: Tháng 7 trả? | AL12: =if(AA12="Done",$J12,0) -> 7 | AM12: =if(AC12="Done",$J12,0) -> 7 | AN12: =if(AE12="Done",$J12,0) -> 7 | AO12: =if(AH12<>"",$J12,0) -> 7
A13: 46080 | B13: MFG | C13: To Thi Phuong Anh | D13: V1524505 | E13: Phuong Anh To | G13: Monitor 2 | H13: =vlookup(G13,'Bidding list 26'!$B$4:$G$270,6,0) -> VA1903H-2, 19 inch, VGA cable + HDMI cable / Brand: VIEWSONIC | I13: 1240000 | J13: 31 | K13: =I13*J13 -> 38440000 | L13: PKK4 | M13: P26 | N13: PKK4 | O13: FATP | P13: MP | Q13: 46123 | R13: =Q13-A13 -> 43 | S13: {=INDEX('G Project Timeline-OPM update'!$G$7:$L$35,MATCH(1,('G Project Timeline-OPM update'!$C$7:$C$35=N13)*('G Project Timeline-OPM update'!$B$7:$B$35=M13)*('G Project Timeline-OPM update'!$D$7:$D$35=O13),0),MATCH(P13,'G Project Timeline-OPM update'!$G$4:$L$4,0))-14} -> 46135 | T13: =S13-A13 -> 55 | U13: =IFERROR(VLOOKUP(G13,'Bidding list 26'!$B$2:$P$31,15,0),"") -> 50 | V13: =S13-U13 -> 46085 | W13: =A13+U13 -> 46130 | X13: =if(A13>V13,"Late", "On time") -> On time | Y13: New Buy | AA13: Done | AB13: FATP-MP-PKK4-MVA2603-03OM | AC13: Done | AD13: 1FSHQ30084 | AE13: Done | AF13: 1FSHQ30084 | AG13: 46144 | AH13: 46144 | AI13: EPR2603070011 | AL13: =if(AA13="Done",$J13,0) -> 31 | AM13: =if(AC13="Done",$J13,0) -> 31 | AN13: =if(AE13="Done",$J13,0) -> 31 | AO13: =if(#REF!<>"",$J13,0) -> #REF!
A14: 46080 | B14: MFG | C14: To Thi Phuong Anh | D14: V1524505 | E14: Phuong Anh To | G14: Mini PC (Assy) | H14: =vlookup(G14,'Bidding list 26'!$B$4:$G$270,6,0) -> #N/A | I14: 7800000 | J14: 31 | K14: =I14*J14 -> 241800000 | L14: PKK4 | M14: P26 | N14: PKK4 | O14: FATP | P14: MP | Q14: 46123 | R14: =Q14-A14 -> 43 | S14: {=INDEX('G Project Timeline-OPM update'!$G$7:$L$35,MATCH(1,('G Project Timeline-OPM update'!$C$7:$C$35=N14)*('G Project Timeline-OPM update'!$B$7:$B$35=M14)*('G Project Timeline-OPM update'!$D$7:$D$35=O14),0),MATCH(P14,'G Project Timeline-OPM update'!$G$4:$L$4,0))-14} -> 46135 | T14: =S14-A14 -> 55 | U14: =IFERROR(VLOOKUP(G14,'Bidding list 26'!$B$2:$P$31,15,0),"") | V14: =S14-U14 -> 46135 | W14: =A14+U14 -> 46080 | X14: =if(A14>V14,"Late", "On time") -> On time | Y14: New Buy | AA14: Done | AB14: FATP-MP-PKK4-MVA2603-03OM | AC14: Done | AD14: 1FSHQ30085 | AE14: Done | AF14: 1FSHQ30085 | AI14: EPR2603070012 | AL14: =if(AA14="Done",$J14,0) -> 31 | AM14: =if(AC14="Done",$J14,0) -> 31 | AN14: =if(AE14="Done",$J14,0) -> 31 | AO14: =if(AH13<>"",$J14,0) -> 31
A15: 46080 | B15: MFG | C15: To Thi Phuong Anh | D15: V1524505 | E15: Phuong Anh To | G15: Barcode Scanner SEUIC HS505DP, USB cable | H15: =vlookup(G15,'Bidding list 26'!$B$4:$G$270,6,0) -> HS505DP, USB cable | I15: 2300000 | J15: 31 | K15: =I15*J15 -> 71300000 | L15: PKK4 | M15: P26 | N15: PKK4 | O15: FATP | P15: MP | Q15: 46123 | R15: =Q15-A15 -> 43 | S15: {=INDEX('G Project Timeline-OPM update'!$G$7:$L$35,MATCH(1,('G Project Timeline-OPM update'!$C$7:$C$35=N15)*('G Project Timeline-OPM update'!$B$7:$B$35=M15)*('G Project Timeline-OPM update'!$D$7:$D$35=O15),0),MATCH(P15,'G Project Timeline-OPM update'!$G$4:$L$4,0))-14} -> 46135 | T15: =S15-A15 -> 55 | U15: =IFERROR(VLOOKUP(G15,'Bidding list 26'!$B$2:$P$31,15,0),"") -> 50 | V15: =S15-U15 -> 46085 | W15: =A15+U15 -> 46130 | X15: =if(A15>V15,"Late", "On time") -> On time | Y15: New Buy | AA15: Done | AB15: FATP-MP-PKK4-MVA2603-28OM | AC15: Done | AD15: VNPR202604040096 | AE15: Done | AF15: VNPO202604160162 | AG15: 46171 | AH15: 46172 | AI15: EPR2603210009 | AL15: =if(AA15="Done",$J15,0) -> 31 | AM15: =if(AC15="Done",$J15,0) -> 31 | AN15: =if(AE15="Done",$J15,0) -> 31 | AO15: =if(AH15<>"",$J15,0) -> 31
A16: 46080 | B16: MFG | C16: To Thi Phuong Anh | D16: V1524505 | E16: Phuong Anh To | G16: Barcode Printer ZEBRA | H16: =vlookup(G16,'Bidding list 26'!$B$4:$G$270,6,0) -> ZT610, 600dpi | I16: 48800000 | J16: 21 | K16: =I16*J16 -> 1024800000 | L16: PKK4 | M16: P26 | N16: PKK4 | O16: FATP | P16: MP | Q16: 46123 | R16: =Q16-A16 -> 43 | S16: {=INDEX('G Project Timeline-OPM update'!$G$7:$L$35,MATCH(1,('G Project Timeline-OPM update'!$C$7:$C$35=N16)*('G Project Timeline-OPM update'!$B$7:$B$35=M16)*('G Project Timeline-OPM update'!$D$7:$D$35=O16),0),MATCH(P16,'G Project Timeline-OPM update'!$G$4:$L$4,0))-14} -> 46135 | T16: =S16-A16 -> 55 | U16: =IFERROR(VLOOKUP(G16,'Bidding list 26'!$B$2:$P$31,15,0),"") -> 50 | V16: =S16-U16 -> 46085 | W16: =A16+U16 -> 46130 | X16: =if(A16>V16,"Late", "On time") -> On time | Y16: New Buy | AA16: Done | AB16: FATP-MP-PKK4-MVA2603-03OM | AC16: Done | AD16: 1FSHQ30087 | AE16: Done | AF16: 1FSHQ30087 | AG16: pending | AH16: =vlookup(AF16,Sheet9!A:D,3,0) | AI16: EPR2603070013 | AK16: Lấy 16x 1FSHQ20007 => Trả hàng trước | AL16: =if(AA16="Done",$J16,0) -> 21 | AM16: =if(AC16="Done",$J16,0) -> 21 | AN16: =if(AE16="Done",$J16,0) -> 21 | AO16: =if(AH16<>"",$J16,0) -> 0
A17: 46080 | B17: MFG | C17: To Thi Phuong Anh | D17: V1524505 | E17: Phuong Anh To | G17: Monitor 2 | H17: =vlookup(G17,'Bidding list 26'!$B$4:$G$270,6,0) -> VA1903H-2, 19 inch, VGA cable + HDMI cable / Brand: VIEWSONIC | I17: 1240000 | J17: 138 | K17: =I17*J17 -> 171120000 | L17: 4CS4 | M17: P26 | N17: 4CS4 | O17: FATP | P17: MP | Q17: 46123 | R17: =Q17-A17 -> 43 | S17: {=INDEX('G Project Timeline-OPM update'!$G$7:$L$35,MATCH(1,('G Project Timeline-OPM update'!$C$7:$C$35=N17)*('G Project Timeline-OPM update'!$B$7:$B$35=M17)*('G Project Timeline-OPM update'!$D$7:$D$35=O17),0),MATCH(P17,'G Project Timeline-OPM update'!$G$4:$L$4,0))-14} -> 46135 | T17: =S17-A17 -> 55 | U17: =IFERROR(VLOOKUP(G17,'Bidding list 26'!$B$2:$P$31,15,0),"") -> 50 | V17: =S17-U17 -> 46085 | W17: =A17+U17 -> 46130 | X17: =if(A17>V17,"Late", "On time") -> On time | Y17: New Buy | AA17: Done | AB17: FATP-MP-4CS4-MVA2603-04OM | AC17: Done | AD17: 1FSHQ30096 | AE17: Done | AF17: 1FSHQ30096 | AG17: EPR2603070014 request này của MFG P26 có 138x màn hình. Chị lấy đơn 1FSHQ40007 & 1FSHQ30117 : 38 + 6 =44x Trả đơn trước cho P26 MFG | AH17: 85x out ngày 10.06.2026 | AI17: EPR2603070014 | AL17: =if(AA17="Done",$J17,0) -> 138 | AM17: =if(AC17="Done",$J17,0) -> 138 | AN17: =if(AE17="Done",$J17,0) -> 138 | AO17: =if(AH17<>"",$J17,0) -> 138
A18: 46080 | B18: MFG | C18: To Thi Phuong Anh | D18: V1524505 | E18: Phuong Anh To | G18: Mini PC (Assy) | H18: =vlookup(G18,'Bidding list 26'!$B$4:$G$270,6,0) -> #N/A | I18: 7800000 | J18: 163 | K18: =I18*J18 -> 1271400000 | L18: 4CS4 | M18: P26 | N18: 4CS4 | O18: FATP | P18: MP | Q18: 46123 | R18: =Q18-A18 -> 43 | S18: {=INDEX('G Project Timeline-OPM update'!$G$7:$L$35,MATCH(1,('G Project Timeline-OPM update'!$C$7:$C$35=N18)*('G Project Timeline-OPM update'!$B$7:$B$35=M18)*('G Project Timeline-OPM update'!$D$7:$D$35=O18),0),MATCH(P18,'G Project Timeline-OPM update'!$G$4:$L$4,0))-14} -> 46135 | T18: =S18-A18 -> 55 | U18: =IFERROR(VLOOKUP(G18,'Bidding list 26'!$B$2:$P$31,15,0),"") | V18: =S18-U18 -> 46135 | W18: =A18+U18 -> 46080 | X18: =if(A18>V18,"Late", "On time") -> On time | Y18: New Buy | AA18: Done | AB18: FATP-MP-4CS4-MVA2603-04OM | AC18: Done | AD18: 100x 1FSHQ30097 63x 1FSHQ30098 | AE18: Done | AF18: 100x 1FSHQ30097 63x 1FSHQ30098 | AG18: pending | AH18: =vlookup(AF18,Sheet9!A:D,3,0) | AI18: EPR2603070015 | AL18: =if(AA18="Done",$J18,0) -> 163 | AM18: =if(AC18="Done",$J18,0) -> 163 | AN18: =if(AE18="Done",$J18,0) -> 163 | AO18: =if(AH18<>"",$J18,0) -> 0
A19: 46080 | B19: MFG | C19: To Thi Phuong Anh | D19: V1524505 | E19: Phuong Anh To | G19: Barcode Scanner SEUIC HS505DP, USB cable | H19: =vlookup(G19,'Bidding list 26'!$B$4:$G$270,6,0) -> HS505DP, USB cable | I19: 2300000 | J19: 160 | K19: =I19*J19 -> 368000000 | L19: 4CS4 | M19: P26 | N19: 4CS4 | O19: FATP | P19: MP | Q19: 46123 | R19: =Q19-A19 -> 43 | S19: {=INDEX('G Project Timeline-OPM update'!$G$7:$L$35,MATCH(1,('G Project Timeline-OPM update'!$C$7:$C$35=N19)*('G Project Timeline-OPM update'!$B$7:$B$35=M19)*('G Project Timeline-OPM update'!$D$7:$D$35=O19),0),MATCH(P19,'G Project Timeline-OPM update'!$G$4:$L$4,0))-14} -> 46135 | T19: =S19-A19 -> 55 | U19: =IFERROR(VLOOKUP(G19,'Bidding list 26'!$B$2:$P$31,15,0),"") -> 50 | V19: =S19-U19 -> 46085 | W19: =A19+U19 -> 46130 | X19: =if(A19>V19,"Late", "On time") -> On time | Y19: New Buy | AA19: Done | AB19: FATP-MP-4CS4-MVA2603-29OM | AC19: Done | AD19: VNPR202604040091 | AE19: Done | AF19: VNPO202604160165 | AG19: 46171 | AH19: 46172 | AI19: EPR2603210010 | AL19: =if(AA19="Done",$J19,0) -> 160 | AM19: =if(AC19="Done",$J19,0) -> 160 | AN19: =if(AE19="Done",$J19,0) -> 160 | AO19: =if(AH19<>"",$J19,0) -> 160
A20: 46080 | B20: MFG | C20: To Thi Phuong Anh | D20: V1524505 | E20: Phuong Anh To | G20: Barcode Scanner SEUIC HS505HDP-2530 ,USB cable | H20: =vlookup(G20,'Bidding list 26'!$B$4:$G$270,6,0) -> SEUIC HS505HDP-2530 ,USB cable | I20: 3300000 | J20: 6 | K20: =I20*J20 -> 19800000 | L20: 4CS4 | M20: P26 | N20: 4CS4 | O20: FATP | P20: MP | Q20: 46123 | R20: =Q20-A20 -> 43 | S20: {=INDEX('G Project Timeline-OPM update'!$G$7:$L$35,MATCH(1,('G Project Timeline-OPM update'!$C$7:$C$35=N20)*('G Project Timeline-OPM update'!$B$7:$B$35=M20)*('G Project Timeline-OPM update'!$D$7:$D$35=O20),0),MATCH(P20,'G Project Timeline-OPM update'!$G$4:$L$4,0))-14} -> 46135 | T20: =S20-A20 -> 55 | U20: =IFERROR(VLOOKUP(G20,'Bidding list 26'!$B$2:$P$31,15,0),"") -> 50 | V20: =S20-U20 -> 46085 | W20: =A20+U20 -> 46130 | X20: =if(A20>V20,"Late", "On time") -> On time | Y20: New Buy | AA20: Done | AB20: FATP-MP-4CS4-MVA2603-29OM | AC20: Done | AD20: VNPR202604040091 | AE20: Done | AF20: VNPO202604160165 | AG20: Dự kiến 25/05 hàng về | AI20: EPR2603210011 | AL20: =if(AA20="Done",$J20,0) -> 6 | AM20: =if(AC20="Done",$J20,0) -> 6 | AN20: =if(AE20="Done",$J20,0) -> 6 | AO20: =if(AH20<>"",$J20,0) -> 0
A21: 46080 | B21: MFG | C21: To Thi Phuong Anh | D21: V1524505 | E21: Phuong Anh To | G21: Barcode Printer ZEBRA | H21: =vlookup(G21,'Bidding list 26'!$B$4:$G$270,6,0) -> ZT610, 600dpi | I21: 48800000 | J21: 20 | K21: =I21*J21 -> 976000000 | L21: 4CS4 | M21: P26 | N21: 4CS4 | O21: FATP | P21: MP | Q21: 46123 | R21: =Q21-A21 -> 43 | S21: {=INDEX('G Project Timeline-OPM update'!$G$7:$L$35,MATCH(1,('G Project Timeline-OPM update'!$C$7:$C$35=N21)*('G Project Timeline-OPM update'!$B$7:$B$35=M21)*('G Project Timeline-OPM update'!$D$7:$D$35=O21),0),MATCH(P21,'G Project Timeline-OPM update'!$G$4:$L$4,0))-14} -> 46135 | T21: =S21-A21 -> 55 | U21: =IFERROR(VLOOKUP(G21,'Bidding list 26'!$B$2:$P$31,15,0),"") -> 50 | V21: =S21-U21 -> 46085 | W21: =A21+U21 -> 46130 | X21: =if(A21>V21,"Late", "On time") -> On time | Y21: New Buy | AA21: Done | AB21: FATP-MP-4CS4-MVA2603-04OM | AC21: Done | AD21: 1FSHQ30099 | AE21: Done | AF21: 1FSHQ30099 | AH21: 46162 | AI21: EPR2603070016 | AL21: =if(AA21="Done",$J21,0) -> 20 | AM21: =if(AC21="Done",$J21,0) -> 20 | AN21: =if(AE21="Done",$J21,0) -> 20 | AO21: =if(AH21<>"",$J21,0) -> 20
A22: 46080 | B22: MFG | C22: To Thi Phuong Anh | D22: V1524505 | E22: Phuong Anh To | G22: Mini PC (Assy) | H22: =vlookup(G22,'Bidding list 26'!$B$4:$G$270,6,0) -> #N/A | I22: 7800000 | J22: 184 | K22: =I22*J22 -> 1435200000 | L22: CGY4 | M22: P26 | N22: CGY4 | O22: FATP | P22: MP | Q22: 46123 | R22: =Q22-A22 -> 43 | S22: {=INDEX('G Project Timeline-OPM update'!$G$7:$L$35,MATCH(1,('G Project Timeline-OPM update'!$C$7:$C$35=N22)*('G Project Timeline-OPM update'!$B$7:$B$35=M22)*('G Project Timeline-OPM update'!$D$7:$D$35=O22),0),MATCH(P22,'G Project Timeline-OPM update'!$G$4:$L$4,0))-14} -> 46135 | T22: =S22-A22 -> 55 | U22: =IFERROR(VLOOKUP(G22,'Bidding list 26'!$B$2:$P$31,15,0),"") | V22: =S22-U22 -> 46135 | W22: =A22+U22 -> 46080 | X22: =if(A22>V22,"Late", "On time") -> On time | Y22: New Buy | AA22: Done | AB22: FATP-MP-CGY4-MVA2603-05OM | AC22: Done | AD22: 100x 1FSHQ30103 84x 1FSHQ30108 | AE22: Done | AF22: 100x 1FSHQ30103 84x 1FSHQ30108 | AG22: pending | AH22: =vlookup(AF22,Sheet9!A:D,3,0) | AI22: EPR2603070018 | AK22: 120x mini PC (OR5) xuất urgent cho P26-CGY4 | AL22: =if(AA22="Done",$J22,0) -> 184 | AM22: =if(AC22="Done",$J22,0) -> 184 | AN22: =if(AE22="Done",$J22,0) -> 184 | AO22: =if(AH22<>"",$J22,0) -> 0
A23: 46080 | B23: MFG | C23: To Thi Phuong Anh | D23: V1524505 | E23: Phuong Anh To | G23: Monitor 2 | H23: =vlookup(G23,'Bidding list 26'!$B$4:$G$270,6,0) -> VA1903H-2, 19 inch, VGA cable + HDMI cable / Brand: VIEWSONIC | I23: 1240000 | J23: 35 | K23: =I23*J23 -> 43400000 | L23: CGY4 | M23: P26 | N23: CGY4 | O23: FATP | P23: MP | Q23: 46123 | R23: =Q23-A23 -> 43 | S23: {=INDEX('G Project Timeline-OPM update'!$G$7:$L$35,MATCH(1,('G Project Timeline-OPM update'!$C$7:$C$35=N23)*('G Project Timeline-OPM update'!$B$7:$B$35=M23)*('G Project Timeline-OPM update'!$D$7:$D$35=O23),0),MATCH(P23,'G Project Timeline-OPM update'!$G$4:$L$4,0))-14} -> 46135 | T23: =S23-A23 -> 55 | U23: =IFERROR(VLOOKUP(G23,'Bidding list 26'!$B$2:$P$31,15,0),"") -> 50 | V23: =S23-U23 -> 46085 | W23: =A23+U23 -> 46130 | X23: =if(A23>V23,"Late", "On time") -> On time | Y23: New Buy | AA23: Done | AB23: FATP-MP-CGY4-MVA2603-05OM | AC23: Done | AD23: 1FSHQ30102 | AE23: Done | AF23: 1FSHQ30102 | AG23: 46144 | AH23: 46144 | AI23: EPR2603070017 | AL23: =if(AA23="Done",$J23,0) -> 35 | AM23: =if(AC23="Done",$J23,0) -> 35 | AN23: =if(AE23="Done",$J23,0) -> 35 | AO23: =if(AH23<>"",$J23,0) -> 35
A24: 46080 | B24: MFG | C24: To Thi Phuong Anh | D24: V1524505 | E24: Phuong Anh To | G24: Barcode Scanner SEUIC HS505DP, USB cable | H24: =vlookup(G24,'Bidding list 26'!$B$4:$G$270,6,0) -> HS505DP, USB cable | I24: 2300000 | J24: 180 | K24: =I24*J24 -> 414000000 | L24: CGY4 | M24: P26 | N24: CGY4 | O24: FATP | P24: MP | Q24: 46123 | R24: =Q24-A24 -> 43 | S24: {=INDEX('G Project Timeline-OPM update'!$G$7:$L$35,MATCH(1,('G Project Timeline-OPM update'!$C$7:$C$35=N24)*('G Project Timeline-OPM update'!$B$7:$B$35=M24)*('G Project Timeline-OPM update'!$D$7:$D$35=O24),0),MATCH(P24,'G Project Timeline-OPM update'!$G$4:$L$4,0))-14} -> 46135 | T24: =S24-A24 -> 55 | U24: =IFERROR(VLOOKUP(G24,'Bidding list 26'!$B$2:$P$31,15,0),"") -> 50 | V24: =S24-U24 -> 46085 | W24: =A24+U24 -> 46130 | X24: =if(A24>V24,"Late", "On time") -> On time | Y24: New Buy | AA24: Done | AB24: FATP-MP-CGY4-MVA2603-30OM | AC24: Done | AD24: VNPR202604040108 | AE24: Done | AF24: VNPO202604160167 | AG24: 46171 | AH24: 46172 | AI24: EPR2603210012 | AL24: =if(AA24="Done",$J24,0) -> 180 | AM24: =if(AC24="Done",$J24,0) -> 180 | AN24: =if(AE24="Done",$J24,0) -> 180 | AO24: =if(AH24<>"",$J24,0) -> 180
A25: 46080 | B25: MFG | C25: To Thi Phuong Anh | D25: V1524505 | E25: Phuong Anh To | G25: Barcode Scanner SEUIC HS505HDP-2530 ,USB cable | H25: =vlookup(G25,'Bidding list 26'!$B$4:$G$270,6,0) -> SEUIC HS505HDP-2530 ,USB cable | I25: 3300000 | J25: 7 | K25: =I25*J25 -> 23100000 | L25: CGY4 | M25: P26 | N25: CGY4 | O25: FATP | P25: MP | Q25: 46123 | R25: =Q25-A25 -> 43 | S25: {=INDEX('G Project Timeline-OPM update'!$G$7:$L$35,MATCH(1,('G Project Timeline-OPM update'!$C$7:$C$35=N25)*('G Project Timeline-OPM update'!$B$7:$B$35=M25)*('G Project Timeline-OPM update'!$D$7:$D$35=O25),0),MATCH(P25,'G Project Timeline-OPM update'!$G$4:$L$4,0))-14} -> 46135 | T25: =S25-A25 -> 55 | U25: =IFERROR(VLOOKUP(G25,'Bidding list 26'!$B$2:$P$31,15,0),"") -> 50 | V25: =S25-U25 -> 46085 | W25: =A25+U25 -> 46130 | X25: =if(A25>V25,"Late", "On time") -> On time | Y25: New Buy | AA25: Done | AB25: FATP-MP-CGY4-MVA2603-30OM | AC25: Done | AD25: VNPR202604040108 | AE25: Done | AF25: VNPO202604160167 | AG25: 46193 | AH25: 46193 | AI25: EPR2603210013: Đã trả request trước PO | AL25: =if(AA25="Done",$J25,0) -> 7 | AM25: =if(AC25="Done",$J25,0) -> 7 | AN25: =if(AE25="Done",$J25,0) -> 7 | AO25: =if(AH25<>"",$J25,0) -> 7
A26: 46080 | B26: MFG | C26: To Thi Phuong Anh | D26: V1524505 | E26: Phuong Anh To | G26: Barcode Printer ZEBRA | H26: =vlookup(G26,'Bidding list 26'!$B$4:$G$270,6,0) -> ZT610, 600dpi | I26: 48800000 | J26: 31 | K26: =I26*J26 -> 1512800000 | L26: CGY4 | M26: P26 | N26: CGY4 | O26: FATP | P26: MP | Q26: 46123 | R26: =Q26-A26 -> 43 | S26: {=INDEX('G Project Timeline-OPM update'!$G$7:$L$35,MATCH(1,('G Project Timeline-OPM update'!$C$7:$C$35=N26)*('G Project Timeline-OPM update'!$B$7:$B$35=M26)*('G Project Timeline-OPM update'!$D$7:$D$35=O26),0),MATCH(P26,'G Project Timeline-OPM update'!$G$4:$L$4,0))-14} -> 46135 | T26: =S26-A26 -> 55 | U26: =IFERROR(VLOOKUP(G26,'Bidding list 26'!$B$2:$P$31,15,0),"") -> 50 | V26: =S26-U26 -> 46085 | W26: =A26+U26 -> 46130 | X26: =if(A26>V26,"Late", "On time") -> On time | Y26: New Buy | AA26: Done | AB26: FATP-MP-CGY4-MVA2603-05OM | AC26: Done | AD26: 20x 1FSHQ30106 11x 1FSHQ30107 | AE26: Done | AF26: 20x 1FSHQ30106 11x 1FSHQ30107 | AG26: 11x 1FSHQ30107 / 20/05 hàng về | AH26: =vlookup(AF26,Sheet9!A:D,3,0) | AI26: EPR2603070019 | AL26: =if(AA26="Done",$J26,0) -> 31 | AM26: =if(AC26="Done",$J26,0) -> 31 | AN26: =if(AE26="Done",$J26,0) -> 31 | AO26: =if(AH26<>"",$J26,0) -> 0
A27: 46080 | B27: MFG | C27: To Thi Phuong Anh | D27: V1524505 | E27: Phuong Anh To | G27: Monitor (White)+ ARM | H27: =vlookup(G27,'Bidding list 26'!$B$4:$G$270,6,0) -> HKC MB24V7-W, 23.8 inch White, With Bracket Arm Warrior WA-MH0802 (White) | I27: 1815000 | J27: 149 | K27: =I27*J27 -> 270435000 | L27: CGY4 | M27: P26 | N27: CGY4 | O27: FATP | P27: MP | Q27: 46123 | R27: =Q27-A27 -> 43 | S27: {=INDEX('G Project Timeline-OPM update'!$G$7:$L$35,MATCH(1,('G Project Timeline-OPM update'!$C$7:$C$35=N27)*('G Project Timeline-OPM update'!$B$7:$B$35=M27)*('G Project Timeline-OPM update'!$D$7:$D$35=O27),0),MATCH(P27,'G Project Timeline-OPM update'!$G$4:$L$4,0))-14} -> 46135 | T27: =S27-A27 -> 55 | U27: =IFERROR(VLOOKUP(G27,'Bidding list 26'!$B$2:$P$31,15,0),"") -> 80 | V27: =S27-U27 -> 46055 | W27: =A27+U27 -> 46160 | X27: =if(A27>V27,"Late", "On time") -> Late | Y27: New Buy | AA27: Done | AB27: FATP-MP-CGY4-MVA2603-05OM | AC27: Done | AD27: 1FSHQ30105 | AE27: Done | AF27: 1FSHQ30105 | AH27: =vlookup(AF27,Sheet9!A:D,3,0) -> Đã nhận 20.04 | AI27: EPR2603070020 | AL27: =if(AA27="Done",$J27,0) -> 149 | AM27: =if(AC27="Done",$J27,0) -> 149 | AN27: =if(AE27="Done",$J27,0) -> 149 | AO27: =if(AH27<>"",$J27,0) -> 149
A28: 46087 | B28: TE FATP | C28: Nguyen Trung Kien | D28: V1524574 | E28: kiennt1@fih-foxconn.com | F28: 4440 | G28: IPC++(updated) | H28: =vlookup(G28,'Bidding list 26'!$B$4:$G$270,6,0) -> Pro Tower QCT1250, Ultra 7 265, Ram 16GB DDR5, SSD 512GB, Integrated graphics card, Power 180W, HDMI & DP Port, Keyboard and Mouse, 3Yrs Wty | I28: 26752000 | J28: 76 | K28: =I28*J28 -> 2033152000 | L28: CGY4 FATP | M28: P26 Demo Line | N28: CGY4 | O28: FATP | P28: EVT | Q28: 46097 | R28: =Q28-A28 -> 10 | S28: {=INDEX('G Project Timeline-OPM update'!$G$7:$L$35,MATCH(1,('G Project Timeline-OPM update'!$C$7:$C$35=N28)*('G Project Timeline-OPM update'!$B$7:$B$35=M28)*('G Project Timeline-OPM update'!$D$7:$D$35=O28),0),MATCH(P28,'G Project Timeline-OPM update'!$G$4:$L$4,0))-14} -> 46058 | T28: =S28-A28 -> -29 | U28: =IFERROR(VLOOKUP(G28,'Bidding list 26'!$B$2:$P$31,15,0),"") -> 70 | V28: =S28-U28 -> 45988 | W28: =A28+U28 -> 46157 | X28: =if(A28>V28,"Late", "On time") -> Late | Y28: New Buy | AA28: Done | AB28: FATP-MP-P26-MVA2603-01OM | AC28: Done | AD28: 40x 1FSHQ30073 40x 1FSHQ30075 40x 1FSHQ30076 21x 1FSHQ30078 | AE28: Done | AF28: 40x 1FSHQ30073 40x 1FSHQ30075 40x 1FSHQ30076 21x 1FSHQ30078 | AH28: 46126 | AI28: EPR2603210043 ( Số lượng QTY cụ thể đã chia trên file chị Q) | AL28: =if(AA28="Done",$J28,0) -> 76 | AM28: =if(AC28="Done",$J28,0) -> 76 | AN28: =if(AE28="Done",$J28,0) -> 76 | AO28: =if(AH28<>"",$J28,0) -> 76
A29: 46087 | B29: TE SMT | C29: Nguyen Trung Kien | D29: V1524574 | E29: kiennt1@fih-foxconn.com | F29: 4440 | G29: IPC++(updated) | H29: =vlookup(G29,'Bidding list 26'!$B$4:$G$270,6,0) -> Pro Tower QCT1250, Ultra 7 265, Ram 16GB DDR5, SSD 512GB, Integrated graphics card, Power 180W, HDMI & DP Port, Keyboard and Mouse, 3Yrs Wty | I29: 26752000 | J29: 36 | K29: =I29*J29 -> 963072000 | L29: CGY4 SMT | M29: P26 Demo Line | N29: CGY4 | O29: SMT | P29: EVT | Q29: 46097 | R29: =Q29-A29 -> 10 | S29: {=INDEX('G Project Timeline-OPM update'!$G$7:$L$35,MATCH(1,('G Project Timeline-OPM update'!$C$7:$C$35=N29)*('G Project Timeline-OPM update'!$B$7:$B$35=M29)*('G Project Timeline-OPM update'!$D$7:$D$35=O29),0),MATCH(P29,'G Project Timeline-OPM update'!$G$4:$L$4,0))-14} -> 46058 | T29: =S29-A29 -> -29 | U29: =IFERROR(VLOOKUP(G29,'Bidding list 26'!$B$2:$P$31,15,0),"") -> 70 | V29: =S29-U29 -> 45988 | W29: =A29+U29 -> 46157 | X29: =if(A29>V29,"Late", "On time") -> Late | Y29: New Buy | AA29: Done | AB29: SMT-MP-P26-MVA2603-17OM | AC29: Done | AD29: 1FSHQ30200 | AE29: Done | AF29: 1FSHQ30200 | AH29: 46126 | AI29: EPR2603210044 | AL29: =if(AA29="Done",$J29,0) -> 36 | AM29: =if(AC29="Done",$J29,0) -> 36 | AN29: =if(AE29="Done",$J29,0) -> 36 | AO29: =if(AH29<>"",$J29,0) -> 36
A30: 46087 | B30: TE FATP | C30: Nguyen Trung Kien | D30: V1524574 | E30: kiennt1@fih-foxconn.com | F30: 4440 | G30: IPC++(updated) | H30: =vlookup(G30,'Bidding list 26'!$B$4:$G$270,6,0) -> Pro Tower QCT1250, Ultra 7 265, Ram 16GB DDR5, SSD 512GB, Integrated graphics card, Power 180W, HDMI & DP Port, Keyboard and Mouse, 3Yrs Wty | I30: 26752000 | J30: 65 | K30: =I30*J30 -> 1738880000 | L30: 4CS4 FATP | M30: P26 | N30: 4CS4 | O30: FATP | P30: MP | Q30: 46097 | R30: =Q30-A30 -> 10 | S30: {=INDEX('G Project Timeline-OPM update'!$G$7:$L$35,MATCH(1,('G Project Timeline-OPM update'!$C$7:$C$35=N30)*('G Project Timeline-OPM update'!$B$7:$B$35=M30)*('G Project Timeline-OPM update'!$D$7:$D$35=O30),0),MATCH(P30,'G Project Timeline-OPM update'!$G$4:$L$4,0))-14} -> 46135 | T30: =S30-A30 -> 48 | U30: =IFERROR(VLOOKUP(G30,'Bidding list 26'!$B$2:$P$31,15,0),"") -> 70 | V30: =S30-U30 -> 46065 | W30: =A30+U30 -> 46157 | X30: =if(A30>V30,"Late", "On time") -> Late | Y30: New Buy | AA30: Done | AB30: FATP-MP-P26-MVA2603-01OM | AC30: Done | AD30: 40x 1FSHQ30073 40x 1FSHQ30075 40x 1FSHQ30076 21x 1FSHQ30078 | AE30: Done | AF30: 40x 1FSHQ30073 40x 1FSHQ30075 40x 1FSHQ30076 21x 1FSHQ30078 | AH30: 46126 | AI30: EPR2603210045 ( Số lượng QTY cụ thể đã chia trên file chị Q) | AL30: =if(AA30="Done",$J30,0) -> 65 | AM30: =if(AC30="Done",$J30,0) -> 65 | AN30: =if(AE30="Done",$J30,0) -> 65 | AO30: =if(AH30<>"",$J30,0) -> 65
A31: 46087 | B31: TE SMT | C31: Nguyen Trung Kien | D31: V1524574 | E31: kiennt1@fih-foxconn.com | F31: 4440 | G31: IPC++(updated) | H31: =vlookup(G31,'Bidding list 26'!$B$4:$G$270,6,0) -> Pro Tower QCT1250, Ultra 7 265, Ram 16GB DDR5, SSD 512GB, Integrated graphics card, Power 180W, HDMI & DP Port, Keyboard and Mouse, 3Yrs Wty | I31: 26752000 | J31: 38 | K31: =I31*J31 -> 1016576000 | L31: 4CS4 SMT | M31: P26 | N31: 4CS4 | O31: SMT | P31: MP | Q31: 46097 | R31: =Q31-A31 -> 10 | S31: {=INDEX('G Project Timeline-OPM update'!$G$7:$L$35,MATCH(1,('G Project Timeline-OPM update'!$C$7:$C$35=N31)*('G Project Timeline-OPM update'!$B$7:$B$35=M31)*('G Project Timeline-OPM update'!$D$7:$D$35=O31),0),MATCH(P31,'G Project Timeline-OPM update'!$G$4:$L$4,0))-14} -> 46135 | T31: =S31-A31 -> 48 | U31: =IFERROR(VLOOKUP(G31,'Bidding list 26'!$B$2:$P$31,15,0),"") -> 70 | V31: =S31-U31 -> 46065 | W31: =A31+U31 -> 46157 | X31: =if(A31>V31,"Late", "On time") -> Late | Y31: New Buy | AA31: Done | AB31: SMT-MP-P26-MVA2603-17OM | AC31: Done | AD31: 1FSHQ30201 | AE31: Done | AF31: 1FSHQ30201 | AH31: 46126 | AI31: EPR2603210046 | AL31: =if(AA31="Done",$J31,0) -> 38 | AM31: =if(AC31="Done",$J31,0) -> 38 | AN31: =if(AE31="Done",$J31,0) -> 38 | AO31: =if(AH31<>"",$J31,0) -> 38
A32: 46094 | B32: GG-WH | C32: Nguyen Thi Viet | D32: V1524536 | E32: Vietnt@fih-foxconn.com | F32: 4478 | G32: Monitor 1 | H32: =vlookup(G32,'Bidding list 26'!$B$4:$G$270,6,0) -> DELL E2225HM, 21.5 inch HDMI cable, 3Yrs Wty | I32: 1980000 | J32: 3 | K32: =I32*J32 -> 5940000 | L32: 4CS4 SVR line | M32: P26 Service line | N32: 4CS4 | O32: FATP | P32: MP | Q32: 46127 | R32: =Q32-A32 -> 33 | S32: {=INDEX('G Project Timeline-OPM update'!$G$7:$L$35,MATCH(1,('G Project Timeline-OPM update'!$C$7:$C$35=N32)*('G Project Timeline-OPM update'!$B$7:$B$35=M32)*('G Project Timeline-OPM update'!$D$7:$D$35=O32),0),MATCH(P32,'G Project Timeline-OPM update'!$G$4:$L$4,0))-14} -> 46146 | T32: =S32-A32 -> 52 | U32: =IFERROR(VLOOKUP(G32,'Bidding list 26'!$B$2:$P$31,15,0),"") -> 50 | V32: =S32-U32 -> 46096 | W32: =A32+U32 -> 46144 | X32: =if(A32>V32,"Late", "On time") -> On time | Y32: New Buy | Z32: G | AA32: Done | AB32: FATP-SV-4CS4-MVA2603-42OM | AC32: Done | AD32: 1FSHQ40058 | AE32: Done | AF32: 1FSHQ40058 | AG32: =vlookup(AF32,Sheet9!A:D,4,0) | AH32: 46141 | AI32: EPR2603240015 | AL32: =if(AA32="Done",$J32,0) -> 3 | AM32: =if(AC32="Done",$J32,0) -> 3 | AN32: =if(AE32="Done",$J32,0) -> 3 | AO32: =if(AH32<>"",$J32,0) -> 3
A33: 46094 | B33: GG-WH | C33: Nguyen Thi Viet | D33: V1524536 | E33: Vietnt@fih-foxconn.com | F33: 4478 | G33: IPC+(updated) | H33: =vlookup(G33,'Bidding list 26'!$B$4:$G$270,6,0) -> Pro Tower QCT1250, Ultra 5 235, Ram 16GB DDR5, SSD 512GB, Integrated graphics card, Power 180W, HDMI & DP Port, Keyboard and Mouse, 3Yrs Wty | I33: 18717000 | J33: 3 | K33: =I33*J33 -> 56151000 | L33: 4CS4 SVR line | M33: P26 Service line | N33: 4CS4 | O33: FATP | P33: MP | Q33: 46127 | R33: =Q33-A33 -> 33 | S33: {=INDEX('G Project Timeline-OPM update'!$G$7:$L$35,MATCH(1,('G Project Timeline-OPM update'!$C$7:$C$35=N33)*('G Project Timeline-OPM update'!$B$7:$B$35=M33)*('G Project Timeline-OPM update'!$D$7:$D$35=O33),0),MATCH(P33,'G Project Timeline-OPM update'!$G$4:$L$4,0))-14} -> 46146 | T33: =S33-A33 -> 52 | U33: =IFERROR(VLOOKUP(G33,'Bidding list 26'!$B$2:$P$31,15,0),"") -> 70 | V33: =S33-U33 -> 46076 | W33: =A33+U33 -> 46164 | X33: =if(A33>V33,"Late", "On time") -> Late | Y33: New Buy | Z33: G | AA33: Done | AB33: FATP-SV-4CS4-MVA2603-42OM | AC33: Done | AD33: 1FSHQ40057 | AF33: 1FSHQ40057 | AH33: Đã nhận 23/04 | AI33: EPR2603240016 | AL33: =if(AA33="Done",$J33,0) -> 3 | AM33: =if(AC33="Done",$J33,0) -> 3 | AN33: =if(AE33="Done",$J33,0) -> 0 | AO33: =if(AH33<>"",$J33,0) -> 3
A34: 46094 | B34: GG-WH | C34: Nguyen Thi Viet | D34: V1524536 | E34: Vietnt@fih-foxconn.com | F34: 4478 | G34: PDA CHAINWAY C61-4850 | H34: =vlookup(G34,'Bidding list 26'!$B$4:$G$270,6,0) -> C61-4850, Not including RFID module. Includes: 64GB 27-key Android 11, controller with battery, charging dock, charging adapter, glass screen protector | I34: 15500000 | J34: 1 | K34: =I34*J34 -> 15500000 | L34: 4CS4 SVR line | M34: P26 | N34: 4CS4 | O34: FATP | P34: MP | Q34: 46127 | R34: =Q34-A34 -> 33 | S34: {=INDEX('G Project Timeline-OPM update'!$G$7:$L$35,MATCH(1,('G Project Timeline-OPM update'!$C$7:$C$35=N34)*('G Project Timeline-OPM update'!$B$7:$B$35=M34)*('G Project Timeline-OPM update'!$D$7:$D$35=O34),0),MATCH(P34,'G Project Timeline-OPM update'!$G$4:$L$4,0))-14} -> 46135 | T34: =S34-A34 -> 41 | U34: =IFERROR(VLOOKUP(G34,'Bidding list 26'!$B$2:$P$31,15,0),"") -> 65 | V34: =S34-U34 -> 46070 | W34: =A34+U34 -> 46159 | X34: =if(A34>V34,"Late", "On time") -> Late | Y34: New Buy | Z34: G | AA34: Done | AB34: FATP-MP-4CS4-MVA2603-42OM | AC34: Done | AD34: VNPR202603260169 | AE34: Done | AF34: VNPO202603310112 | AH34: 46149 | AI34: EPR2603240017 | AK34: đã out 20may tại vp OM - chị Việt | AL34: =if(AA34="Done",$J34,0) -> 1 | AM34: =if(AC34="Done",$J34,0) -> 1 | AN34: =if(AE34="Done",$J34,0) -> 1 | AO34: =if(AH34<>"",$J34,0) -> 1
A35: 46094 | B35: GG-WH | C35: Nguyen Thi Viet | D35: V1524536 | E35: Vietnt@fih-foxconn.com | F35: 4478 | G35: Barcode Scanner ZEBRA DS8178,USB cable | H35: =vlookup(G35,'Bidding list 26'!$B$4:$G$270,6,0) -> ZEBRA DS8178,USB cable PCS Wireless Scanner | I35: 5800000 | J35: 1 | K35: =I35*J35 -> 5800000 | L35: 4CS4 SVR line | M35: P26 | N35: 4CS4 | O35: FATP | P35: MP | Q35: 46127 | R35: =Q35-A35 -> 33 | S35: {=INDEX('G Project Timeline-OPM update'!$G$7:$L$35,MATCH(1,('G Project Timeline-OPM update'!$C$7:$C$35=N35)*('G Project Timeline-OPM update'!$B$7:$B$35=M35)*('G Project Timeline-OPM update'!$D$7:$D$35=O35),0),MATCH(P35,'G Project Timeline-OPM update'!$G$4:$L$4,0))-14} -> 46135 | T35: =S35-A35 -> 41 | U35: =IFERROR(VLOOKUP(G35,'Bidding list 26'!$B$2:$P$31,15,0),"") -> 65 | V35: =S35-U35 -> 46070 | W35: =A35+U35 -> 46159 | X35: =if(A35>V35,"Late", "On time") -> Late | Y35: New Buy | Z35: G | AA35: Done | AB35: FATP-MP-4CS4-MVA2603-42OM | AC35: Done | AD35: VNPR202603260169 | AE35: Done | AF35: VNPO202603310112 | AH35: Đã nhận 25.04 | AI35: EPR2603210023 | AL35: =if(AA35="Done",$J35,0) -> 1 | AM35: =if(AC35="Done",$J35,0) -> 1 | AN35: =if(AE35="Done",$J35,0) -> 1 | AO35: =if(AH35<>"",$J35,0) -> 1
A36: 46094 | B36: GG-WH | C36: Nguyen Thi Viet | D36: V1524536 | E36: Vietnt@fih-foxconn.com | F36: 4478 | G36: Monitor 1 | H36: =vlookup(G36,'Bidding list 26'!$B$4:$G$270,6,0) -> DELL E2225HM, 21.5 inch HDMI cable, 3Yrs Wty | I36: 1980000 | J36: 3 | K36: =I36*J36 -> 5940000 | L36: CGY4 SVR line | M36: P26 Service line | N36: CGY4 | O36: FATP | P36: MP | Q36: 46127 | R36: =Q36-A36 -> 33 | S36: {=INDEX('G Project Timeline-OPM update'!$G$7:$L$35,MATCH(1,('G Project Timeline-OPM update'!$C$7:$C$35=N36)*('G Project Timeline-OPM update'!$B$7:$B$35=M36)*('G Project Timeline-OPM update'!$D$7:$D$35=O36),0),MATCH(P36,'G Project Timeline-OPM update'!$G$4:$L$4,0))-14} -> 46146 | T36: =S36-A36 -> 52 | U36: =IFERROR(VLOOKUP(G36,'Bidding list 26'!$B$2:$P$31,15,0),"") -> 50 | V36: =S36-U36 -> 46096 | W36: =A36+U36 -> 46144 | X36: =if(A36>V36,"Late", "On time") -> On time | Y36: New Buy | Z36: G | AA36: Done | AB36: FATP-SV-CGY4-MVA2603-43OM | AC36: Done | AD36: 1FSHQ40061 | AE36: Done | AF36: 1FSHQ40061 | AH36: 46141 | AI36: EPR2603240018 | AL36: =if(AA36="Done",$J36,0) -> 3 | AM36: =if(AC36="Done",$J36,0) -> 3 | AN36: =if(AE36="Done",$J36,0) -> 3 | AO36: =if(AH36<>"",$J36,0) -> 3
A37: 46094 | B37: GG-WH | C37: Nguyen Thi Viet | D37: V1524536 | E37: Vietnt@fih-foxconn.com | F37: 4478 | G37: IPC+(updated) | H37: =vlookup(G37,'Bidding list 26'!$B$4:$G$270,6,0) -> Pro Tower QCT1250, Ultra 5 235, Ram 16GB DDR5, SSD 512GB, Integrated graphics card, Power 180W, HDMI & DP Port, Keyboard and Mouse, 3Yrs Wty | I37: 18717000 | J37: 3 | K37: =I37*J37 -> 56151000 | L37: CGY4 SVR line | M37: P26 Service line | N37: CGY4 | O37: FATP | P37: MP | Q37: 46127 | R37: =Q37-A37 -> 33 | S37: {=INDEX('G Project Timeline-OPM update'!$G$7:$L$35,MATCH(1,('G Project Timeline-OPM update'!$C$7:$C$35=N37)*('G Project Timeline-OPM update'!$B$7:$B$35=M37)*('G Project Timeline-OPM update'!$D$7:$D$35=O37),0),MATCH(P37,'G Project Timeline-OPM update'!$G$4:$L$4,0))-14} -> 46146 | T37: =S37-A37 -> 52 | U37: =IFERROR(VLOOKUP(G37,'Bidding list 26'!$B$2:$P$31,15,0),"") -> 70 | V37: =S37-U37 -> 46076 | W37: =A37+U37 -> 46164 | X37: =if(A37>V37,"Late", "On time") -> Late | Y37: New Buy | Z37: G | AA37: Done | AB37: FATP-SV-CGY4-MVA2603-43OM | AC37: Done | AD37: 1FSHQ40059 | AE37: Done | AF37: 1FSHQ40059 | AH37: Đã nhận | AI37: EPR2603240019 | AL37: =if(AA37="Done",$J37,0) -> 3 | AM37: =if(AC37="Done",$J37,0) -> 3 | AN37: =if(AE37="Done",$J37,0) -> 3 | AO37: =if(AH37<>"",$J37,0) -> 3
A38: 46094 | B38: GG-WH | C38: Nguyen Thi Viet | D38: V1524536 | E38: Vietnt@fih-foxconn.com | F38: 4478 | G38: PDA CHAINWAY C61-4850 | H38: =vlookup(G38,'Bidding list 26'!$B$4:$G$270,6,0) -> C61-4850, Not including RFID module. Includes: 64GB 27-key Android 11, controller with battery, charging dock, charging adapter, glass screen protector | I38: 15500000 | J38: 1 | K38: =I38*J38 -> 15500000 | L38: CGY4 SVR line | M38: P26 | N38: CGY4 | O38: FATP | P38: MP | Q38: 46127 | R38: =Q38-A38 -> 33 | S38: {=INDEX('G Project Timeline-OPM update'!$G$7:$L$35,MATCH(1,('G Project Timeline-OPM update'!$C$7:$C$35=N38)*('G Project Timeline-OPM update'!$B$7:$B$35=M38)*('G Project Timeline-OPM update'!$D$7:$D$35=O38),0),MATCH(P38,'G Project Timeline-OPM update'!$G$4:$L$4,0))-14} -> 46135 | T38: =S38-A38 -> 41 | U38: =IFERROR(VLOOKUP(G38,'Bidding list 26'!$B$2:$P$31,15,0),"") -> 65 | V38: =S38-U38 -> 46070 | W38: =A38+U38 -> 46159 | X38: =if(A38>V38,"Late", "On time") -> Late | Y38: New Buy | Z38: G | AA38: Done | AB38: FATP-MP-CGY4-MVA2603-43OM | AC38: Done | AD38: VNPR202603260195 | AE38: Done | AF38: VNPO202603310112 | AH38: 46149 | AI38: EPR2603240020 | AK38: đã out 20may tại vp OM - chị Việt | AL38: =if(AA38="Done",$J38,0) -> 1 | AM38: =if(AC38="Done",$J38,0) -> 1 | AN38: =if(AE38="Done",$J38,0) -> 1 | AO38: =if(AH38<>"",$J38,0) -> 1
A39: 46094 | B39: GG-WH | C39: Nguyen Thi Viet | D39: V1524536 | E39: Vietnt@fih-foxconn.com | F39: 4478 | G39: Barcode Scanner ZEBRA DS8178,USB cable | H39: =vlookup(G39,'Bidding list 26'!$B$4:$G$270,6,0) -> ZEBRA DS8178,USB cable PCS Wireless Scanner | I39: 5800000 | J39: 1 | K39: =I39*J39 -> 5800000 | L39: CGY4 SVR line | M39: P26 | N39: CGY4 | O39: FATP | P39: MP | Q39: 46127 | R39: =Q39-A39 -> 33 | S39: {=INDEX('G Project Timeline-OPM update'!$G$7:$L$35,MATCH(1,('G Project Timeline-OPM update'!$C$7:$C$35=N39)*('G Project Timeline-OPM update'!$B$7:$B$35=M39)*('G Project Timeline-OPM update'!$D$7:$D$35=O39),0),MATCH(P39,'G Project Timeline-OPM update'!$G$4:$L$4,0))-14} -> 46135 | T39: =S39-A39 -> 41 | U39: =IFERROR(VLOOKUP(G39,'Bidding list 26'!$B$2:$P$31,15,0),"") -> 65 | V39: =S39-U39 -> 46070 | W39: =A39+U39 -> 46159 | X39: =if(A39>V39,"Late", "On time") -> Late | Y39: New Buy | Z39: G | AA39: Done | AB39: FATP-MP-CGY4-MVA2603-43OM | AC39: Done | AD39: VNPR202603260195 | AE39: Done | AF39: VNPO202603310112 | AH39: Đã nhận 25.04 | AI39: EPR2603210025 | AL39: =if(AA39="Done",$J39,0) -> 1 | AM39: =if(AC39="Done",$J39,0) -> 1 | AN39: =if(AE39="Done",$J39,0) -> 1 | AO39: =if(AH39<>"",$J39,0) -> 1
A40: 46094 | B40: GG-WH | C40: Nguyen Thi Viet | D40: V1524536 | E40: Vietnt@fih-foxconn.com | F40: 4478 | G40: Monitor 1 | H40: =vlookup(G40,'Bidding list 26'!$B$4:$G$270,6,0) -> DELL E2225HM, 21.5 inch HDMI cable, 3Yrs Wty | I40: 1980000 | J40: 3 | K40: =I40*J40 -> 5940000 | L40: PKK4 SVR line | M40: P26 Service line | N40: PKK4 | O40: FATP | P40: MP | Q40: 46127 | R40: =Q40-A40 -> 33 | S40: {=INDEX('G Project Timeline-OPM update'!$G$7:$L$35,MATCH(1,('G Project Timeline-OPM update'!$C$7:$C$35=N40)*('G Project Timeline-OPM update'!$B$7:$B$35=M40)*('G Project Timeline-OPM update'!$D$7:$D$35=O40),0),MATCH(P40,'G Project Timeline-OPM update'!$G$4:$L$4,0))-14} -> 46146 | T40: =S40-A40 -> 52 | U40: =IFERROR(VLOOKUP(G40,'Bidding list 26'!$B$2:$P$31,15,0),"") -> 50 | V40: =S40-U40 -> 46096 | W40: =A40+U40 -> 46144 | X40: =if(A40>V40,"Late", "On time") -> On time | Y40: New Buy | Z40: G | AA40: Done | AB40: FATP-SV-PKK4-MVA2603-44OM | AC40: Done | AD40: 1FSHQ40063 | AE40: Done | AF40: 1FSHQ40063 | AH40: 46141 | AI40: EPR2603240021 | AL40: =if(AA40="Done",$J40,0) -> 3 | AM40: =if(AC40="Done",$J40,0) -> 3 | AN40: =if(AE40="Done",$J40,0) -> 3 | AO40: =if(AH40<>"",$J40,0) -> 3
A41: 46094 | B41: GG-WH | C41: Nguyen Thi Viet | D41: V1524536 | E41: Vietnt@fih-foxconn.com | F41: 4478 | G41: IPC+(updated) | H41: =vlookup(G41,'Bidding list 26'!$B$4:$G$270,6,0) -> Pro Tower QCT1250, Ultra 5 235, Ram 16GB DDR5, SSD 512GB, Integrated graphics card, Power 180W, HDMI & DP Port, Keyboard and Mouse, 3Yrs Wty | I41: 18717000 | J41: 3 | K41: =I41*J41 -> 56151000 | L41: PKK4 SVR line | M41: P26 Service line | N41: PKK4 | O41: FATP | P41: MP | Q41: 46127 | R41: =Q41-A41 -> 33 | S41: {=INDEX('G Project Timeline-OPM update'!$G$7:$L$35,MATCH(1,('G Project Timeline-OPM update'!$C$7:$C$35=N41)*('G Project Timeline-OPM update'!$B$7:$B$35=M41)*('G Project Timeline-OPM update'!$D$7:$D$35=O41),0),MATCH(P41,'G Project Timeline-OPM update'!$G$4:$L$4,0))-14} -> 46146 | T41: =S41-A41 -> 52 | U41: =IFERROR(VLOOKUP(G41,'Bidding list 26'!$B$2:$P$31,15,0),"") -> 70 | V41: =S41-U41 -> 46076 | W41: =A41+U41 -> 46164 | X41: =if(A41>V41,"Late", "On time") -> Late | Y41: New Buy | Z41: G | AA41: Done | AB41: FATP-SV-PKK4-MVA2603-44OM | AC41: Done | AD41: 1FSHQ40062 | AE41: Done | AF41: 1FSHQ40062 | AH41: Đã nhận | AI41: EPR2603240022 | AL41: =if(AA41="Done",$J41,0) -> 3 | AM41: =if(AC41="Done",$J41,0) -> 3 | AN41: =if(AE41="Done",$J41,0) -> 3 | AO41: =if(AH41<>"",$J41,0) -> 3
A42: 46094 | B42: GG-WH | C42: Nguyen Thi Viet | D42: V1524536 | E42: Vietnt@fih-foxconn.com | F42: 4478 | G42: PDA CHAINWAY C61-4850 | H42: =vlookup(G42,'Bidding list 26'!$B$4:$G$270,6,0) -> C61-4850, Not including RFID module. Includes: 64GB 27-key Android 11, controller with battery, charging dock, charging adapter, glass screen protector | I42: 15500000 | J42: 1 | K42: =I42*J42 -> 15500000 | L42: PKK4 SVR line | M42: P26 Service line | N42: PKK4 | O42: FATP | P42: MP | Q42: 46127 | R42: =Q42-A42 -> 33 | S42: {=INDEX('G Project Timeline-OPM update'!$G$7:$L$35,MATCH(1,('G Project Timeline-OPM update'!$C$7:$C$35=N42)*('G Project Timeline-OPM update'!$B$7:$B$35=M42)*('G Project Timeline-OPM update'!$D$7:$D$35=O42),0),MATCH(P42,'G Project Timeline-OPM update'!$G$4:$L$4,0))-14} -> 46146 | T42: =S42-A42 -> 52 | U42: =IFERROR(VLOOKUP(G42,'Bidding list 26'!$B$2:$P$31,15,0),"") -> 65 | V42: =S42-U42 -> 46081 | W42: =A42+U42 -> 46159 | X42: =if(A42>V42,"Late", "On time") -> Late | Y42: New Buy | Z42: G | AA42: Done | AB42: FATP-SV-PKK4-MVA2603-44OM | AC42: Done | AD42: VNPR202603260203 | AE42: Done | AF42: VNPO202603310112 | AG42: =vlookup(AF42,Sheet9!A:D,4,0) | AH42: Đã nhận 25.04 | AI42: EPR2603240023 | AK42: đã out 20may tại vp OM - chị Việt | AL42: =if(AA42="Done",$J42,0) -> 1 | AM42: =if(AC42="Done",$J42,0) -> 1 | AN42: =if(AE42="Done",$J42,0) -> 1 | AO42: =if(AH42<>"",$J42,0) -> 1
A43: 46097 | B43: MFG | C43: Bui Thi Thanh Huong | D43: V1523147 | E43: huongbtt1@fih-foxconn.com | F43: 4327 | G43: Monitor 2 | H43: VA1903H-2, 19 inch, VGA cable + HDMI cable / Brand: VIEWSONIC | I43: 1240000 | J43: 33 | K43: =I43*J43 -> 40920000 | L43: 4CS4 Service | M43: P26 Service line | N43: 4CS4 | O43: FATP | P43: MP | Q43: 46127 | R43: =Q43-A43 -> 30 | S43: {=INDEX('G Project Timeline-OPM update'!$G$7:$L$35,MATCH(1,('G Project Timeline-OPM update'!$C$7:$C$35=N43)*('G Project Timeline-OPM update'!$B$7:$B$35=M43)*('G Project Timeline-OPM update'!$D$7:$D$35=O43),0),MATCH(P43,'G Project Timeline-OPM update'!$G$4:$L$4,0))-14} -> 46146 | T43: =S43-A43 -> 49 | U43: =IFERROR(VLOOKUP(G43,'Bidding list 26'!$B$2:$P$31,15,0),"") -> 50 | V43: =S43-U43 -> 46096 | W43: =A43+U43 -> 46147 | X43: =if(A43>V43,"Late", "On time") -> Late | Y43: New Buy | Z43: G | AA43: Done | AB43: FATP-SV-4CS4-MVA2603-36OM | AC43: Done | AD43: 1FSHQ40025 | AE43: Done | AF43: 1FSHQ40025 | AG43: pending | AH43: Lấy 33x / 93x 1FSHQ40123 P27 trả hàng trước | AI43: EPR2603240024 | AK43: Mới add | AL43: =if(AA43="Done",$J43,0) -> 33 | AM43: =if(AC43="Done",$J43,0) -> 33 | AN43: =if(AE43="Done",$J43,0) -> 33 | AO43: =if(AH43<>"",$J43,0) -> 33
A44: 46097 | B44: MFG | C44: Bui Thi Thanh Huong | D44: V1523147 | E44: huongbtt1@fih-foxconn.com | F44: 4327 | G44: Mini PC (Assy) | H44: LAMITOUCH LM-30 CPU:i3-6100, RAM 16GB DDR4 3200, SSD 256G, Slot: CAT61/HDMI1/VGA1/USB8 | I44: 7800000 | J44: 33 | K44: =I44*J44 -> 257400000 | L44: 4CS4 Service | M44: P26 Service line | N44: 4CS4 | O44: FATP | P44: MP | Q44: 46127 | R44: =Q44-A44 -> 30 | S44: {=INDEX('G Project Timeline-OPM update'!$G$7:$L$35,MATCH(1,('G Project Timeline-OPM update'!$C$7:$C$35=N44)*('G Project Timeline-OPM update'!$B$7:$B$35=M44)*('G Project Timeline-OPM update'!$D$7:$D$35=O44),0),MATCH(P44,'G Project Timeline-OPM update'!$G$4:$L$4,0))-14} -> 46146 | T44: =S44-A44 -> 49 | U44: =IFERROR(VLOOKUP(G44,'Bidding list 26'!$B$2:$P$31,15,0),"") | V44: =S44-U44 -> 46146 | W44: =A44+U44 -> 46097 | X44: =if(A44>V44,"Late", "On time") -> On time | Y44: New Buy | Z44: G | AA44: Done | AB44: FATP-SV-4CS4-MVA2603-36OM // FATP-MP-P26-MVA2605-38OM | AC44: Done | AD44: 1FSHQ40030 // 1FSHQ50347 | AE44: Done | AF44: 1FSHQ40030 ( Cancel PO ) // 1FSHQ50347 | AH44: Lấy 40x trong 100x MINI PC LAMITOUCH NON G / 81x trả đơn 15.06.2026 | AI44: EPR2603240025 (Cancel) // EPR2606110005 & EPR2606130001 | AL44: =if(AA44="Done",$J44,0) -> 33 | AM44: =if(AC44="Done",$J44,0) -> 33 | AN44: =if(AE44="Done",$J44,0) -> 33 | AO44: =if(AH44<>"",$J44,0) -> 33
A45: 46097 | B45: MFG | C45: Bui Thi Thanh Huong | D45: V1523147 | E45: huongbtt1@fih-foxconn.com | F45: 4327 | G45: Barcode Scanner SEUIC HS505DP, USB cable | H45: HS505DP, USB cable | I45: 2300000 | J45: 51 | K45: =I45*J45 -> 117300000 | L45: 4CS4 Service | M45: P26 Service line | N45: 4CS4 | O45: FATP | P45: MP | Q45: 46127 | R45: =Q45-A45 -> 30 | S45: {=INDEX('G Project Timeline-OPM update'!$G$7:$L$35,MATCH(1,('G Project Timeline-OPM update'!$C$7:$C$35=N45)*('G Project Timeline-OPM update'!$B$7:$B$35=M45)*('G Project Timeline-OPM update'!$D$7:$D$35=O45),0),MATCH(P45,'G Project Timeline-OPM update'!$G$4:$L$4,0))-14} -> 46146 | T45: =S45-A45 -> 49 | U45: =IFERROR(VLOOKUP(G45,'Bidding list 26'!$B$2:$P$31,15,0),"") -> 50 | V45: =S45-U45 -> 46096 | W45: =A45+U45 -> 46147 | X45: =if(A45>V45,"Late", "On time") -> Late | Y45: New Buy | Z45: G | AA45: Done | AB45: FATP-SV-4CS4-MVA2603-36OM | AC45: Done | AD45: VNPR202604030260 | AE45: Done | AF45: VNPO202604100259 | AG45: 46137 | AH45: 46137 | AI45: EPR2603210028 | AK45: Mới add | AL45: =if(AA45="Done",$J45,0) -> 51 | AM45: =if(AC45="Done",$J45,0) -> 51 | AN45: =if(AE45="Done",$J45,0) -> 51 | AO45: =if(AH45<>"",$J45,0) -> 51
A46: 46097 | B46: MFG | C46: Bui Thi Thanh Huong | D46: V1523147 | E46: huongbtt1@fih-foxconn.com | F46: 4327 | G46: Barcode Scanner SEUIC HS505HDP-2530 ,USB cable | H46: SEUIC HS505HDP-2530 ,USB cable | I46: 3300000 | J46: 9 | K46: =I46*J46 -> 29700000 | L46: 4CS4 Service | M46: P26 Service line | N46: 4CS4 | O46: FATP | P46: MP | Q46: 46127 | R46: =Q46-A46 -> 30 | S46: {=INDEX('G Project Timeline-OPM update'!$G$7:$L$35,MATCH(1,('G Project Timeline-OPM update'!$C$7:$C$35=N46)*('G Project Timeline-OPM update'!$B$7:$B$35=M46)*('G Project Timeline-OPM update'!$D$7:$D$35=O46),0),MATCH(P46,'G Project Timeline-OPM update'!$G$4:$L$4,0))-14} -> 46146 | T46: =S46-A46 -> 49 | U46: =IFERROR(VLOOKUP(G46,'Bidding list 26'!$B$2:$P$31,15,0),"") -> 50 | V46: =S46-U46 -> 46096 | W46: =A46+U46 -> 46147 | X46: =if(A46>V46,"Late", "On time") -> Late | Y46: New Buy | Z46: G | AA46: Done | AB46: FATP-SV-4CS4-MVA2603-36OM | AC46: Done | AD46: VNPR202604030260 | AE46: Done | AF46: VNPO202604100259 | AG46: 46149 | AH46: 46151 | AI46: EPR2603210029 / May 9, 8:20 AM | AK46: Mới add | AL46: =if(AA46="Done",$J46,0) -> 9 | AM46: =if(AC46="Done",$J46,0) -> 9 | AN46: =if(AE46="Done",$J46,0) -> 9 | AO46: =if(AH46<>"",$J46,0) -> 9
A47: 46097 | B47: MFG | C47: Bui Thi Thanh Huong | D47: V1523147 | E47: huongbtt1@fih-foxconn.com | F47: 4327 | G47: Barcode Printer ZEBRA | H47: ZT610, 600dpi | I47: 48800000 | J47: 14 | K47: =I47*J47 -> 683200000 | L47: 4CS4 Service | M47: P26 Service line | N47: 4CS4 | O47: FATP | P47: MP | Q47: 46127 | R47: =Q47-A47 -> 30 | S47: {=INDEX('G Project Timeline-OPM update'!$G$7:$L$35,MATCH(1,('G Project Timeline-OPM update'!$C$7:$C$35=N47)*('G Project Timeline-OPM update'!$B$7:$B$35=M47)*('G Project Timeline-OPM update'!$D$7:$D$35=O47),0),MATCH(P47,'G Project Timeline-OPM update'!$G$4:$L$4,0))-14} -> 46146 | T47: =S47-A47 -> 49 | U47: =IFERROR(VLOOKUP(G47,'Bidding list 26'!$B$2:$P$31,15,0),"") | V47: =S47-U47 -> 46146 | W47: =A47+U47 -> 46097 | X47: =if(A47>V47,"Late", "On time") -> On time | Y47: New Buy | Z47: G | AA47: Done | AB47: FATP-SV-4CS4-MVA2603-36OM | AC47: Done | AD47: 1FSHQ40031 | AE47: Done | AF47: 1FSHQ40031 | AG47: 46198 | AH47: 46200 | AI47: EPR2603240026 | AK47: Mới add | AL47: =if(AA47="Done",$J47,0) -> 14 | AM47: =if(AC47="Done",$J47,0) -> 14 | AN47: =if(AE47="Done",$J47,0) -> 14 | AO47: =if(AH47<>"",$J47,0) -> 14
A48: 46097 | B48: MFG | C48: Bui Thi Thanh Huong | D48: V1523147 | E48: huongbtt1@fih-foxconn.com | F48: 4327 | G48: Monitor 2 | H48: VA1903H-2, 19 inch, VGA cable + HDMI cable / Brand: VIEWSONIC | I48: 1240000 | J48: 40 | K48: =I48*J48 -> 49600000 | L48: CGY4 Service | M48: P26 Service line | N48: CGY4 | O48: FATP | P48: MP | Q48: 46127 | R48: =Q48-A48 -> 30 | S48: {=INDEX('G Project Timeline-OPM update'!$G$7:$L$35,MATCH(1,('G Project Timeline-OPM update'!$C$7:$C$35=N48)*('G Project Timeline-OPM update'!$B$7:$B$35=M48)*('G Project Timeline-OPM update'!$D$7:$D$35=O48),0),MATCH(P48,'G Project Timeline-OPM update'!$G$4:$L$4,0))-14} -> 46146 | T48: =S48-A48 -> 49 | U48: =IFERROR(VLOOKUP(G48,'Bidding list 26'!$B$2:$P$31,15,0),"") -> 50 | V48: =S48-U48 -> 46096 | W48: =A48+U48 -> 46147 | X48: =if(A48>V48,"Late", "On time") -> Late | Y48: New Buy | Z48: G | AA48: Done | AB48: FATP-SV-CGY4-MVA2603-37OM | AC48: Done | AD48: 1FSHQ40027 | AE48: Done | AF48: 1FSHQ40027 | AG48: pending | AH48: Lấy 40x / 93x 1FSHQ40123 P27 trả hàng trước | AI48: EPR2603240027 | AK48: Mới add | AL48: =if(AA48="Done",$J48,0) -> 40 | AM48: =if(AC48="Done",$J48,0) -> 40 | AN48: =if(AE48="Done",$J48,0) -> 40 | AO48: =if(AH48<>"",$J48,0) -> 40
A49: 46097 | B49: MFG | C49: Bui Thi Thanh Huong | D49: V1523147 | E49: huongbtt1@fih-foxconn.com | F49: 4327 | G49: Mini PC (Assy) | H49: LAMITOUCH LM-30 CPU:i3-6100, RAM 16GB DDR4 3200, SSD 256G, Slot: CAT61/HDMI1/VGA1/USB8 | I49: 7800000 | J49: 40 | K49: =I49*J49 -> 312000000 | L49: CGY4 Service | M49: P26 Service line | N49: CGY4 | O49: FATP | P49: MP | Q49: 46127 | R49: =Q49-A49 -> 30 | S49: {=INDEX('G Project Timeline-OPM update'!$G$7:$L$35,MATCH(1,('G Project Timeline-OPM update'!$C$7:$C$35=N49)*('G Project Timeline-OPM update'!$B$7:$B$35=M49)*('G Project Timeline-OPM update'!$D$7:$D$35=O49),0),MATCH(P49,'G Project Timeline-OPM update'!$G$4:$L$4,0))-14} -> 46146 | T49: =S49-A49 -> 49 | U49: =IFERROR(VLOOKUP(G49,'Bidding list 26'!$B$2:$P$31,15,0),"") | V49: =S49-U49 -> 46146 | W49: =A49+U49 -> 46097 | X49: =if(A49>V49,"Late", "On time") -> On time | Y49: New Buy | Z49: G | AA49: Done | AB49: FATP-SV-CGY4-MVA2603-37OM // FATP-MP-P26-MVA2605-38OM | AC49: Done | AD49: 1FSHQ40028 // 1FSHQ50347 | AE49: Done | AF49: 1FSHQ40028 ( Cancel PO ) // 1FSHQ50347 | AH49: Lấy 40x trong 100x MINI PC LAMITOUCH NON G | AI49: EPR2603240028 (Cancel) EPR2606110005 & EPR2606130001 | AL49: =if(AA49="Done",$J49,0) -> 40 | AM49: =if(AC49="Done",$J49,0) -> 40 | AN49: =if(AE49="Done",$J49,0) -> 40 | AO49: =if(AH49<>"",$J49,0) -> 40
A50: 46097 | B50: MFG | C50: Bui Thi Thanh Huong | D50: V1523147 | E50: huongbtt1@fih-foxconn.com | F50: 4327 | G50: Barcode Scanner SEUIC HS505DP, USB cable | H50: HS505DP, USB cable | I50: 2300000 | J50: 44 | K50: =I50*J50 -> 101200000 | L50: CGY4 Service | M50: P26 Service line | N50: CGY4 | O50: FATP | P50: MP | Q50: 46127 | R50: =Q50-A50 -> 30 | S50: {=INDEX('G Project Timeline-OPM update'!$G$7:$L$35,MATCH(1,('G Project Timeline-OPM update'!$C$7:$C$35=N50)*('G Project Timeline-OPM update'!$B$7:$B$35=M50)*('G Project Timeline-OPM update'!$D$7:$D$35=O50),0),MATCH(P50,'G Project Timeline-OPM update'!$G$4:$L$4,0))-14} -> 46146 | T50: =S50-A50 -> 49 | U50: =IFERROR(VLOOKUP(G50,'Bidding list 26'!$B$2:$P$31,15,0),"") -> 50 | V50: =S50-U50 -> 46096 | W50: =A50+U50 -> 46147 | X50: =if(A50>V50,"Late", "On time") -> Late | Y50: New Buy | Z50: G | AA50: Done | AB50: FATP-SV-CGY4-MVA2603-37OM | AC50: Done | AD50: VNPR202604030258 | AE50: Done | AF50: VNPO202604150301 | AG50: 46171 | AH50: 46172 | AI50: EPR2603210030 | AK50: Mới add | AL50: =if(AA50="Done",$J50,0) -> 44 | AM50: =if(AC50="Done",$J50,0) -> 44 | AN50: =if(AE50="Done",$J50,0) -> 44 | AO50: =if(AG50<>"",$J50,0) -> 44
A51: 46097 | B51: MFG | C51: Bui Thi Thanh Huong | D51: V1523147 | E51: huongbtt1@fih-foxconn.com | F51: 4327 | G51: Barcode Scanner SEUIC HS505HDP-2530 ,USB cable | H51: SEUIC HS505HDP-2530 ,USB cable | I51: 3300000 | J51: 6 | K51: =I51*J51 -> 19800000 | L51: CGY4 Service | M51: P26 Service line | N51: CGY4 | O51: FATP | P51: MP | Q51: 46127 | R51: =Q51-A51 -> 30 | S51: {=INDEX('G Project Timeline-OPM update'!$G$7:$L$35,MATCH(1,('G Project Timeline-OPM update'!$C$7:$C$35=N51)*('G Project Timeline-OPM update'!$B$7:$B$35=M51)*('G Project Timeline-OPM update'!$D$7:$D$35=O51),0),MATCH(P51,'G Project Timeline-OPM update'!$G$4:$L$4,0))-14} -> 46146 | T51: =S51-A51 -> 49 | U51: =IFERROR(VLOOKUP(G51,'Bidding list 26'!$B$2:$P$31,15,0),"") -> 50 | V51: =S51-U51 -> 46096 | W51: =A51+U51 -> 46147 | X51: =if(A51>V51,"Late", "On time") -> Late | Y51: New Buy | Z51: G | AA51: Done | AB51: FATP-SV-CGY4-MVA2603-37OM | AC51: Done | AD51: VNPR202604030258 | AE51: Done | AF51: VNPO202604150301 | AG51: 46167 | AI51: EPR2603210031 Đã trả đơn trước PO về | AK51: Lấy scanner ở PO: VNPO202604100231 trả đơn trước // anh Mạnh TE OR6 đồng ý | AL51: =if(AA51="Done",$J51,0) -> 6 | AM51: =if(AC51="Done",$J51,0) -> 6 | AN51: =if(AE51="Done",$J51,0) -> 6 | AO51: =if(AG51<>"",$J51,0) -> 6
A52: 46097 | B52: MFG | C52: Bui Thi Thanh Huong | D52: V1523147 | E52: huongbtt1@fih-foxconn.com | F52: 4327 | G52: Barcode Printer ZEBRA | H52: ZT610, 600dpi | I52: 48800000 | J52: 14 | K52: =I52*J52 -> 683200000 | L52: CGY4 Service | M52: P26 Service line | N52: CGY4 | O52: FATP | P52: MP | Q52: 46127 | R52: =Q52-A52 -> 30 | S52: {=INDEX('G Project Timeline-OPM update'!$G$7:$L$35,MATCH(1,('G Project Timeline-OPM update'!$C$7:$C$35=N52)*('G Project Timeline-OPM update'!$B$7:$B$35=M52)*('G Project Timeline-OPM update'!$D$7:$D$35=O52),0),MATCH(P52,'G Project Timeline-OPM update'!$G$4:$L$4,0))-14} -> 46146 | T52: =S52-A52 -> 49 | U52: =IFERROR(VLOOKUP(G52,'Bidding list 26'!$B$2:$P$31,15,0),"") | V52: =S52-U52 -> 46146 | W52: =A52+U52 -> 46097 | X52: =if(A52>V52,"Late", "On time") -> On time | Y52: New Buy | Z52: G | AA52: Done | AB52: FATP-SV-CGY4-MVA2603-37OM | AC52: Done | AD52: 1FSHQ40029 | AE52: Done | AF52: 1FSHQ40029 | AG52: 46164 | AH52: 46165 | AI52: EPR2603240029 | AK52: Mới add | AL52: =if(AA52="Done",$J52,0) -> 14 | AM52: =if(AC52="Done",$J52,0) -> 14 | AN52: =if(AE52="Done",$J52,0) -> 14 | AO52: =if(AH52<>"",$J52,0) -> 14
A53: 46097 | B53: MFG | C53: Bui Thi Thanh Huong | D53: V1523147 | E53: huongbtt1@fih-foxconn.com | F53: 4327 | G53: Monitor 2 | H53: VA1903H-2, 19 inch, VGA cable + HDMI cable / Brand: VIEWSONIC | I53: 1240000 | J53: 48 | K53: =I53*J53 -> 59520000 | L53: PKK4 Service | M53: P26 Service line | N53: PKK4 | O53: FATP | P53: MP | Q53: 46127 | R53: =Q53-A53 -> 30 | S53: {=INDEX('G Project Timeline-OPM update'!$G$7:$L$35,MATCH(1,('G Project Timeline-OPM update'!$C$7:$C$35=N53)*('G Project Timeline-OPM update'!$B$7:$B$35=M53)*('G Project Timeline-OPM update'!$D$7:$D$35=O53),0),MATCH(P53,'G Project Timeline-OPM update'!$G$4:$L$4,0))-14} -> 46146 | T53: =S53-A53 -> 49 | U53: =IFERROR(VLOOKUP(G53,'Bidding list 26'!$B$2:$P$31,15,0),"") -> 50 | V53: =S53-U53 -> 46096 | W53: =A53+U53 -> 46147 | X53: =if(A53>V53,"Late", "On time") -> Late | Y53: New Buy | Z53: G | AA53: Done | AB53: FATP-SV-PKK4-MVA2603-38OM | AC53: Done | AD53: 1FSHQ40032 | AE53: Done | AF53: 1FSHQ40032 | AG53: 46193 | AH53: Lấy 23x / 93x 1FSHQ40123 P27 trả hàng trước ; (48x-23x= 25x / 92x 1FSHQ40126 P27 trả hàng trước) | AI53: EPR2603240030 | AK53: Mới add | AL53: =if(AA53="Done",$J53,0) -> 48 | AM53: =if(AC53="Done",$J53,0) -> 48 | AN53: =if(AE53="Done",$J53,0) -> 48 | AO53: =if(AH53<>"",$J53,0) -> 48
A54: 46097 | B54: MFG | C54: Bui Thi Thanh Huong | D54: V1523147 | E54: huongbtt1@fih-foxconn.com | F54: 4327 | G54: Mini PC (Assy) | H54: LAMITOUCH LM-30 CPU:i3-6100, RAM 16GB DDR4 3200, SSD 256G, Slot: CAT61/HDMI1/VGA1/USB8 | I54: 7800000 | J54: 48 | K54: =I54*J54 -> 374400000 | L54: PKK4 Service | M54: P26 Service line | N54: PKK4 | O54: FATP | P54: MP | Q54: 46127 | R54: =Q54-A54 -> 30 | S54: {=INDEX('G Project Timeline-OPM update'!$G$7:$L$35,MATCH(1,('G Project Timeline-OPM update'!$C$7:$C$35=N54)*('G Project Timeline-OPM update'!$B$7:$B$35=M54)*('G Project Timeline-OPM update'!$D$7:$D$35=O54),0),MATCH(P54,'G Project Timeline-OPM update'!$G$4:$L$4,0))-14} -> 46146 | T54: =S54-A54 -> 49 | U54: =IFERROR(VLOOKUP(G54,'Bidding list 26'!$B$2:$P$31,15,0),"") | V54: =S54-U54 -> 46146 | W54: =A54+U54 -> 46097 | X54: =if(A54>V54,"Late", "On time") -> On time | Y54: New Buy | Z54: G | AA54: Done | AB54: FATP-SV-PKK4-MVA2603-38OM // FATP-MP-P26-MVA2605-38OM | AC54: Done | AD54: 1FSHQ40033 // 1FSHQ50347 | AE54: Done | AF54: 1FSHQ50347 | AH54: Lấy 40x trong 100x MINI PC LAMITOUCH NON G / 81x trả đơn 15.06.2026 | AI54: EPR2603240031 (Cancel) EPR2606110005 & EPR2606130001 | AJ54: tạm dừng khớp giá | AL54: =if(AA54="Done",$J54,0) -> 48 | AM54: =if(AC54="Done",$J54,0) -> 48 | AN54: =if(AE54="Done",$J54,0) -> 48 | AO54: =if(AH54<>"",$J54,0) -> 48
A55: 46097 | B55: MFG | C55: Bui Thi Thanh Huong | D55: V1523147 | E55: huongbtt1@fih-foxconn.com | F55: 4327 | G55: Barcode Scanner SEUIC HS505DP, USB cable | H55: HS505DP, USB cable | I55: 2300000 | J55: 49 | K55: =I55*J55 -> 112700000 | L55: PKK4 Service | M55: P26 Service line | N55: PKK4 | O55: FATP | P55: MP | Q55: 46127 | R55: =Q55-A55 -> 30 | S55: {=INDEX('G Project Timeline-OPM update'!$G$7:$L$35,MATCH(1,('G Project Timeline-OPM update'!$C$7:$C$35=N55)*('G Project Timeline-OPM update'!$B$7:$B$35=M55)*('G Project Timeline-OPM update'!$D$7:$D$35=O55),0),MATCH(P55,'G Project Timeline-OPM update'!$G$4:$L$4,0))-14} -> 46146 | T55: =S55-A55 -> 49 | U55: =IFERROR(VLOOKUP(G55,'Bidding list 26'!$B$2:$P$31,15,0),"") -> 50 | V55: =S55-U55 -> 46096 | W55: =A55+U55 -> 46147 | X55: =if(A55>V55,"Late", "On time") -> Late | Y55: New Buy | Z55: G | AA55: Done | AB55: FATP-SV-PKK4-MVA2603-38OM | AC55: Done | AD55: VNPR202604030289 | AE55: Done | AF55: VNPO202604150301 | AG55: 46171 | AH55: 46172 | AI55: EPR2603210032 | AK55: Mới add | AL55: =if(AA55="Done",$J55,0) -> 49 | AM55: =if(AC55="Done",$J55,0) -> 49 | AN55: =if(AE55="Done",$J55,0) -> 49 | AO55: =if(AG55<>"",$J55,0) -> 49
A56: 46097 | B56: MFG | C56: Bui Thi Thanh Huong | D56: V1523147 | E56: huongbtt1@fih-foxconn.com | F56: 4327 | G56: Barcode Scanner SEUIC HS505HDP-2530 ,USB cable | H56: SEUIC HS505HDP-2530 ,USB cable | I56: 3300000 | J56: 5 | K56: =I56*J56 -> 16500000 | L56: PKK4 Service | M56: P26 Service line | N56: PKK4 | O56: FATP | P56: MP | Q56: 46127 | R56: =Q56-A56 -> 30 | S56: {=INDEX('G Project Timeline-OPM update'!$G$7:$L$35,MATCH(1,('G Project Timeline-OPM update'!$C$7:$C$35=N56)*('G Project Timeline-OPM update'!$B$7:$B$35=M56)*('G Project Timeline-OPM update'!$D$7:$D$35=O56),0),MATCH(P56,'G Project Timeline-OPM update'!$G$4:$L$4,0))-14} -> 46146 | T56: =S56-A56 -> 49 | U56: =IFERROR(VLOOKUP(G56,'Bidding list 26'!$B$2:$P$31,15,0),"") -> 50 | V56: =S56-U56 -> 46096 | W56: =A56+U56 -> 46147 | X56: =if(A56>V56,"Late", "On time") -> Late | Y56: New Buy | Z56: G | AA56: Done | AB56: FATP-SV-PKK4-MVA2603-38OM | AC56: Done | AD56: VNPR202604030289 | AE56: Done | AF56: VNPO202604150301 | AG56: 46167 | AI56: EPR2603210033: Đã trả đơn trước PO về | AK56: Mới add | AL56: =if(AA56="Done",$J56,0) -> 5 | AM56: =if(AC56="Done",$J56,0) -> 5 | AN56: =if(AE56="Done",$J56,0) -> 5 | AO56: =if(AG56<>"",$J56,0) -> 5
A57: 46097 | B57: MFG | C57: Bui Thi Thanh Huong | D57: V1523147 | E57: huongbtt1@fih-foxconn.com | F57: 4327 | G57: Barcode Printer ZEBRA | H57: ZT610, 600dpi | I57: 48800000 | J57: 15 | K57: =I57*J57 -> 732000000 | L57: PKK4 Service | M57: P26 Service line | N57: PKK4 | O57: FATP | P57: MP | Q57: 46127 | R57: =Q57-A57 -> 30 | S57: {=INDEX('G Project Timeline-OPM update'!$G$7:$L$35,MATCH(1,('G Project Timeline-OPM update'!$C$7:$C$35=N57)*('G Project Timeline-OPM update'!$B$7:$B$35=M57)*('G Project Timeline-OPM update'!$D$7:$D$35=O57),0),MATCH(P57,'G Project Timeline-OPM update'!$G$4:$L$4,0))-14} -> 46146 | T57: =S57-A57 -> 49 | U57: =IFERROR(VLOOKUP(G57,'Bidding list 26'!$B$2:$P$31,15,0),"") | V57: =S57-U57 -> 46146 | W57: =A57+U57 -> 46097 | X57: =if(A57>V57,"Late", "On time") -> On time | Y57: New Buy | Z57: G | AA57: Done | AB57: FATP-SV-PKK4-MVA2603-38OM | AC57: Done | AD57: 1FSHQ40034 | AE57: Done | AF57: 1FSHQ40034 | AG57: 46198 | AH57: 46200 | AI57: EPR2603240032 | AL57: =if(AA57="Done",$J57,0) -> 15 | AM57: =if(AC57="Done",$J57,0) -> 15 | AN57: =if(AE57="Done",$J57,0) -> 15 | AO57: =if(AH57<>"",$J57,0) -> 15
A58: 46094 | B58: GG-WH | C58: Nguyen Thi Viet | D58: V1524536 | E58: Vietnt@fih-foxconn.com | F58: 4478 | G58: Barcode Scanner ZEBRA DS8178,USB cable | H58: =vlookup(G58,'Bidding list 26'!$B$4:$G$270,6,0) -> ZEBRA DS8178,USB cable PCS Wireless Scanner | I58: 5800000 | J58: 1 | K58: =I58*J58 -> 5800000 | L58: PKK4 SVR line | M58: P26 Service line | N58: PKK4 | O58: FATP | P58: MP | Q58: 46127 | R58: =Q58-A58 -> 33 | S58: {=INDEX('G Project Timeline-OPM update'!$G$7:$L$35,MATCH(1,('G Project Timeline-OPM update'!$C$7:$C$35=N58)*('G Project Timeline-OPM update'!$B$7:$B$35=M58)*('G Project Timeline-OPM update'!$D$7:$D$35=O58),0),MATCH(P58,'G Project Timeline-OPM update'!$G$4:$L$4,0))-14} -> 46146 | T58: =S58-A58 -> 52 | U58: =IFERROR(VLOOKUP(G58,'Bidding list 26'!$B$2:$P$31,15,0),"") -> 65 | V58: =S58-U58 -> 46081 | W58: =A58+U58 -> 46159 | X58: =if(A58>V58,"Late", "On time") -> Late | Y58: New Buy | Z58: G | AA58: Done | AB58: FATP-SV-PKK4-MVA2603-44OM | AC58: Done | AD58: VNPR202603260203 | AE58: Done | AF58: VNPO202603310112 | AG58: =vlookup(AF58,Sheet9!A:D,4,0) | AH58: Đã nhận 25.04 | AI58: EPR2603210027 | AL58: =if(AA58="Done",$J58,0) -> 1 | AM58: =if(AC58="Done",$J58,0) -> 1 | AN58: =if(AE58="Done",$J58,0) -> 1 | AO58: =if(AH58<>"",$J58,0) -> 1
A59: 46097 | B59: ENG1 | C59: Ngo Van Duong | D59: v1523845 | E59: Kelvin Duong STPM | F59: 4328 | G59: Monitor 2 | H59: =vlookup(G59,'Bidding list 26'!$B$4:$G$270,6,0) -> VA1903H-2, 19 inch, VGA cable + HDMI cable / Brand: VIEWSONIC | I59: 1240000 | J59: 1 | K59: =I59*J59 -> 1240000 | L59: NB for MP P26 | M59: P26 | N59: 4CS4 | O59: FATP | P59: MP | Q59: 46132 | R59: =Q59-A59 -> 35 | S59: {=INDEX('G Project Timeline-OPM update'!$G$7:$L$35,MATCH(1,('G Project Timeline-OPM update'!$C$7:$C$35=N59)*('G Project Timeline-OPM update'!$B$7:$B$35=M59)*('G Project Timeline-OPM update'!$D$7:$D$35=O59),0),MATCH(P59,'G Project Timeline-OPM update'!$G$4:$L$4,0))-14} -> 46135 | T59: =S59-A59 -> 38 | U59: =IFERROR(VLOOKUP(G59,'Bidding list 26'!$B$2:$P$31,15,0),"") -> 50 | V59: =S59-U59 -> 46085 | W59: =A59+U59 -> 46147 | X59: =if(A59>V59,"Late", "On time") -> Late | Y59: New Buy | Z59: G | AA59: Done | AB59: FATP-MP-4CS4-MVA2603-19OM | AC59: Done | AD59: 1FSHQ30273 | AE59: Done | AF59: 1FSHQ30273 | AG59: =vlookup(AF59,Sheet9!A:D,4,0) | AH59: 46154 | AI59: EPR2603210018 | AK59: Lấy OM stock trước / Mua bù sau | AL59: =if(AA59="Done",$J59,0) -> 1 | AM59: =if(AC59="Done",$J59,0) -> 1 | AN59: =if(AE59="Done",$J59,0) -> 1 | AO59: =if(AH59<>"",$J59,0) -> 1
A60: 46097 | B60: ENG1 | C60: Ngo Van Duong | D60: v1523845 | E60: Kelvin Duong STPM | F60: 4328 | G60: Monitor 2 | H60: =vlookup(G60,'Bidding list 26'!$B$4:$G$270,6,0) -> VA1903H-2, 19 inch, VGA cable + HDMI cable / Brand: VIEWSONIC | I60: 1240000 | J60: 1 | K60: =I60*J60 -> 1240000 | L60: NB for MP P26 | M60: P26 | N60: PKK4 | O60: FATP | P60: MP | Q60: 46132 | R60: =Q60-A60 -> 35 | S60: {=INDEX('G Project Timeline-OPM update'!$G$7:$L$35,MATCH(1,('G Project Timeline-OPM update'!$C$7:$C$35=N60)*('G Project Timeline-OPM update'!$B$7:$B$35=M60)*('G Project Timeline-OPM update'!$D$7:$D$35=O60),0),MATCH(P60,'G Project Timeline-OPM update'!$G$4:$L$4,0))-14} -> 46135 | T60: =S60-A60 -> 38 | U60: =IFERROR(VLOOKUP(G60,'Bidding list 26'!$B$2:$P$31,15,0),"") -> 50 | V60: =S60-U60 -> 46085 | W60: =A60+U60 -> 46147 | X60: =if(A60>V60,"Late", "On time") -> Late | Y60: New Buy | Z60: G | AA60: Done | AB60: FATP-MP-PKK4-MVA2603-20OM | AC60: Done | AD60: 1FSHQ30275 | AE60: Done | AF60: 1FSHQ30275 | AH60: Đã nhận 10.4 | AI60: EPR2603210019 | AK60: Lấy OM stock trước / Mua bù sau / 1FSHQ30275x: Đã nhận hàng | AL60: =if(AA60="Done",$J60,0) -> 1 | AM60: =if(AC60="Done",$J60,0) -> 1 | AN60: =if(AE60="Done",$J60,0) -> 1 | AO60: =if(AH60<>"",$J60,0) -> 1 | AQ60: =31+180+130 -> 341
A61: 46097 | B61: ENG1 | C61: Ngo Van Duong | D61: v1523845 | E61: Kelvin Duong STPM | F61: 4328 | G61: Monitor 2 | H61: =vlookup(G61,'Bidding list 26'!$B$4:$G$270,6,0) -> VA1903H-2, 19 inch, VGA cable + HDMI cable / Brand: VIEWSONIC | I61: 1240000 | J61: 1 | K61: =I61*J61 -> 1240000 | L61: NB for MP P26 | M61: P26 | N61: CGY4 | O61: FATP | P61: MP | Q61: 46132 | R61: =Q61-A61 -> 35 | S61: {=INDEX('G Project Timeline-OPM update'!$G$7:$L$35,MATCH(1,('G Project Timeline-OPM update'!$C$7:$C$35=N61)*('G Project Timeline-OPM update'!$B$7:$B$35=M61)*('G Project Timeline-OPM update'!$D$7:$D$35=O61),0),MATCH(P61,'G Project Timeline-OPM update'!$G$4:$L$4,0))-14} -> 46135 | T61: =S61-A61 -> 38 | U61: =IFERROR(VLOOKUP(G61,'Bidding list 26'!$B$2:$P$31,15,0),"") -> 50 | V61: =S61-U61 -> 46085 | W61: =A61+U61 -> 46147 | X61: =if(A61>V61,"Late", "On time") -> Late | Y61: New Buy | Z61: G | AA61: Done | AB61: FATP-MP-CGY4-MVA2603-21OM | AC61: Done | AD61: 1FSHQ30277 | AE61: Done | AF61: 1FSHQ30277 | AH61: Đã nhận 10.4 | AI61: EPR2603210021 | AK61: Lấy OM stock trước / Mua bù sau / 1FSHQ30277x: Đã nhận 1x | AL61: =if(AA61="Done",$J61,0) -> 1 | AM61: =if(AC61="Done",$J61,0) -> 1 | AN61: =if(AE61="Done",$J61,0) -> 1 | AO61: =if(AH61<>"",$J61,0) -> 1
A62: 46097 | B62: ENG1 | C62: Ngo Van Duong | D62: v1523845 | E62: Kelvin Duong STPM | F62: 4328 | G62: IPC(updated) | H62: =vlookup(G62,'Bidding list 26'!$B$4:$G$270,6,0) -> Pro Tower QCT1250, Core i3-14100, Ram 8GB DDR5, SSD 512GB, Integrated graphics card, Power 180W, HDMI & DP Port, Keyboard and Mouse, 3Yrs Wty | I62: 13888000 | J62: 1 | K62: =I62*J62 -> 13888000 | L62: NB for MP P26 | M62: P26 | N62: 4CS4 | O62: FATP | P62: MP | Q62: 46132 | R62: =Q62-A62 -> 35 | S62: {=INDEX('G Project Timeline-OPM update'!$G$7:$L$35,MATCH(1,('G Project Timeline-OPM update'!$C$7:$C$35=N62)*('G Project Timeline-OPM update'!$B$7:$B$35=M62)*('G Project Timeline-OPM update'!$D$7:$D$35=O62),0),MATCH(P62,'G Project Timeline-OPM update'!$G$4:$L$4,0))-14} -> 46135 | T62: =S62-A62 -> 38 | U62: =IFERROR(VLOOKUP(G62,'Bidding list 26'!$B$2:$P$31,15,0),"") -> 50 | V62: =S62-U62 -> 46085 | W62: =A62+U62 -> 46147 | X62: =if(A62>V62,"Late", "On time") -> Late | Y62: New Buy | Z62: G | AA62: Done | AB62: FATP-MP-4CS4-MVA2603-19OM | AC62: Done | AD62: 1FSHQ30274 | AE62: Done | AF62: 1FSHQ30274 | AH62: Đã nhận 09.4 | AI62: EPR2603210022 | AK62: Lấy OM stock trước / Mua bù sau / 1FSHQ30274x: Đã nhận được hàng | AL62: =if(AA62="Done",$J62,0) -> 1 | AM62: =if(AC62="Done",$J62,0) -> 1 | AN62: =if(AE62="Done",$J62,0) -> 1 | AO62: =if(AH62<>"",$J62,0) -> 1
A63: 46097 | B63: ENG1 | C63: Ngo Van Duong | D63: v1523845 | E63: Kelvin Duong STPM | F63: 4328 | G63: IPC(updated) | H63: =vlookup(G63,'Bidding list 26'!$B$4:$G$270,6,0) -> Pro Tower QCT1250, Core i3-14100, Ram 8GB DDR5, SSD 512GB, Integrated graphics card, Power 180W, HDMI & DP Port, Keyboard and Mouse, 3Yrs Wty | I63: 13888000 | J63: 1 | K63: =I63*J63 -> 13888000 | L63: NB for MP P26 | M63: P26 | N63: PKK4 | O63: FATP | P63: MP | Q63: 46132 | R63: =Q63-A63 -> 35 | S63: {=INDEX('G Project Timeline-OPM update'!$G$7:$L$35,MATCH(1,('G Project Timeline-OPM update'!$C$7:$C$35=N63)*('G Project Timeline-OPM update'!$B$7:$B$35=M63)*('G Project Timeline-OPM update'!$D$7:$D$35=O63),0),MATCH(P63,'G Project Timeline-OPM update'!$G$4:$L$4,0))-14} -> 46135 | T63: =S63-A63 -> 38 | U63: =IFERROR(VLOOKUP(G63,'Bidding list 26'!$B$2:$P$31,15,0),"") -> 50 | V63: =S63-U63 -> 46085 | W63: =A63+U63 -> 46147 | X63: =if(A63>V63,"Late", "On time") -> Late | Y63: New Buy | Z63: G | AA63: Done | AB63: FATP-MP-PKK4-MVA2603-20OM | AC63: Done | AD63: 1FSHQ30276 | AE63: Done | AF63: 1FSHQ30276 | AH63: Đã nhận 09.4 | AI63: EPR2603210024 | AK63: Lấy OM stock trước / Mua bù sau / 1FSHQ30276x: Đã nhận hàng | AL63: =if(AA63="Done",$J63,0) -> 1 | AM63: =if(AC63="Done",$J63,0) -> 1 | AN63: =if(AE63="Done",$J63,0) -> 1 | AO63: =if(AH63<>"",$J63,0) -> 1
A64: 46097 | B64: ENG1 | C64: Ngo Van Duong | D64: v1523845 | E64: Kelvin Duong STPM | F64: 4328 | G64: IPC(updated) | H64: =vlookup(G64,'Bidding list 26'!$B$4:$G$270,6,0) -> Pro Tower QCT1250, Core i3-14100, Ram 8GB DDR5, SSD 512GB, Integrated graphics card, Power 180W, HDMI & DP Port, Keyboard and Mouse, 3Yrs Wty | I64: 13888000 | J64: 1 | K64: =I64*J64 -> 13888000 | L64: NB for MP P26 | M64: P26 | N64: CGY4 | O64: FATP | P64: MP | Q64: 46132 | R64: =Q64-A64 -> 35 | S64: {=INDEX('G Project Timeline-OPM update'!$G$7:$L$35,MATCH(1,('G Project Timeline-OPM update'!$C$7:$C$35=N64)*('G Project Timeline-OPM update'!$B$7:$B$35=M64)*('G Project Timeline-OPM update'!$D$7:$D$35=O64),0),MATCH(P64,'G Project Timeline-OPM update'!$G$4:$L$4,0))-14} -> 46135 | T64: =S64-A64 -> 38 | U64: =IFERROR(VLOOKUP(G64,'Bidding list 26'!$B$2:$P$31,15,0),"") -> 50 | V64: =S64-U64 -> 46085 | W64: =A64+U64 -> 46147 | X64: =if(A64>V64,"Late", "On time") -> Late | Y64: New Buy | Z64: G | AA64: Done | AB64: FATP-MP-CGY4-MVA2603-21OM | AC64: Done | AD64: 1FSHQ30278 | AE64: Done | AF64: 1FSHQ30278 | AH64: Đã nhận 09.4 | AI64: EPR2603210026: Done | AK64: Lấy OM stock trước / Mua bù sau / 1FSHQ30278x: Đã nhận hàng | AL64: =if(AA64="Done",$J64,0) -> 1 | AM64: =if(AC64="Done",$J64,0) -> 1 | AN64: =if(AE64="Done",$J64,0) -> 1 | AO64: =if(AH64<>"",$J64,0) -> 1
A65: 46097 | B65: GG-PQE | C65: Phạm Thị Bích | D65: V1524485 | E65: Bich_Kate IPQC | F65: 3040 | G65: Monitor 2 | H65: =vlookup(G65,'Bidding list 26'!$B$4:$G$270,6,0) -> VA1903H-2, 19 inch, VGA cable + HDMI cable / Brand: VIEWSONIC | I65: 1240000 | J65: 21 | K65: =I65*J65 -> 26040000 | L65: Service MP 4CS4 | M65: P26 Service line | N65: 4CS4 | O65: FATP | P65: MP | Q65: 46132 | R65: =Q65-A65 -> 35 | S65: {=INDEX('G Project Timeline-OPM update'!$G$7:$L$35,MATCH(1,('G Project Timeline-OPM update'!$C$7:$C$35=N65)*('G Project Timeline-OPM update'!$B$7:$B$35=M65)*('G Project Timeline-OPM update'!$D$7:$D$35=O65),0),MATCH(P65,'G Project Timeline-OPM update'!$G$4:$L$4,0))-14} -> 46146 | T65: =S65-A65 -> 49 | U65: =IFERROR(VLOOKUP(G65,'Bidding list 26'!$B$2:$P$31,15,0),"") -> 50 | V65: =S65-U65 -> 46096 | W65: =A65+U65 -> 46147 | X65: =if(A65>V65,"Late", "On time") -> Late | Y65: New Buy | Z65: Q | AA65: Done | AB65: FATP-SV-4CS4-MVA2603-39OM | AC65: Done | AD65: 1FSHQ40064 | AE65: Done | AF65: 1FSHQ40064 | AG65: 46190 | AH65: 46193 | AI65: EPR2603240006 | AL65: =if(AA65="Done",$J65,0) -> 21 | AM65: =if(AC65="Done",$J65,0) -> 21 | AN65: =if(AE65="Done",$J65,0) -> 21 | AO65: =if(AH65<>"",$J65,0) -> 21
A66: 46097 | B66: GG-PQE | C66: Phạm Thị Bích | D66: V1524485 | E66: Bich_Kate IPQC | F66: 3040 | G66: Barcode Scanner SEUIC HS505HDP-2530 ,USB cable | H66: =vlookup(G66,'Bidding list 26'!$B$4:$G$270,6,0) -> SEUIC HS505HDP-2530 ,USB cable | I66: 3300000 | J66: 19 | K66: =I66*J66 -> 62700000 | L66: Service MP 4CS4 | M66: P26 Service line | N66: 4CS4 | O66: FATP | P66: MP | Q66: 46132 | R66: =Q66-A66 -> 35 | S66: {=INDEX('G Project Timeline-OPM update'!$G$7:$L$35,MATCH(1,('G Project Timeline-OPM update'!$C$7:$C$35=N66)*('G Project Timeline-OPM update'!$B$7:$B$35=M66)*('G Project Timeline-OPM update'!$D$7:$D$35=O66),0),MATCH(P66,'G Project Timeline-OPM update'!$G$4:$L$4,0))-14} -> 46146 | T66: =S66-A66 -> 49 | U66: =IFERROR(VLOOKUP(G66,'Bidding list 26'!$B$2:$P$31,15,0),"") -> 50 | V66: =S66-U66 -> 46096 | W66: =A66+U66 -> 46147 | X66: =if(A66>V66,"Late", "On time") -> Late | Y66: New Buy | Z66: Q | AA66: Done | AB66: FATP-SV-4CS4-MVA2603-39OM | AC66: Done | AD66: VNPR202604060057 | AE66: Done | AF66: VNPO202604150088 | AG66: 46193 | AH66: 46193 | AI66: EPR2603210036 | AL66: =if(AA66="Done",$J66,0) -> 19 | AM66: =if(AC66="Done",$J66,0) -> 19 | AN66: =if(AE66="Done",$J66,0) -> 19 | AO66: =if(AH66<>"",$J66,0) -> 19
A67: 46097 | B67: GG-PQE | C67: Phạm Thị Bích | D67: V1524485 | E67: Bich_Kate IPQC | F67: 3040 | G67: IPC(updated) | H67: =vlookup(G67,'Bidding list 26'!$B$4:$G$270,6,0) -> Pro Tower QCT1250, Core i3-14100, Ram 8GB DDR5, SSD 512GB, Integrated graphics card, Power 180W, HDMI & DP Port, Keyboard and Mouse, 3Yrs Wty | I67: 13888000 | J67: 21 | K67: =I67*J67 -> 291648000 | L67: Service MP 4CS4 | M67: P26 Service line | N67: 4CS4 | O67: FATP | P67: MP | Q67: 46132 | R67: =Q67-A67 -> 35 | S67: {=INDEX('G Project Timeline-OPM update'!$G$7:$L$35,MATCH(1,('G Project Timeline-OPM update'!$C$7:$C$35=N67)*('G Project Timeline-OPM update'!$B$7:$B$35=M67)*('G Project Timeline-OPM update'!$D$7:$D$35=O67),0),MATCH(P67,'G Project Timeline-OPM update'!$G$4:$L$4,0))-14} -> 46146 | T67: =S67-A67 -> 49 | U67: =IFERROR(VLOOKUP(G67,'Bidding list 26'!$B$2:$P$31,15,0),"") -> 50 | V67: =S67-U67 -> 46096 | X67: =if(A67>V67,"Late", "On time") -> Late | Y67: New Buy | Z67: Q | AA67: Done | AB67: FATP-SV-4CS4-MVA2603-39OM | AC67: Done | AD67: 1FSHQ40065 | AE67: Done | AF67: 1FSHQ40065 | AH67: Đã nhận 17.04 | AI67: EPR2603240004 | AK67: đã out | AL67: =if(AA67="Done",$J67,0) -> 21 | AM67: =if(AC67="Done",$J67,0) -> 21 | AN67: =if(AE67="Done",$J67,0) -> 21 | AO67: =if(AH67<>"",$J67,0) -> 21
A68: 46097 | B68: GG-PQE | C68: Phạm Thị Bích | D68: V1524485 | E68: Bich_Kate IPQC | F68: 3040 | G68: Monitor 2 | H68: =vlookup(G68,'Bidding list 26'!$B$4:$G$270,6,0) -> VA1903H-2, 19 inch, VGA cable + HDMI cable / Brand: VIEWSONIC | I68: 1240000 | J68: 21 | K68: =I68*J68 -> 26040000 | L68: Service MP CGY4 | M68: P26 Service line | N68: CGY4 | O68: FATP | P68: MP | Q68: 46132 | R68: =Q68-A68 -> 35 | S68: {=INDEX('G Project Timeline-OPM update'!$G$7:$L$35,MATCH(1,('G Project Timeline-OPM update'!$C$7:$C$35=N68)*('G Project Timeline-OPM update'!$B$7:$B$35=M68)*('G Project Timeline-OPM update'!$D$7:$D$35=O68),0),MATCH(P68,'G Project Timeline-OPM update'!$G$4:$L$4,0))-14} -> 46146 | T68: =S68-A68 -> 49 | U68: =IFERROR(VLOOKUP(G68,'Bidding list 26'!$B$2:$P$31,15,0),"") -> 50 | V68: =S68-U68 -> 46096 | W68: =A68+U68 -> 46147 | X68: =if(A68>V68,"Late", "On time") -> Late | Y68: New Buy | Z68: Q | AA68: Done | AB68: FATP-SV-CGY4-MVA2603-40OM | AC68: Done | AD68: 1FSHQ40066 | AE68: Done | AF68: 1FSHQ40066 | AG68: =vlookup(AF68,Sheet9!A:D,4,0) | AH68: 46154 | AI68: EPR2603240005 | AK68: đã out | AL68: =if(AA68="Done",$J68,0) -> 21 | AM68: =if(AC68="Done",$J68,0) -> 21 | AN68: =if(AE68="Done",$J68,0) -> 21 | AO68: =if(AH68<>"",$J68,0) -> 21
A69: 46097 | B69: GG-PQE | C69: Phạm Thị Bích | D69: V1524485 | E69: Bich_Kate IPQC | F69: 3040 | G69: Barcode Scanner SEUIC HS505HDP-2530 ,USB cable | H69: =vlookup(G69,'Bidding list 26'!$B$4:$G$270,6,0) -> SEUIC HS505HDP-2530 ,USB cable | I69: 3300000 | J69: 19 | K69: =I69*J69 -> 62700000 | L69: Service MP CGY4 | M69: P26 Service line | N69: CGY4 | O69: FATP | P69: MP | Q69: 46132 | R69: =Q69-A69 -> 35 | S69: {=INDEX('G Project Timeline-OPM update'!$G$7:$L$35,MATCH(1,('G Project Timeline-OPM update'!$C$7:$C$35=N69)*('G Project Timeline-OPM update'!$B$7:$B$35=M69)*('G Project Timeline-OPM update'!$D$7:$D$35=O69),0),MATCH(P69,'G Project Timeline-OPM update'!$G$4:$L$4,0))-14} -> 46146 | T69: =S69-A69 -> 49 | U69: =IFERROR(VLOOKUP(G69,'Bidding list 26'!$B$2:$P$31,15,0),"") -> 50 | V69: =S69-U69 -> 46096 | W69: =A69+U69 -> 46147 | X69: =if(A69>V69,"Late", "On time") -> Late | Y69: New Buy | Z69: Q | AA69: Done | AB69: FATP-SV-CGY4-MVA2603-40OM | AC69: Done | AD69: VNPR202604060058 | AE69: Done | AF69: VNPO202604150088 | AG69: 46193 | AH69: 46193 | AI69: EPR2603210037 | AL69: =if(AA69="Done",$J69,0) -> 19 | AM69: =if(AC69="Done",$J69,0) -> 19 | AN69: =if(AE69="Done",$J69,0) -> 19 | AO69: =if(AH69<>"",$J69,0) -> 19
A70: 46097 | B70: GG-PQE | C70: Phạm Thị Bích | D70: V1524485 | E70: Bich_Kate IPQC | F70: 3040 | G70: IPC(updated) | H70: =vlookup(G70,'Bidding list 26'!$B$4:$G$270,6,0) -> Pro Tower QCT1250, Core i3-14100, Ram 8GB DDR5, SSD 512GB, Integrated graphics card, Power 180W, HDMI & DP Port, Keyboard and Mouse, 3Yrs Wty | I70: 13888000 | J70: 21 | K70: =I70*J70 -> 291648000 | L70: Service MP CGY4 | M70: P26 Service line | N70: CGY4 | O70: FATP | P70: MP | Q70: 46132 | R70: =Q70-A70 -> 35 | S70: {=INDEX('G Project Timeline-OPM update'!$G$7:$L$35,MATCH(1,('G Project Timeline-OPM update'!$C$7:$C$35=N70)*('G Project Timeline-OPM update'!$B$7:$B$35=M70)*('G Project Timeline-OPM update'!$D$7:$D$35=O70),0),MATCH(P70,'G Project Timeline-OPM update'!$G$4:$L$4,0))-14} -> 46146 | T70: =S70-A70 -> 49 | U70: =IFERROR(VLOOKUP(G70,'Bidding list 26'!$B$2:$P$31,15,0),"") -> 50 | V70: =S70-U70 -> 46096 | X70: =if(A70>V70,"Late", "On time") -> Late | Y70: New Buy | Z70: Q | AA70: Done | AB70: FATP-SV-CGY4-MVA2603-40OM | AC70: Done | AD70: 1FSHQ40067 | AE70: Done | AF70: 1FSHQ40067 | AH70: Đã nhận 17.04 | AI70: EPR2603240001 | AK70: đã out | AL70: =if(AA70="Done",$J70,0) -> 21 | AM70: =if(AC70="Done",$J70,0) -> 21 | AN70: =if(AE70="Done",$J70,0) -> 21 | AO70: =if(AH70<>"",$J70,0) -> 21
A71: 46097 | B71: GG-PQE | C71: Phạm Thị Bích | D71: V1524485 | E71: Bich_Kate IPQC | F71: 3040 | G71: Monitor 2 | H71: =vlookup(G71,'Bidding list 26'!$B$4:$G$270,6,0) -> VA1903H-2, 19 inch, VGA cable + HDMI cable / Brand: VIEWSONIC | I71: 1240000 | J71: 21 | K71: =I71*J71 -> 26040000 | L71: Service MP PKK4 | M71: P26 Service line | N71: PKK4 | O71: FATP | P71: MP | Q71: 46132 | R71: =Q71-A71 -> 35 | S71: {=INDEX('G Project Timeline-OPM update'!$G$7:$L$35,MATCH(1,('G Project Timeline-OPM update'!$C$7:$C$35=N71)*('G Project Timeline-OPM update'!$B$7:$B$35=M71)*('G Project Timeline-OPM update'!$D$7:$D$35=O71),0),MATCH(P71,'G Project Timeline-OPM update'!$G$4:$L$4,0))-14} -> 46146 | T71: =S71-A71 -> 49 | U71: =IFERROR(VLOOKUP(G71,'Bidding list 26'!$B$2:$P$31,15,0),"") -> 50 | V71: =S71-U71 -> 46096 | W71: =A71+U71 -> 46147 | X71: =if(A71>V71,"Late", "On time") -> Late | Y71: New Buy | Z71: Q | AA71: Done | AB71: FATP-SV-PKK4-MVA2603-41OM | AC71: Done | AD71: 1FSHQ40069 | AE71: Done | AF71: 1FSHQ40069 | AG71: 46190 | AH71: 46193 | AI71: EPR2603240002 | AL71: =if(AA71="Done",$J71,0) -> 21 | AM71: =if(AC71="Done",$J71,0) -> 21 | AN71: =if(AE71="Done",$J71,0) -> 21 | AO71: =if(AH71<>"",$J71,0) -> 21
A72: 46097 | B72: GG-PQE | C72: Phạm Thị Bích | D72: V1524485 | E72: Bich_Kate IPQC | F72: 3040 | G72: Barcode Scanner SEUIC HS505HDP-2530 ,USB cable | H72: =vlookup(G72,'Bidding list 26'!$B$4:$G$270,6,0) -> SEUIC HS505HDP-2530 ,USB cable | I72: 3300000 | J72: 20 | K72: =I72*J72 -> 66000000 | L72: Service MP PKK4 | M72: P26 Service line | N72: PKK4 | O72: FATP | P72: MP | Q72: 46132 | R72: =Q72-A72 -> 35 | S72: {=INDEX('G Project Timeline-OPM update'!$G$7:$L$35,MATCH(1,('G Project Timeline-OPM update'!$C$7:$C$35=N72)*('G Project Timeline-OPM update'!$B$7:$B$35=M72)*('G Project Timeline-OPM update'!$D$7:$D$35=O72),0),MATCH(P72,'G Project Timeline-OPM update'!$G$4:$L$4,0))-14} -> 46146 | T72: =S72-A72 -> 49 | U72: =IFERROR(VLOOKUP(G72,'Bidding list 26'!$B$2:$P$31,15,0),"") -> 50 | V72: =S72-U72 -> 46096 | W72: =A72+U72 -> 46147 | X72: =if(A72>V72,"Late", "On time") -> Late | Y72: New Buy | Z72: Q | AA72: Done | AB72: FATP-SV-PKK4-MVA2603-41OM | AC72: Done | AD72: VNPR202604060063 | AE72: Done | AF72: VNPO202604150088 | AG72: 46193 | AH72: 46193 | AI72: EPR2603210038 | AL72: =if(AA72="Done",$J72,0) -> 20 | AM72: =if(AC72="Done",$J72,0) -> 20 | AN72: =if(AE72="Done",$J72,0) -> 20 | AO72: =if(AH72<>"",$J72,0) -> 20
A73: 46097 | B73: GG-PQE | C73: Phạm Thị Bích | D73: V1524485 | E73: Bich_Kate IPQC | F73: 3040 | G73: IPC(updated) | H73: =vlookup(G73,'Bidding list 26'!$B$4:$G$270,6,0) -> Pro Tower QCT1250, Core i3-14100, Ram 8GB DDR5, SSD 512GB, Integrated graphics card, Power 180W, HDMI & DP Port, Keyboard and Mouse, 3Yrs Wty | I73: 13888000 | J73: 21 | K73: =I73*J73 -> 291648000 | L73: Service MP PKK4 | M73: P26 Service line | N73: PKK4 | O73: FATP | P73: MP | Q73: 46132 | R73: =Q73-A73 -> 35 | S73: {=INDEX('G Project Timeline-OPM update'!$G$7:$L$35,MATCH(1,('G Project Timeline-OPM update'!$C$7:$C$35=N73)*('G Project Timeline-OPM update'!$B$7:$B$35=M73)*('G Project Timeline-OPM update'!$D$7:$D$35=O73),0),MATCH(P73,'G Project Timeline-OPM update'!$G$4:$L$4,0))-14} -> 46146 | T73: =S73-A73 -> 49 | U73: =IFERROR(VLOOKUP(G73,'Bidding list 26'!$B$2:$P$31,15,0),"") -> 50 | V73: =S73-U73 -> 46096 | X73: =if(A73>V73,"Late", "On time") -> Late | Y73: New Buy | Z73: Q | AA73: Done | AB73: FATP-SV-PKK4-MVA2603-41OM | AC73: Done | AD73: 1FSHQ40070 | AE73: Done | AF73: 1FSHQ40070 | AH73: Đã nhận 17.04 | AI73: EPR2603240003 | AK73: đã out | AL73: =if(AA73="Done",$J73,0) -> 21 | AM73: =if(AC73="Done",$J73,0) -> 21 | AN73: =if(AE73="Done",$J73,0) -> 21 | AO73: =if(AH73<>"",$J73,0) -> 21
A74: 46098 | B74: TE | C74: Nguyen Ngoc Huyen | D74: V1549412 | E74: Nguyen Ngoc Huyen (Evelyn) | F74: 4440 | G74: Mini PC ASUS NUC 14 Essential NUC14MNK150 (TE P26 MP ONLY) | H74: =vlookup(G74,'Bidding list 26'!$B$4:$G$270,6,0) -> #N/A | I74: 9680000 | J74: 26 | K74: =I74*J74 -> 251680000 | L74: P26 SMT MP 4CS4 | M74: P26 | N74: 4CS4 | O74: SMT | P74: MP | Q74: 46132 | R74: =Q74-A74 -> 34 | S74: {=INDEX('G Project Timeline-OPM update'!$G$7:$L$35,MATCH(1,('G Project Timeline-OPM update'!$C$7:$C$35=N74)*('G Project Timeline-OPM update'!$B$7:$B$35=M74)*('G Project Timeline-OPM update'!$D$7:$D$35=O74),0),MATCH(P74,'G Project Timeline-OPM update'!$G$4:$L$4,0))-14} -> 46135 | T74: =S74-A74 -> 37 | U74: =IFERROR(VLOOKUP(G74,'Bidding list 26'!$B$2:$P$31,15,0),"") | V74: =S74-U74 -> 46135 | W74: =A74+U74 -> 46098 | X74: =if(A74>V74,"Late", "On time") -> On time | Y74: New Buy | AA74: Done | AB74: SMT-MP-4CS4-MVA2603-34OM | AC74: Done | AD74: 1FSHQ30271 | AE74: Done | AF74: 1FSHQ30271 | AH74: Đã nhận 16.4 | AI74: EPR2603240038 | AL74: =if(AA74="Done",$J74,0) -> 26 | AM74: =if(AC74="Done",$J74,0) -> 26 | AN74: =if(AE74="Done",$J74,0) -> 26 | AO74: =if(AH74<>"",$J74,0) -> 26
A75: 46098 | B75: TE | C75: Nguyen Ngoc Huyen | D75: V1549412 | E75: Nguyen Ngoc Huyen (Evelyn) | F75: 4440 | G75: Mini PC ASUS NUC 14 Essential NUC14MNK150 (TE P26 MP ONLY) | H75: =vlookup(G75,'Bidding list 26'!$B$4:$G$270,6,0) -> #N/A | I75: 9680000 | J75: 22 | K75: =I75*J75 -> 212960000 | L75: P26 SMT MP CGY4 | M75: P26 | N75: CGY4 | O75: SMT | P75: MP | Q75: 46132 | R75: =Q75-A75 -> 34 | S75: {=INDEX('G Project Timeline-OPM update'!$G$7:$L$35,MATCH(1,('G Project Timeline-OPM update'!$C$7:$C$35=N75)*('G Project Timeline-OPM update'!$B$7:$B$35=M75)*('G Project Timeline-OPM update'!$D$7:$D$35=O75),0),MATCH(P75,'G Project Timeline-OPM update'!$G$4:$L$4,0))-14} -> 46135 | T75: =S75-A75 -> 37 | U75: =IFERROR(VLOOKUP(G75,'Bidding list 26'!$B$2:$P$31,15,0),"") | V75: =S75-U75 -> 46135 | W75: =A75+U75 -> 46098 | X75: =if(A75>V75,"Late", "On time") -> On time | Y75: New Buy | AA75: Done | AB75: SMT-MP-CGY4-MVA2603-35OM | AC75: Done | AD75: 1FSHQ30272 | AE75: Done | AF75: 1FSHQ30272 | AH75: Đã nhận 16.4 | AI75: EPR2603240039 | AL75: =if(AA75="Done",$J75,0) -> 22 | AM75: =if(AC75="Done",$J75,0) -> 22 | AN75: =if(AE75="Done",$J75,0) -> 22 | AO75: =if(AH75<>"",$J75,0) -> 22
A76: 46099 | B76: TE | C76: Nguyen Ngoc Huyen | D76: V1549412 | E76: Nguyen Ngoc Huyen (Evelyn) | F76: 4440 | G76: Mini PC ASUS NUC 14 Essential NUC14MNK150 (TE P26 MP ONLY) | H76: =vlookup(G76,'Bidding list 26'!$B$4:$G$270,6,0) -> #N/A | I76: 9680000 | J76: 1 | K76: =I76*J76 -> 9680000 | L76: P26 FATP MP 4CS4 | M76: P26 | N76: 4CS4 | O76: FATP | P76: MP | Q76: 46132 | R76: =Q76-A76 -> 33 | S76: {=INDEX('G Project Timeline-OPM update'!$G$7:$L$35,MATCH(1,('G Project Timeline-OPM update'!$C$7:$C$35=N76)*('G Project Timeline-OPM update'!$B$7:$B$35=M76)*('G Project Timeline-OPM update'!$D$7:$D$35=O76),0),MATCH(P76,'G Project Timeline-OPM update'!$G$4:$L$4,0))-14} -> 46135 | T76: =S76-A76 -> 36 | U76: =IFERROR(VLOOKUP(G76,'Bidding list 26'!$B$2:$P$31,15,0),"") | V76: =S76-U76 -> 46135 | W76: =A76+U76 -> 46099 | X76: =if(A76>V76,"Late", "On time") -> On time | Y76: New Buy | Z76: G | AA76: Done | AB76: FATP-MP-4CS4-MVA2603-48OM | AC76: Done | AD76: 1FSHQ30252 | AE76: Done | AF76: 1FSHQ30252 | AH76: Đã nhận 16.4 | AI76: EPR2603240040 | AL76: =if(AA76="Done",$J76,0) -> 1 | AM76: =if(AC76="Done",$J76,0) -> 1 | AN76: =if(AE76="Done",$J76,0) -> 1 | AO76: =if(AH76<>"",$J76,0) -> 1
A77: 46099 | B77: TE | C77: Nguyen Ngoc Huyen | D77: V1549412 | E77: Nguyen Ngoc Huyen (Evelyn) | F77: 4440 | G77: Mini PC ASUS NUC 14 Essential NUC14MNK150 (TE P26 MP ONLY) | H77: =vlookup(G77,'Bidding list 26'!$B$4:$G$270,6,0) -> #N/A | I77: 9680000 | J77: 1 | K77: =I77*J77 -> 9680000 | L77: P26 FATP MP CGY4 | M77: P26 | N77: CGY4 | O77: FATP | P77: MP | Q77: 46132 | R77: =Q77-A77 -> 33 | S77: {=INDEX('G Project Timeline-OPM update'!$G$7:$L$35,MATCH(1,('G Project Timeline-OPM update'!$C$7:$C$35=N77)*('G Project Timeline-OPM update'!$B$7:$B$35=M77)*('G Project Timeline-OPM update'!$D$7:$D$35=O77),0),MATCH(P77,'G Project Timeline-OPM update'!$G$4:$L$4,0))-14} -> 46135 | T77: =S77-A77 -> 36 | U77: =IFERROR(VLOOKUP(G77,'Bidding list 26'!$B$2:$P$31,15,0),"") | V77: =S77-U77 -> 46135 | W77: =A77+U77 -> 46099 | X77: =if(A77>V77,"Late", "On time") -> On time | Y77: New Buy | Z77: G | AA77: Done | AB77: FATP-MP-CGY4-MVA2603-49OM | AC77: Done | AD77: 1FSHQ30254 | AE77: Done | AF77: 1FSHQ30254 | AH77: Đã nhận 16.4 | AI77: EPR2603240041 | AL77: =if(AA77="Done",$J77,0) -> 1 | AM77: =if(AC77="Done",$J77,0) -> 1 | AN77: =if(AE77="Done",$J77,0) -> 1 | AO77: =if(AH77<>"",$J77,0) -> 1
A78: 46106 | B78: ENG2 | C78: Đỗ Thị Xuân | D78: V1536196 | E78: xuandt99@fih-foxconn.com | F78: 4347 | G78: Monitor 2 | H78: =vlookup(G78,'Bidding list 26'!$B$4:$G$270,6,0) -> VA1903H-2, 19 inch, VGA cable + HDMI cable / Brand: VIEWSONIC | I78: 1240000 | J78: 1 | K78: =I78*J78 -> 1240000 | L78: P26 FATP MP 4CS4 Service line | M78: P26 Service line | N78: 4CS4 | O78: FATP | P78: MP | Q78: 46132 | R78: =Q78-A78 -> 26 | S78: {=INDEX('G Project Timeline-OPM update'!$G$7:$L$35,MATCH(1,('G Project Timeline-OPM update'!$C$7:$C$35=N78)*('G Project Timeline-OPM update'!$B$7:$B$35=M78)*('G Project Timeline-OPM update'!$D$7:$D$35=O78),0),MATCH(P78,'G Project Timeline-OPM update'!$G$4:$L$4,0))-14} -> 46146 | T78: =S78-A78 -> 40 | U78: =IFERROR(VLOOKUP(G78,'Bidding list 26'!$B$2:$P$31,15,0),"") -> 50 | V78: =S78-U78 -> 46096 | W78: =A78+U78 -> 46156 | X78: =if(A78>V78,"Late", "On time") -> Late | Y78: New Buy | Z78: G | AA78: Done | AB78: FATP-SV-4CS4-MVA2603-56OM | AC78: Done | AD78: 1FSHQ40047 | AE78: Done | AF78: 1FSHQ40047 | AH78: =vlookup(AF78,Sheet9!A:D,3,0) | AI78: EPR2603280003 | AL78: =if(AA78="Done",$J78,0) -> 1 | AM78: =if(AC78="Done",$J78,0) -> 1 | AN78: =if(AE78="Done",$J78,0) -> 1 | AO78: =if(AH78<>"",$J78,0) -> 0
A79: 46106 | B79: ENG2 | C79: Đỗ Thị Xuân | D79: V1536196 | E79: xuandt99@fih-foxconn.com | F79: 4347 | G79: Mini PC (Assy) | H79: =vlookup(G79,'Bidding list 26'!$B$4:$G$270,6,0) -> #N/A | I79: 7800000 | J79: 1 | K79: =I79*J79 -> 7800000 | L79: P26 FATP MP 4CS4 Service line | M79: P26 Service line | N79: 4CS4 | O79: FATP | P79: MP | Q79: 46132 | R79: =Q79-A79 -> 26 | S79: {=INDEX('G Project Timeline-OPM update'!$G$7:$L$35,MATCH(1,('G Project Timeline-OPM update'!$C$7:$C$35=N79)*('G Project Timeline-OPM update'!$B$7:$B$35=M79)*('G Project Timeline-OPM update'!$D$7:$D$35=O79),0),MATCH(P79,'G Project Timeline-OPM update'!$G$4:$L$4,0))-14} -> 46146 | T79: =S79-A79 -> 40 | U79: =IFERROR(VLOOKUP(G79,'Bidding list 26'!$B$2:$P$31,15,0),"") | V79: =S79-U79 -> 46146 | W79: =A79+U79 -> 46106 | X79: =if(A79>V79,"Late", "On time") -> On time | Y79: New Buy | Z79: G | AA79: Done | AB79: FATP-SV-4CS4-MVA2603-56OM | AC79: Done | AD79: 1FSHQ40048 | AE79: Pending | AI79: EPR2603280004 (cancel) | AK79: Bác L bảo bỏ qua tạm thời | AL79: =if(AA79="Done",$J79,0) -> 1 | AM79: =if(AC79="Done",$J79,0) -> 1 | AN79: =if(AE79="Done",$J79,0) -> 0 | AO79: =if(AH79<>"",$J79,0) -> 0
A80: 46106 | B80: ENG2 | C80: Đỗ Thị Xuân | D80: V1536196 | E80: xuandt99@fih-foxconn.com | F80: 4347 | G80: Monitor 2 | H80: =vlookup(G80,'Bidding list 26'!$B$4:$G$270,6,0) -> VA1903H-2, 19 inch, VGA cable + HDMI cable / Brand: VIEWSONIC | I80: 1240000 | J80: 1 | K80: =I80*J80 -> 1240000 | L80: P26 FATP MP CGY4Service line | M80: P26 Service line | N80: CGY4 | O80: FATP | P80: MP | Q80: 46132 | R80: =Q80-A80 -> 26 | S80: {=INDEX('G Project Timeline-OPM update'!$G$7:$L$35,MATCH(1,('G Project Timeline-OPM update'!$C$7:$C$35=N80)*('G Project Timeline-OPM update'!$B$7:$B$35=M80)*('G Project Timeline-OPM update'!$D$7:$D$35=O80),0),MATCH(P80,'G Project Timeline-OPM update'!$G$4:$L$4,0))-14} -> 46146 | T80: =S80-A80 -> 40 | U80: =IFERROR(VLOOKUP(G80,'Bidding list 26'!$B$2:$P$31,15,0),"") -> 50 | V80: =S80-U80 -> 46096 | W80: =A80+U80 -> 46156 | X80: =if(A80>V80,"Late", "On time") -> Late | Y80: New Buy | Z80: G | AA80: Done | AB80: FATP-SV-CGY4-MVA2603-57OM | AC80: Done | AD80: 1FSHQ40049 | AE80: Done | AF80: 1FSHQ40049 | AH80: =vlookup(AF80,Sheet9!A:D,3,0) | AI80: EPR2603280005 | AL80: =if(AA80="Done",$J80,0) -> 1 | AM80: =if(AC80="Done",$J80,0) -> 1 | AN80: =if(AE80="Done",$J80,0) -> 1 | AO80: =if(AH80<>"",$J80,0) -> 0
A81: 46106 | B81: ENG2 | C81: Đỗ Thị Xuân | D81: V1536196 | E81: xuandt99@fih-foxconn.com | F81: 4347 | G81: Mini PC (Assy) | H81: =vlookup(G81,'Bidding list 26'!$B$4:$G$270,6,0) -> #N/A | I81: 7800000 | J81: 1 | K81: =I81*J81 -> 7800000 | L81: P26 FATP MP CGY4Service line | M81: P26 Service line | N81: CGY4 | O81: FATP | P81: MP | Q81: 46132 | R81: =Q81-A81 -> 26 | S81: {=INDEX('G Project Timeline-OPM update'!$G$7:$L$35,MATCH(1,('G Project Timeline-OPM update'!$C$7:$C$35=N81)*('G Project Timeline-OPM update'!$B$7:$B$35=M81)*('G Project Timeline-OPM update'!$D$7:$D$35=O81),0),MATCH(P81,'G Project Timeline-OPM update'!$G$4:$L$4,0))-14} -> 46146 | T81: =S81-A81 -> 40 | U81: =IFERROR(VLOOKUP(G81,'Bidding list 26'!$B$2:$P$31,15,0),"") | V81: =S81-U81 -> 46146 | W81: =A81+U81 -> 46106 | X81: =if(A81>V81,"Late", "On time") -> On time | Y81: New Buy | Z81: G | AA81: Done | AB81: FATP-SV-CGY4-MVA2603-57OM | AC81: Done | AD81: 1FSHQ40050 | AE81: Pending | AI81: EPR2603280006 (cancel) | AK81: Bác L bảo bỏ qua tạm thời | AL81: =if(AA81="Done",$J81,0) -> 1 | AM81: =if(AC81="Done",$J81,0) -> 1 | AN81: =if(AE81="Done",$J81,0) -> 0 | AO81: =if(AH81<>"",$J81,0) -> 0
A82: 46106 | B82: ENG2 | C82: Đỗ Thị Xuân | D82: V1536196 | E82: xuandt99@fih-foxconn.com | F82: 4347 | G82: Monitor 2 | H82: =vlookup(G82,'Bidding list 26'!$B$4:$G$270,6,0) -> VA1903H-2, 19 inch, VGA cable + HDMI cable / Brand: VIEWSONIC | I82: 1240000 | J82: 1 | K82: =I82*J82 -> 1240000 | L82: P26 FATP MP PKK4Service line | M82: P26 Service line | N82: PKK4 | O82: FATP | P82: MP | Q82: 46132 | R82: =Q82-A82 -> 26 | S82: {=INDEX('G Project Timeline-OPM update'!$G$7:$L$35,MATCH(1,('G Project Timeline-OPM update'!$C$7:$C$35=N82)*('G Project Timeline-OPM update'!$B$7:$B$35=M82)*('G Project Timeline-OPM update'!$D$7:$D$35=O82),0),MATCH(P82,'G Project Timeline-OPM update'!$G$4:$L$4,0))-14} -> 46146 | T82: =S82-A82 -> 40 | U82: =IFERROR(VLOOKUP(G82,'Bidding list 26'!$B$2:$P$31,15,0),"") -> 50 | V82: =S82-U82 -> 46096 | W82: =A82+U82 -> 46156 | X82: =if(A82>V82,"Late", "On time") -> Late | Y82: New Buy | Z82: G | AA82: Done | AB82: FATP-SV-PKK4-MVA2603-58OM | AC82: Done | AD82: 1FSHQ40052 | AE82: Done | AF82: 1FSHQ40052 | AH82: =vlookup(AF82,Sheet9!A:D,3,0) | AI82: EPR2603280007 | AL82: =if(AA82="Done",$J82,0) -> 1 | AM82: =if(AC82="Done",$J82,0) -> 1 | AN82: =if(AE82="Done",$J82,0) -> 1 | AO82: =if(AH82<>"",$J82,0) -> 0
A83: 46106 | B83: ENG2 | C83: Đỗ Thị Xuân | D83: V1536196 | E83: xuandt99@fih-foxconn.com | F83: 4347 | G83: Mini PC (Assy) | H83: =vlookup(G83,'Bidding list 26'!$B$4:$G$270,6,0) -> #N/A | I83: 7800000 | J83: 1 | K83: =I83*J83 -> 7800000 | L83: P26 FATP MP PKK4Service line | M83: P26 Service line | N83: PKK4 | O83: FATP | P83: MP | Q83: 46132 | R83: =Q83-A83 -> 26 | S83: {=INDEX('G Project Timeline-OPM update'!$G$7:$L$35,MATCH(1,('G Project Timeline-OPM update'!$C$7:$C$35=N83)*('G Project Timeline-OPM update'!$B$7:$B$35=M83)*('G Project Timeline-OPM update'!$D$7:$D$35=O83),0),MATCH(P83,'G Project Timeline-OPM update'!$G$4:$L$4,0))-14} -> 46146 | T83: =S83-A83 -> 40 | U83: =IFERROR(VLOOKUP(G83,'Bidding list 26'!$B$2:$P$31,15,0),"") | V83: =S83-U83 -> 46146 | W83: =A83+U83 -> 46106 | X83: =if(A83>V83,"Late", "On time") -> On time | Y83: New Buy | Z83: G | AA83: Done | AB83: FATP-SV-PKK4-MVA2603-58OM | AC83: Done | AD83: 1FSHQ40053 | AE83: Pending | AI83: EPR2603280008 (cancel) | AK83: Bác L bảo bỏ qua tạm thời | AL83: =if(AA83="Done",$J83,0) -> 1 | AM83: =if(AC83="Done",$J83,0) -> 1 | AN83: =if(AE83="Done",$J83,0) -> 0 | AO83: =if(AH83<>"",$J83,0) -> 0
A84: 46107 | B84: TE | C84: Nguyễn Ngọc Huyền | D84: V1549412 | E84: Nguyen Ngoc Huyen (Evelyn) | F84: 4440 | G84: IPC++(updated) | H84: =vlookup(G84,'Bidding list 26'!$B$4:$G$270,6,0) -> Pro Tower QCT1250, Ultra 7 265, Ram 16GB DDR5, SSD 512GB, Integrated graphics card, Power 180W, HDMI & DP Port, Keyboard and Mouse, 3Yrs Wty | I84: 26752000 | J84: 10 | K84: =I84*J84 -> 267520000 | L84: P26 SMT service PKK4 | M84: P26 Service line | N84: PKK4 | O84: SMT | P84: MP | Q84: 46132 | R84: =Q84-A84 -> 25 | S84: {=INDEX('G Project Timeline-OPM update'!$G$7:$L$35,MATCH(1,('G Project Timeline-OPM update'!$C$7:$C$35=N84)*('G Project Timeline-OPM update'!$B$7:$B$35=M84)*('G Project Timeline-OPM update'!$D$7:$D$35=O84),0),MATCH(P84,'G Project Timeline-OPM update'!$G$4:$L$4,0))-14} -> 46135 | T84: =S84-A84 -> 28 | U84: =IFERROR(VLOOKUP(G84,'Bidding list 26'!$B$2:$P$31,15,0),"") -> 70 | V84: =S84-U84 -> 46065 | X84: =if(A84>V84,"Late", "On time") -> Late | Y84: New Buy | Z84: G | AA84: Done | AB84: SMT-SV-PKK4-MVA2603-61OM | AC84: Done | AD84: 1FSHQ40073 | AE84: Done | AF84: 1FSHQ40073 | AH84: Đã nhận 16.4 | AI84: EPR2603280009 | AL84: =if(AA84="Done",$J84,0) -> 10 | AM84: =if(AC84="Done",$J84,0) -> 10 | AN84: =if(AE84="Done",$J84,0) -> 10 | AO84: =if(AH84<>"",$J84,0) -> 10
A85: 46107 | B85: TE | C85: Nguyễn Ngọc Huyền | D85: V1549412 | E85: Nguyen Ngoc Huyen (Evelyn) | F85: 4440 | G85: IPC++(updated) | H85: =vlookup(G85,'Bidding list 26'!$B$4:$G$270,6,0) -> Pro Tower QCT1250, Ultra 7 265, Ram 16GB DDR5, SSD 512GB, Integrated graphics card, Power 180W, HDMI & DP Port, Keyboard and Mouse, 3Yrs Wty | I85: 26752000 | J85: 10 | K85: =I85*J85 -> 267520000 | L85: P26 SMT service CGY4 | M85: P26 Service line | N85: CGY4 | O85: SMT | P85: MP | Q85: 46132 | R85: =Q85-A85 -> 25 | S85: {=INDEX('G Project Timeline-OPM update'!$G$7:$L$35,MATCH(1,('G Project Timeline-OPM update'!$C$7:$C$35=N85)*('G Project Timeline-OPM update'!$B$7:$B$35=M85)*('G Project Timeline-OPM update'!$D$7:$D$35=O85),0),MATCH(P85,'G Project Timeline-OPM update'!$G$4:$L$4,0))-14} -> 46135 | T85: =S85-A85 -> 28 | U85: =IFERROR(VLOOKUP(G85,'Bidding list 26'!$B$2:$P$31,15,0),"") -> 70 | V85: =S85-U85 -> 46065 | X85: =if(A85>V85,"Late", "On time") -> Late | Y85: New Buy | Z85: G | AA85: Done | AB85: SMT-SV-CGY4-MVA2603-60OM | AC85: Done | AD85: 1FSHQ40072 | AE85: Done | AF85: 1FSHQ40072 | AH85: Đã nhận 16.4 | AI85: EPR2603280010 | AL85: =if(AA85="Done",$J85,0) -> 10 | AM85: =if(AC85="Done",$J85,0) -> 10 | AN85: =if(AE85="Done",$J85,0) -> 10 | AO85: =if(AH85<>"",$J85,0) -> 10
A86: 46107 | B86: TE | C86: Nguyễn Ngọc Huyền | D86: V1549412 | E86: Nguyen Ngoc Huyen (Evelyn) | F86: 4440 | G86: IPC++(updated) | H86: L10-MP-OR5-MVA2601-105OM | I86: 26752000 | J86: 10 | K86: =I86*J86 -> 267520000 | L86: P26 SMT service 4CS4 | M86: P26 Service line | N86: 4CS4 | O86: SMT | P86: MP | Q86: 46132 | R86: =Q86-A86 -> 25 | S86: {=INDEX('G Project Timeline-OPM update'!$G$7:$L$35,MATCH(1,('G Project Timeline-OPM update'!$C$7:$C$35=N86)*('G Project Timeline-OPM update'!$B$7:$B$35=M86)*('G Project Timeline-OPM update'!$D$7:$D$35=O86),0),MATCH(P86,'G Project Timeline-OPM update'!$G$4:$L$4,0))-14} -> 46135 | T86: =S86-A86 -> 28 | U86: =IFERROR(VLOOKUP(G86,'Bidding list 26'!$B$2:$P$31,15,0),"") -> 70 | V86: =S86-U86 -> 46065 | X86: =if(A86>V86,"Late", "On time") -> Late | Y86: New Buy | Z86: G | AA86: Done | AB86: SMT-SV-4CS4-MVA2603-59OM | AC86: Done | AD86: 1FSHQ40071 | AE86: Done | AF86: 1FSHQ40071 | AH86: Đã nhận 16.4 | AI86: EPR2603280011 | AL86: =if(AA86="Done",$J86,0) -> 10 | AM86: =if(AC86="Done",$J86,0) -> 10 | AN86: =if(AE86="Done",$J86,0) -> 10 | AO86: =if(AH86<>"",$J86,0) -> 10
A87: 46107 | B87: TE | C87: Nguyễn Ngọc Huyền | D87: V1549412 | E87: Nguyen Ngoc Huyen (Evelyn) | F87: 4440 | G87: Barcode Scanner SEUIC HS505HDP-2530 ,USB cable | H87: =vlookup(G87,'Bidding list 26'!$B$4:$G$270,6,0) -> SEUIC HS505HDP-2530 ,USB cable | I87: 3300000 | J87: 2 | K87: =I87*J87 -> 6600000 | L87: P26 SMT service PKK4 | M87: P26 Service line | N87: PKK4 | O87: SMT | P87: MP | Q87: 46132 | R87: =Q87-A87 -> 25 | S87: {=INDEX('G Project Timeline-OPM update'!$G$7:$L$35,MATCH(1,('G Project Timeline-OPM update'!$C$7:$C$35=N87)*('G Project Timeline-OPM update'!$B$7:$B$35=M87)*('G Project Timeline-OPM update'!$D$7:$D$35=O87),0),MATCH(P87,'G Project Timeline-OPM update'!$G$4:$L$4,0))-14} -> 46135 | T87: =S87-A87 -> 28 | U87: =IFERROR(VLOOKUP(G87,'Bidding list 26'!$B$2:$P$31,15,0),"") -> 50 | V87: =S87-U87 -> 46085 | W87: =A87+U87 -> 46157 | X87: =if(A87>V87,"Late", "On time") -> Late | Y87: New Buy | Z87: G | AA87: Done | AB87: SMT-SV-PKK4-MVA2603-61OM | AC87: Done | AD87: VNPR202604060080 | AE87: Done | AF87: VNPO202604110046 | AG87: Dự kiến 07/05 hàng về | AH87: 46149 | AI87: EPR2603280012 | AL87: =if(AA87="Done",$J87,0) -> 2 | AM87: =if(AC87="Done",$J87,0) -> 2 | AN87: =if(AE87="Done",$J87,0) -> 2 | AO87: =if(AH87<>"",$J87,0) -> 2
A88: 46107 | B88: TE | C88: Nguyễn Ngọc Huyền | D88: V1549412 | E88: Nguyen Ngoc Huyen (Evelyn) | F88: 4440 | G88: Barcode Scanner SEUIC HS505HDP-2530 ,USB cable | H88: =vlookup(G88,'Bidding list 26'!$B$4:$G$270,6,0) -> SEUIC HS505HDP-2530 ,USB cable | I88: 3300000 | J88: 2 | K88: =I88*J88 -> 6600000 | L88: P26 SMT service CGY4 | M88: P26 Service line | N88: CGY4 | O88: SMT | P88: MP | Q88: 46132 | R88: =Q88-A88 -> 25 | S88: {=INDEX('G Project Timeline-OPM update'!$G$7:$L$35,MATCH(1,('G Project Timeline-OPM update'!$C$7:$C$35=N88)*('G Project Timeline-OPM update'!$B$7:$B$35=M88)*('G Project Timeline-OPM update'!$D$7:$D$35=O88),0),MATCH(P88,'G Project Timeline-OPM update'!$G$4:$L$4,0))-14} -> 46135 | T88: =S88-A88 -> 28 | U88: =IFERROR(VLOOKUP(G88,'Bidding list 26'!$B$2:$P$31,15,0),"") -> 50 | V88: =S88-U88 -> 46085 | W88: =A88+U88 -> 46157 | X88: =if(A88>V88,"Late", "On time") -> Late | Y88: New Buy | Z88: G | AA88: Done | AB88: SMT-SV-CGY4-MVA2603-60OM | AC88: Done | AD88: VNPR202604060079 | AE88: Done | AF88: VNPO202604110046 | AG88: Dự kiến 07/05 hàng về | AH88: 46149 | AI88: EPR2603280013 | AL88: =if(AA88="Done",$J88,0) -> 2 | AM88: =if(AC88="Done",$J88,0) -> 2 | AN88: =if(AE88="Done",$J88,0) -> 2 | AO88: =if(AH88<>"",$J88,0) -> 2
A89: 46107 | B89: TE | C89: Nguyễn Ngọc Huyền | D89: V1549412 | E89: Nguyen Ngoc Huyen (Evelyn) | F89: 4440 | G89: Barcode Scanner SEUIC HS505HDP-2530 ,USB cable | H89: =vlookup(G89,'Bidding list 26'!$B$4:$G$270,6,0) -> SEUIC HS505HDP-2530 ,USB cable | I89: 3300000 | J89: 2 | K89: =I89*J89 -> 6600000 | L89: P26 SMT service 4CS4 | M89: P26 Service line | N89: 4CS4 | O89: SMT | P89: MP | Q89: 46132 | R89: =Q89-A89 -> 25 | S89: {=INDEX('G Project Timeline-OPM update'!$G$7:$L$35,MATCH(1,('G Project Timeline-OPM update'!$C$7:$C$35=N89)*('G Project Timeline-OPM update'!$B$7:$B$35=M89)*('G Project Timeline-OPM update'!$D$7:$D$35=O89),0),MATCH(P89,'G Project Timeline-OPM update'!$G$4:$L$4,0))-14} -> 46135 | T89: =S89-A89 -> 28 | U89: =IFERROR(VLOOKUP(G89,'Bidding list 26'!$B$2:$P$31,15,0),"") -> 50 | V89: =S89-U89 -> 46085 | W89: =A89+U89 -> 46157 | X89: =if(A89>V89,"Late", "On time") -> Late | Y89: New Buy | Z89: G | AA89: Done | AB89: SMT-SV-4CS4-MVA2603-59OM | AC89: Done | AD89: VNPR202604060075 | AE89: Done | AF89: VNPO202604110046 | AG89: Dự kiến 07/05 hàng về | AH89: 46149 | AI89: EPR2603280014 | AL89: =if(AA89="Done",$J89,0) -> 2 | AM89: =if(AC89="Done",$J89,0) -> 2 | AN89: =if(AE89="Done",$J89,0) -> 2 | AO89: =if(AH89<>"",$J89,0) -> 2
A90: 46111 | B90: GG-WH | C90: Nguyen Thi Viet | D90: V1524536 | E90: Vietnt@fih-foxconn.com | F90: 4478 | G90: Monitor 1 | H90: DELL E2225HM, 21.5 inch HDMI cable, 3Yrs Wty | I90: 1980000 | J90: 3 | K90: 5940000 | L90: P26 MP | M90: P26 | N90: PKK4 | O90: FATP | P90: MP | Q90: 46142 | R90: =Q90-A90 -> 31 | S90: {=INDEX('G Project Timeline-OPM update'!$G$7:$L$35,MATCH(1,('G Project Timeline-OPM update'!$C$7:$C$35=N90)*('G Project Timeline-OPM update'!$B$7:$B$35=M90)*('G Project Timeline-OPM update'!$D$7:$D$35=O90),0),MATCH(P90,'G Project Timeline-OPM update'!$G$4:$L$4,0))-14} -> 46135 | T90: =S90-A90 -> 24 | U90: =IFERROR(VLOOKUP(G90,'Bidding list 26'!$B$2:$P$31,15,0),"") -> 50 | V90: =S90-U90 -> 46085 | W90: =A90+U90 -> 46161 | Y90: New Buy | Z90: L | AA90: Done | AB90: FATP-MP-PKK4-MVA2603-71OM | AC90: Done | AD90: 1FSHQ40136 | AE90: Done | AF90: 1FSHQ40136 | AG90: =vlookup(AF90,Sheet9!A:D,4,0) | AH90: Đã nhận 29.04 | AI90: EPR2604140009 | AL90: =if(AA90="Done",$J90,0) -> 3 | AM90: =if(AC90="Done",$J90,0) -> 3 | AN90: =if(AE90="Done",$J90,0) -> 3 | AO90: =if(AH90<>"",$J90,0) -> 3
A91: 46111 | B91: GG-WH | C91: Nguyen Thi Viet | D91: V1524536 | E91: Vietnt@fih-foxconn.com | F91: 4478 | G91: IPC+(updated) | H91: =vlookup(G91,'Bidding list 26'!$B$4:$G$270,6,0) -> Pro Tower QCT1250, Ultra 5 235, Ram 16GB DDR5, SSD 512GB, Integrated graphics card, Power 180W, HDMI & DP Port, Keyboard and Mouse, 3Yrs Wty | I91: 18717000 | J91: 3 | K91: =I91*J91 -> 56151000 | L91: P26 MP | M91: P26 | N91: PKK4 | O91: FATP | P91: MP | Q91: 46142 | R91: =Q91-A91 -> 31 | S91: {=INDEX('G Project Timeline-OPM update'!$G$7:$L$35,MATCH(1,('G Project Timeline-OPM update'!$C$7:$C$35=N91)*('G Project Timeline-OPM update'!$B$7:$B$35=M91)*('G Project Timeline-OPM update'!$D$7:$D$35=O91),0),MATCH(P91,'G Project Timeline-OPM update'!$G$4:$L$4,0))-14} -> 46135 | T91: =S91-A91 -> 24 | U91: =IFERROR(VLOOKUP(G91,'Bidding list 26'!$B$2:$P$31,15,0),"") -> 70 | V91: =S91-U91 -> 46065 | W91: =A91+U91 -> 46181 | X91: =if(A91>V91,"Late", "On time") -> Late | Y91: New Buy | Z91: L | AA91: Done | AB91: FATP-MP-PKK4-MVA2603-71OM | AC91: Done | AD91: 1FSHQ40137 | AE91: Done | AF91: 1FSHQ40137 | AH91: =vlookup(AF91,Sheet9!A:D,3,0) -> Đã nhận 23/04 | AI91: EPR2604140010 | AL91: =if(AA91="Done",$J91,0) -> 3 | AM91: =if(AC91="Done",$J91,0) -> 3 | AN91: =if(AE91="Done",$J91,0) -> 3 | AO91: =if(AH91<>"",$J91,0) -> 3
A92: 46111 | B92: GG-WH | C92: Nguyen Thi Viet | D92: V1524536 | E92: Vietnt@fih-foxconn.com | F92: 4478 | G92: Monitor 1 | H92: =vlookup(G92,'Bidding list 26'!$B$4:$G$270,6,0) -> DELL E2225HM, 21.5 inch HDMI cable, 3Yrs Wty | I92: 1980000 | J92: 4 | K92: =I92*J92 -> 7920000 | L92: P26 MP | M92: P26 | N92: CGY4 | O92: FATP | P92: MP | Q92: 46142 | R92: =Q92-A92 -> 31 | S92: {=INDEX('G Project Timeline-OPM update'!$G$7:$L$35,MATCH(1,('G Project Timeline-OPM update'!$C$7:$C$35=N92)*('G Project Timeline-OPM update'!$B$7:$B$35=M92)*('G Project Timeline-OPM update'!$D$7:$D$35=O92),0),MATCH(P92,'G Project Timeline-OPM update'!$G$4:$L$4,0))-14} -> 46135 | T92: =S92-A92 -> 24 | U92: =IFERROR(VLOOKUP(G92,'Bidding list 26'!$B$2:$P$31,15,0),"") -> 50 | V92: =S92-U92 -> 46085 | W92: =A92+U92 -> 46161 | X92: =if(A92>V92,"Late", "On time") -> Late | Y92: New Buy | Z92: L | AA92: Done | AB92: FATP-MP-CGY4-MVA2603-70OM | AC92: Done | AD92: 1FSHQ40134 | AE92: Done | AF92: 1FSHQ40134 | AG92: =vlookup(AF92,Sheet9!A:D,4,0) | AH92: Đã nhận 29.04 | AI92: EPR2604140011 | AL92: =if(AA92="Done",$J92,0) -> 4 | AM92: =if(AC92="Done",$J92,0) -> 4 | AN92: =if(AE92="Done",$J92,0) -> 4 | AO92: =if(AH92<>"",$J92,0) -> 4
A93: 46111 | B93: GG-WH | C93: Nguyen Thi Viet | D93: V1524536 | E93: Vietnt@fih-foxconn.com | F93: 4478 | G93: IPC+(updated) | H93: =vlookup(G93,'Bidding list 26'!$B$4:$G$270,6,0) -> Pro Tower QCT1250, Ultra 5 235, Ram 16GB DDR5, SSD 512GB, Integrated graphics card, Power 180W, HDMI & DP Port, Keyboard and Mouse, 3Yrs Wty | I93: 18717000 | J93: 5 | K93: =I93*J93 -> 93585000 | L93: P26 MP | M93: P26 | N93: CGY4 | O93: FATP | P93: MP | Q93: 46142 | R93: =Q93-A93 -> 31 | S93: {=INDEX('G Project Timeline-OPM update'!$G$7:$L$35,MATCH(1,('G Project Timeline-OPM update'!$C$7:$C$35=N93)*('G Project Timeline-OPM update'!$B$7:$B$35=M93)*('G Project Timeline-OPM update'!$D$7:$D$35=O93),0),MATCH(P93,'G Project Timeline-OPM update'!$G$4:$L$4,0))-14} -> 46135 | T93: =S93-A93 -> 24 | U93: =IFERROR(VLOOKUP(G93,'Bidding list 26'!$B$2:$P$31,15,0),"") -> 70 | V93: =S93-U93 -> 46065 | W93: =A93+U93 -> 46181 | X93: =if(A93>V93,"Late", "On time") -> Late | Y93: New Buy | Z93: L | AA93: Done | AB93: FATP-MP-CGY4-MVA2603-70OM | AC93: Done | AD93: 1FSHQ40135 | AE93: Done | AF93: 1FSHQ40135 | AH93: =vlookup(AF93,Sheet9!A:D,3,0) -> Đã nhận 23/04 | AI93: EPR2604140012 | AL93: =if(AA93="Done",$J93,0) -> 5 | AM93: =if(AC93="Done",$J93,0) -> 5 | AN93: =if(AE93="Done",$J93,0) -> 5 | AO93: =if(AH93<>"",$J93,0) -> 5
A94: 46111 | B94: GG-WH | C94: Nguyen Thi Viet | D94: V1524536 | E94: Vietnt@fih-foxconn.com | F94: 4478 | G94: Monitor 1 | H94: =vlookup(G94,'Bidding list 26'!$B$4:$G$270,6,0) -> DELL E2225HM, 21.5 inch HDMI cable, 3Yrs Wty | I94: 1980000 | J94: 5 | K94: =I94*J94 -> 9900000 | L94: P26 MP | M94: P26 | N94: 4CS4 | O94: FATP | P94: MP | Q94: 46142 | R94: =Q94-A94 -> 31 | S94: {=INDEX('G Project Timeline-OPM update'!$G$7:$L$35,MATCH(1,('G Project Timeline-OPM update'!$C$7:$C$35=N94)*('G Project Timeline-OPM update'!$B$7:$B$35=M94)*('G Project Timeline-OPM update'!$D$7:$D$35=O94),0),MATCH(P94,'G Project Timeline-OPM update'!$G$4:$L$4,0))-14} -> 46135 | T94: =S94-A94 -> 24 | U94: =IFERROR(VLOOKUP(G94,'Bidding list 26'!$B$2:$P$31,15,0),"") -> 50 | V94: =S94-U94 -> 46085 | W94: =A94+U94 -> 46161 | X94: =if(A94>V94,"Late", "On time") -> Late | Y94: New Buy | Z94: L | AA94: Done | AB94: FATP-MP-4CS4-MVA2603-69OM | AC94: Done | AD94: 1FSHQ40132 | AE94: Done | AF94: 1FSHQ40132 | AG94: =vlookup(AF94,Sheet9!A:D,4,0) | AH94: Đã nhận 29.04 | AI94: EPR2604140013 | AL94: =if(AA94="Done",$J94,0) -> 5 | AM94: =if(AC94="Done",$J94,0) -> 5 | AN94: =if(AE94="Done",$J94,0) -> 5 | AO94: =if(AH94<>"",$J94,0) -> 5
A95: 46111 | B95: GG-WH | C95: Nguyen Thi Viet | D95: V1524536 | E95: Vietnt@fih-foxconn.com | F95: 4478 | G95: IPC+(updated) | H95: =vlookup(G95,'Bidding list 26'!$B$4:$G$270,6,0) -> Pro Tower QCT1250, Ultra 5 235, Ram 16GB DDR5, SSD 512GB, Integrated graphics card, Power 180W, HDMI & DP Port, Keyboard and Mouse, 3Yrs Wty | I95: 18717000 | J95: 4 | K95: =I95*J95 -> 74868000 | L95: P26 MP | M95: P26 | N95: 4CS4 | O95: FATP | P95: MP | Q95: 46142 | R95: =Q95-A95 -> 31 | S95: {=INDEX('G Project Timeline-OPM update'!$G$7:$L$35,MATCH(1,('G Project Timeline-OPM update'!$C$7:$C$35=N95)*('G Project Timeline-OPM update'!$B$7:$B$35=M95)*('G Project Timeline-OPM update'!$D$7:$D$35=O95),0),MATCH(P95,'G Project Timeline-OPM update'!$G$4:$L$4,0))-14} -> 46135 | T95: =S95-A95 -> 24 | U95: =IFERROR(VLOOKUP(G95,'Bidding list 26'!$B$2:$P$31,15,0),"") -> 70 | V95: =S95-U95 -> 46065 | W95: =A95+U95 -> 46181 | X95: =if(A95>V95,"Late", "On time") -> Late | Y95: New Buy | Z95: L | AA95: Done | AB95: FATP-MP-4CS4-MVA2603-69OM | AC95: Done | AD95: 1FSHQ40133 | AE95: Done | AF95: 1FSHQ40133 | AH95: =vlookup(AF95,Sheet9!A:D,3,0) -> Đã nhận 23/04 | AI95: EPR2604140014 | AL95: =if(AA95="Done",$J95,0) -> 4 | AM95: =if(AC95="Done",$J95,0) -> 4 | AN95: =if(AE95="Done",$J95,0) -> 4 | AO95: =if(AH95<>"",$J95,0) -> 4
A96: 46111 | B96: GG-WH | C96: Nguyen Thi Viet | D96: V1524536 | E96: Vietnt@fih-foxconn.com | F96: 4478 | G96: Printer GODEX | H96: =vlookup(G96,'Bidding list 26'!$B$4:$G$270,6,0) -> GODEX GX4600i pro, 600dpi | I96: 31150000 | J96: 2 | K96: =I96*J96 -> 62300000 | L96: P26 MP | M96: P26 | N96: PKK4 | O96: FATP | P96: MP | Q96: 46142 | R96: =Q96-A96 -> 31 | S96: {=INDEX('G Project Timeline-OPM update'!$G$7:$L$35,MATCH(1,('G Project Timeline-OPM update'!$C$7:$C$35=N96)*('G Project Timeline-OPM update'!$B$7:$B$35=M96)*('G Project Timeline-OPM update'!$D$7:$D$35=O96),0),MATCH(P96,'G Project Timeline-OPM update'!$G$4:$L$4,0))-14} -> 46135 | T96: =S96-A96 -> 24 | U96: =IFERROR(VLOOKUP(G96,'Bidding list 26'!$B$2:$P$31,15,0),"") -> 48 | V96: =S96-U96 -> 46087 | W96: =A96+U96 -> 46159 | X96: =if(A96>V96,"Late", "On time") -> Late | Y96: New Buy | Z96: L | AA96: Done | AB96: L10-MP-PKK4-MVA2604-17OM | AC96: Done | AD96: 1FSHQ40297 | AE96: Done | AF96: 1FSHQ40297 | AG96: 46147 | AH96: 46147 | AI96: EPR2605060002 | AL96: =if(AA96="Done",$J96,0) -> 2 | AM96: =if(AC96="Done",$J96,0) -> 2 | AN96: =if(AE96="Done",$J96,0) -> 2 | AO96: =if(AH96<>"",$J96,0) -> 2
A97: 46111 | B97: GG-WH | C97: Nguyen Thi Viet | D97: V1524536 | E97: Vietnt@fih-foxconn.com | F97: 4478 | G97: Printer GODEX | H97: =vlookup(G97,'Bidding list 26'!$B$4:$G$270,6,0) -> GODEX GX4600i pro, 600dpi | I97: 31150000 | J97: 2 | K97: =I97*J97 -> 62300000 | L97: P26 MP | M97: P26 | N97: CGY4 | O97: FATP | P97: MP | Q97: 46142 | R97: =Q97-A97 -> 31 | S97: {=INDEX('G Project Timeline-OPM update'!$G$7:$L$35,MATCH(1,('G Project Timeline-OPM update'!$C$7:$C$35=N97)*('G Project Timeline-OPM update'!$B$7:$B$35=M97)*('G Project Timeline-OPM update'!$D$7:$D$35=O97),0),MATCH(P97,'G Project Timeline-OPM update'!$G$4:$L$4,0))-14} -> 46135 | T97: =S97-A97 -> 24 | U97: =IFERROR(VLOOKUP(G97,'Bidding list 26'!$B$2:$P$31,15,0),"") -> 48 | V97: =S97-U97 -> 46087 | W97: =A97+U97 -> 46159 | X97: =if(A97>V97,"Late", "On time") -> Late | Y97: New Buy | Z97: L | AA97: Done | AB97: L10-MP-CGY4-MVA2604-16OM | AC97: Done | AD97: 1FSHQ40310 | AE97: Done | AF97: 1FSHQ40310 | AG97: 46147 | AH97: 46147 | AI97: EPR2605060003 | AL97: =if(AA97="Done",$J97,0) -> 2 | AM97: =if(AC97="Done",$J97,0) -> 2 | AN97: =if(AE97="Done",$J97,0) -> 2 | AO97: =if(AH97<>"",$J97,0) -> 2
A98: 46111 | B98: GG-WH | C98: Nguyen Thi Viet | D98: V1524536 | E98: Vietnt@fih-foxconn.com | F98: 4478 | G98: Printer GODEX | H98: =vlookup(G98,'Bidding list 26'!$B$4:$G$270,6,0) -> GODEX GX4600i pro, 600dpi | I98: 31150000 | J98: 2 | K98: =I98*J98 -> 62300000 | L98: P26 MP | M98: P26 | N98: 4CS4 | O98: FATP | P98: MP | Q98: 46142 | R98: =Q98-A98 -> 31 | S98: {=INDEX('G Project Timeline-OPM update'!$G$7:$L$35,MATCH(1,('G Project Timeline-OPM update'!$C$7:$C$35=N98)*('G Project Timeline-OPM update'!$B$7:$B$35=M98)*('G Project Timeline-OPM update'!$D$7:$D$35=O98),0),MATCH(P98,'G Project Timeline-OPM update'!$G$4:$L$4,0))-14} -> 46135 | T98: =S98-A98 -> 24 | U98: =IFERROR(VLOOKUP(G98,'Bidding list 26'!$B$2:$P$31,15,0),"") -> 48 | V98: =S98-U98 -> 46087 | W98: =A98+U98 -> 46159 | X98: =if(A98>V98,"Late", "On time") -> Late | Y98: New Buy | Z98: L | AA98: Done | AB98: L10-MP-4CS4-MVA2604-15OM | AC98: Done | AD98: 1FSHQ40296 | AE98: Done | AF98: 1FSHQ40296 | AG98: 46147 | AH98: 46147 | AI98: EPR2605060004 | AL98: =if(AA98="Done",$J98,0) -> 2 | AM98: =if(AC98="Done",$J98,0) -> 2 | AN98: =if(AE98="Done",$J98,0) -> 2 | AO98: =if(AH98<>"",$J98,0) -> 2
A99: 46112 | B99: ENG3 | C99: Phạm Van Hùng | D99: V1544999 | E99: hungpv3@fih-foxconn.com | F99: 4500 | G99: IPC+(updated) | H99: =vlookup(G99,'Bidding list 26'!$B$4:$G$270,6,0) -> Pro Tower QCT1250, Ultra 5 235, Ram 16GB DDR5, SSD 512GB, Integrated graphics card, Power 180W, HDMI & DP Port, Keyboard and Mouse, 3Yrs Wty | I99: 18717000 | J99: 3 | K99: =I99*J99 -> 56151000 | L99: PC for Auto charging machine P26 | M99: P26 | N99: 4CS4 | O99: FATP | P99: MP | Q99: 46126 | R99: =Q99-A99 -> 14 | S99: {=INDEX('G Project Timeline-OPM update'!$G$7:$L$35,MATCH(1,('G Project Timeline-OPM update'!$C$7:$C$35=N99)*('G Project Timeline-OPM update'!$B$7:$B$35=M99)*('G Project Timeline-OPM update'!$D$7:$D$35=O99),0),MATCH(P99,'G Project Timeline-OPM update'!$G$4:$L$4,0))-14} -> 46135 | T99: =S99-A99 -> 23 | U99: =IFERROR(VLOOKUP(G99,'Bidding list 26'!$B$2:$P$31,15,0),"") -> 70 | V99: =S99-U99 -> 46065 | W99: =A99+U99 -> 46182 | X99: =if(A99>V99,"Late", "On time") -> Late | Y99: New Buy | Z99: G | AA99: Done | AB99: FATP-MP-4CS4-MVA2603-74AUTO | AC99: Done | AD99: 1FSHQ40198 | AE99: Done | AF99: 1FSHQ40198 | AH99: 46149 | AI99: EPR2605040001 | AL99: =if(AA99="Done",$J99,0) -> 3 | AM99: =if(AC99="Done",$J99,0) -> 3 | AN99: =if(AE99="Done",$J99,0) -> 3 | AO99: =if(AH99<>"",$J99,0) -> 3
A100: 46112 | B100: ENG3 | C100: Phạm Van Hùng | D100: V1544999 | E100: hungpv3@fih-foxconn.com | F100: 4500 | G100: IPC+(updated) | H100: =vlookup(G100,'Bidding list 26'!$B$4:$G$270,6,0) -> Pro Tower QCT1250, Ultra 5 235, Ram 16GB DDR5, SSD 512GB, Integrated graphics card, Power 180W, HDMI & DP Port, Keyboard and Mouse, 3Yrs Wty | I100: 18717000 | J100: 3 | K100: =I100*J100 -> 56151000 | L100: PC for Auto charging machine P26 | M100: P26 | N100: PKK4 | O100: FATP | P100: MP | Q100: 46126 | R100: =Q100-A100 -> 14 | S100: {=INDEX('G Project Timeline-OPM update'!$G$7:$L$35,MATCH(1,('G Project Timeline-OPM update'!$C$7:$C$35=N100)*('G Project Timeline-OPM update'!$B$7:$B$35=M100)*('G Project Timeline-OPM update'!$D$7:$D$35=O100),0),MATCH(P100,'G Project Timeline-OPM update'!$G$4:$L$4,0))-14} -> 46135 | T100: =S100-A100 -> 23 | U100: =IFERROR(VLOOKUP(G100,'Bidding list 26'!$B$2:$P$31,15,0),"") -> 70 | V100: =S100-U100 -> 46065 | W100: =A100+U100 -> 46182 | X100: =if(A100>V100,"Late", "On time") -> Late | Y100: New Buy | Z100: G | AA100: Done | AB100: FATP-MP-PKK4-MVA2603-75AUTO | AC100: Done | AD100: 1FSHQ40199 | AE100: Done | AF100: 1FSHQ40199 | AH100: 46149 | AI100: EPR2605040002 | AL100: =if(AA100="Done",$J100,0) -> 3 | AM100: =if(AC100="Done",$J100,0) -> 3 | AN100: =if(AE100="Done",$J100,0) -> 3 | AO100: =if(AH100<>"",$J100,0) -> 3
...

Sheet Check mini PC issue
A2: Mini PC Lamitouch Issue
A3: Project | B3: Dept | C3: Qty request | D3: Yubo Supplied Qty | E3: Pending Qty | F3: PO release Qty | G3: Actual Backup | H3: Detail back up | I3: Pending Supply Qty
A4: P26 MP | B4: MFG | C4: 378 | D4: 0 | E4: =C4-D4 -> 378 | F4: 378 | G4: =92+40+120+5+7+12-14 -> 262 | H4: +12x-newbuy from P26 zombie line -DL return: +40x- PC Assy at OM WH +120x - newbuy from OR5 - DL return: -14x-NG line return +5x- borrow OR5 wisetech-DL return: +7x-OM stock-lev for P26 +8x PC Assy (8x MFG return NG, OM check OK- re-supplied) +4x PC Assy-borrow PQE-DL return: | I4: =C4-G4 -> 116
B5: ENG | C5: 24 | D5: 0 | E5: =C5-D5 -> 24 | F5: 24 | G5: 0 | I5: =C5-G5 -> 24 | J5: Cancel PO, change to order from Banico Mini PC Asus
A6: P26 service | B6: MFG | C6: 121 | D6: 0 | E6: =C6-D6 -> 121 | F6: =121-48 -> 73 | G6: 80 | H6: Đang mượn 80x from p26 zombie line-DL ruturn: | I6: =C6-G6 -> 41
B7: ENG | C7: 3 | D7: 0 | E7: 3 | F7: 0 | G7: 0 | I7: =C7-G7 -> 3
A8: P27 P1.0 | B8: MFG | C8: 140 | D8: 0 | E8: =C8-D8 -> 140 | F8: 0 | G8: 140 | H8: Order 140x- Mini PC asus Banico- Received | I8: =C8-G8 -> 0
A9: Total | C9: =SUM(C4:C8) -> 666 | D9: =SUM(D4:D8) -> 0 | E9: =SUM(E4:E8) -> 666 | F9: =SUM(F4:F8) -> 475 | G9: =SUM(G4:G8) -> 482 | I9: =C9-G9 -> 184
F10: Cancel 475x, change order to NUC asus Banico | I10: 92 | J10: Trả P26 zombie line
F11: Remain Qty not yet released PO | G11: =804-475 -> 329 | I11: =SUM(I9:I10) -> 276
A14: now Total order request mini Lamitouch 780x for P26-378x, P26 service: 124x (Line open date 5/18), P27: 278x ( line open date 6/1). Current we temporary use pending pickup mini PC of P26 zombie line 92x and PC assy 40x supplied for P26 MP, total Qty lack ~ 780x-132x= 648x

Sheet NON G MVA EQ request
A1: Date of Request | B1: Department | C1: Requester name | D1: Requester employee ID | E1: Email | F1: Phone | G1: Item | H1: Request equipment spec | I1: Price | J1: Quantity | K1: Total Cost | L1: Purpose | M1: Year Project | N1: Project | O1: Phase | P1: Stage | Q1: Required Delivery Date (update by DRI) | R1: Given LT (days) (follow DRI update) | S1: Required Delivery Date follow Stage date (line open date - 14 days) | T1: Given LT (days) follow stage date | U1: Total Leadtime | V1: Request Deadline | W1: Late/ ontime | X1: Action | Y1: Remark | Z1: Budget Status | AA1: Budget # | AB1: PR Status | AC1: PR # | AD1: PO Status | AE1: PO # | AF1: ETA (Plan) | AG1: DTA (Actual) | AH1: #PUR request No | AI1: Action for delivery later than time Setup line | AK1: Qty Done Budget | AL1: Qty Done PQ | AM1: Qty Done PO | AN1: Qty Recieved
A2: 46035 | B2: FAE | C2: Vu Xuan Bach | D2: V1521896 | E2: bachvx@fih-foxconn.com | F2: 3546/3435 | G2: IPC | H2: =vlookup(G2,'Bidding list 26'!$B$4:$G$270,6,0) -> #N/A | I2: 10870000 | J2: 2 | K2: =I2*J2 -> 21740000 | L2: OR6 EVT | N2: OR6 | O2: FATP | P2: EVT | Q2: 46052 | R2: =Q2-A2 -> 17 | S2: {=INDEX('NONG Project Timeline-OPM updat'!$D$8:$I$65,MATCH(1,('NONG Project Timeline-OPM updat'!$B$8:$B$65=N2)*('NONG Project Timeline-OPM updat'!$C$8:$C$65=O2),0),MATCH(P2,'NONG Project Timeline-OPM updat'!$D$5:$I$5,0))-14} -> 46074 | T2: =S2-A2 -> 39 | U2: =IFERROR(VLOOKUP(G2,'Bidding list 26'!$B$2:$P$21,15,0),"") | V2: =S2-U2 -> 46074 | W2: =if(A2>V2,"Late", "On time") -> On time | X2: New Buy | Z2: Done | AB2: Done | AD2: Done | AG2: 46073 | AH2: EPR2602020005 : Done | AJ2: =B2&G2&J2&N2&X2&AA2 -> FAEIPC2OR6New Buy | AK2: =if(Z2="Done",$J2,0) -> 2 | AL2: =if(AB2="Done",$J2,0) -> 2 | AM2: =if(AD2="Done",$J2,0) -> 2 | AN2: =if(AG2<>"",$J2,0) -> 2
A3: 46035 | B3: FAE | C3: Vu Xuan Bach | D3: V1521896 | E3: bachvx@fih-foxconn.com | G3: Monitor 1 | H3: =vlookup(G3,'Bidding list 26'!$B$4:$G$270,6,0) -> DELL E2225HM, 21.5 inch HDMI cable, 3Yrs Wty | I3: 1980000 | J3: 2 | K3: =I3*J3 -> 3960000 | L3: OR6 EVT | N3: OR6 | O3: FATP | P3: EVT | Q3: 46052 | R3: =Q3-A3 -> 17 | S3: {=INDEX('NONG Project Timeline-OPM updat'!$D$8:$I$65,MATCH(1,('NONG Project Timeline-OPM updat'!$B$8:$B$65=N3)*('NONG Project Timeline-OPM updat'!$C$8:$C$65=O3),0),MATCH(P3,'NONG Project Timeline-OPM updat'!$D$5:$I$5,0))-14} -> 46074 | T3: =S3-A3 -> 39 | U3: =IFERROR(VLOOKUP(G3,'Bidding list 26'!$B$2:$P$21,15,0),"") | V3: =S3-U3 -> 46074 | W3: =if(A3>V3,"Late", "On time") -> On time | X3: New Buy | Z3: Done | AA3: FATP-NPI-OR6-MVA2601-101OM | AB3: Done | AC3: 1FSHQ10134 | AD3: Done | AE3: 1FSHQ10134 | AG3: 46073 | AH3: EPR2602020006 | AJ3: =B3&G3&J3&N3&X3&AA3 -> FAEMonitor 12OR6New BuyFATP-NPI-OR6-MVA2601-101OM | AK3: =if(Z3="Done",$J3,0) -> 2 | AL3: =if(AB3="Done",$J3,0) -> 2 | AM3: =if(AD3="Done",$J3,0) -> 2 | AN3: =if(AG3<>"",$J3,0) -> 2
A4: 46037 | B4: WH | C4: Le Thi Lich | D4: V1525678 | E4: lichlt@fih-foxconn.com | F4: 4478 | G4: IPC+ | H4: =vlookup(G4,'Bidding list 26'!$B$4:$G$270,6,0) -> #N/A | I4: 14200000 | J4: 2 | K4: =I4*J4 -> 28400000 | L4: OR6 EVT | N4: OR6 | O4: FATP | P4: EVT | Q4: 46052 | R4: =Q4-A4 -> 15 | S4: {=INDEX('NONG Project Timeline-OPM updat'!$D$8:$I$65,MATCH(1,('NONG Project Timeline-OPM updat'!$B$8:$B$65=N4)*('NONG Project Timeline-OPM updat'!$C$8:$C$65=O4),0),MATCH(P4,'NONG Project Timeline-OPM updat'!$D$5:$I$5,0))-14} -> 46074 | T4: =S4-A4 -> 37 | U4: =IFERROR(VLOOKUP(G4,'Bidding list 26'!$B$2:$P$21,15,0),"") | V4: =S4-U4 -> 46074 | W4: =if(A4>V4,"Late", "On time") -> On time | X4: New Buy | Z4: Done | AA4: FATP-NPI-OR6-MVA2601-101OM | AB4: Done | AC4: 1FSHQ10132 | AD4: Done | AE4: 1FSHQ10132 | AG4: 46066 | AH4: EPR2602020007 : Done | AJ4: =B4&G4&J4&N4&X4&AA4 -> WHIPC+2OR6New BuyFATP-NPI-OR6-MVA2601-101OM | AK4: =if(Z4="Done",$J4,0) -> 2 | AL4: =if(AB4="Done",$J4,0) -> 2 | AM4: =if(AD4="Done",$J4,0) -> 2 | AN4: =if(AG4<>"",$J4,0) -> 2
A5: 46037 | B5: WH | C5: Le Thi Lich | D5: V1525678 | E5: lichlt@fih-foxconn.com | F5: 4478 | G5: Monitor 1 | H5: =vlookup(G5,'Bidding list 26'!$B$4:$G$270,6,0) -> DELL E2225HM, 21.5 inch HDMI cable, 3Yrs Wty | I5: 1980000 | J5: 2 | K5: =I5*J5 -> 3960000 | L5: OR6 EVT | N5: OR6 | O5: FATP | P5: EVT | Q5: 46052 | R5: =Q5-A5 -> 15 | S5: {=INDEX('NONG Project Timeline-OPM updat'!$D$8:$I$65,MATCH(1,('NONG Project Timeline-OPM updat'!$B$8:$B$65=N5)*('NONG Project Timeline-OPM updat'!$C$8:$C$65=O5),0),MATCH(P5,'NONG Project Timeline-OPM updat'!$D$5:$I$5,0))-14} -> 46074 | T5: =S5-A5 -> 37 | U5: =IFERROR(VLOOKUP(G5,'Bidding list 26'!$B$2:$P$21,15,0),"") | V5: =S5-U5 -> 46074 | W5: =if(A5>V5,"Late", "On time") -> On time | X5: New Buy | Z5: Done | AB5: Done | AD5: Done | AG5: 46073 | AH5: EPR2602020008 ( cũ ) | AJ5: =B5&G5&J5&N5&X5&AA5 -> WHMonitor 12OR6New Buy | AK5: =if(Z5="Done",$J5,0) -> 2 | AL5: =if(AB5="Done",$J5,0) -> 2 | AM5: =if(AD5="Done",$J5,0) -> 2 | AN5: =if(AG5<>"",$J5,0) -> 2
A6: 46037 | B6: WH | C6: Le Thi Lich | D6: V1525678 | E6: lichlt@fih-foxconn.com | F6: 4478 | G6: PDA CHAINWAY C61-4850 | H6: =vlookup(G6,'Bidding list 26'!$B$4:$G$270,6,0) -> C61-4850, Not including RFID module. Includes: 64GB 27-key Android 11, controller with battery, charging dock, charging adapter, glass screen protector | I6: 15500000 | J6: 1 | K6: =I6*J6 -> 15500000 | L6: OR6 EVT | N6: OR6 | O6: FATP | P6: EVT | Q6: 46084 | R6: =Q6-A6 -> 47 | S6: {=INDEX('NONG Project Timeline-OPM updat'!$D$8:$I$65,MATCH(1,('NONG Project Timeline-OPM updat'!$B$8:$B$65=N6)*('NONG Project Timeline-OPM updat'!$C$8:$C$65=O6),0),MATCH(P6,'NONG Project Timeline-OPM updat'!$D$5:$I$5,0))-14} -> 46074 | T6: =S6-A6 -> 37 | U6: =IFERROR(VLOOKUP(G6,'Bidding list 26'!$B$2:$P$21,15,0),"") -> 65 | V6: =S6-U6 -> 46009 | W6: =if(A6>V6,"Late", "On time") -> Late | X6: New Buy | Z6: Done | AA6: FATP-NPI-OR6-MVA2602-112OM | AB6: Done | AC6: VNPR202602090065 | AD6: Done | AE6: VNPO202602130022 | AG6: 46112 | AH6: EPR2603100002 | AJ6: =B6&G6&J6&N6&X6&AA6 -> WHPDA CHAINWAY C61-48501OR6New BuyFATP-NPI-OR6-MVA2602-112OM | AK6: =if(Z6="Done",$J6,0) -> 1 | AL6: =if(AB6="Done",$J6,0) -> 1 | AM6: =if(AD6="Done",$J6,0) -> 1 | AN6: =if(AG6<>"",$J6,0) -> 1
A7: 46041 | B7: ME | C7: Nguyen Thi Hai | D7: V1516000 | E7: haint2@fih-foxconn.com | F7: 4493 | G7: Mini PC (Assy) | H7: =vlookup(G7,'Bidding list 26'!$B$4:$G$270,6,0) -> #N/A | I7: 7800000 | J7: 440 | K7: =I7*J7 -> 3432000000 | L7: OR5 DVT | N7: OR5 | O7: FATP | P7: DVT | Q7: 46076 | R7: =Q7-A7 -> 35 | S7: {=INDEX('NONG Project Timeline-OPM updat'!$D$8:$I$65,MATCH(1,('NONG Project Timeline-OPM updat'!$B$8:$B$65=N7)*('NONG Project Timeline-OPM updat'!$C$8:$C$65=O7),0),MATCH(P7,'NONG Project Timeline-OPM updat'!$D$5:$I$5,0))-14} -> -14 | T7: =S7-A7 -> -46055 | U7: =IFERROR(VLOOKUP(G7,'Bidding list 26'!$B$2:$P$21,15,0),"") | V7: =S7-U7 -> -14 | W7: =if(A7>V7,"Late", "On time") -> Late | X7: New Buy | Z7: Done | AA7: L10-MP-OR5-MVA2601-103OM / L10-MP-OR5-MVA2601-105OM | AB7: Done | AC7: 3 PR: 120 / 120 / 120 => check total AMT 120x 1FSHQ20008 120x 1FSHQ20009 120x 1FSHQ20010 80x 1FSHQ10131 | AD7: Done | AE7: 3 PR: 120 / 120 / 120 => check total AMT 120x 1FSHQ20008 120x 1FSHQ20009 120x 1FSHQ20010 8x + 40x 1FSHQ10131 | AF7: pending | AG7: 30-03-2026 | AH7: EPR2602020009 | AI7: Lấy 120x-1FSHQ20008, cấp trước cho P26-MP CGY4 / lấy 40x 1FSHQ10131 cấp cho MFG G trong đống 100x | AJ7: =B7&G7&J7&N7&X7&AA7 -> MEMini PC (Assy)440OR5New BuyL10-MP-OR5-MVA2601-103OM / L10-MP-OR5-MVA2601-105OM | AK7: =if(Z7="Done",$J7,0) -> 440 | AL7: =if(AB7="Done",$J7,0) -> 440 | AM7: =if(AD7="Done",$J7,0) -> 440 | AN7: =if(AG7<>"",$J7,0) -> 440
A8: 46041 | B8: ME | C8: Nguyen Thi Hai | D8: V1516000 | E8: haint2@fih-foxconn.com | F8: 4493 | G8: Monitor 2 | H8: =vlookup(G8,'Bidding list 26'!$B$4:$G$270,6,0) -> VA1903H-2, 19 inch, VGA cable + HDMI cable / Brand: VIEWSONIC | I8: 1240000 | J8: 360 | K8: =I8*J8 -> 446400000 | L8: OR5 DVT | N8: OR5 | O8: FATP | P8: DVT | Q8: 46076 | R8: =Q8-A8 -> 35 | S8: {=INDEX('NONG Project Timeline-OPM updat'!$D$8:$I$65,MATCH(1,('NONG Project Timeline-OPM updat'!$B$8:$B$65=N8)*('NONG Project Timeline-OPM updat'!$C$8:$C$65=O8),0),MATCH(P8,'NONG Project Timeline-OPM updat'!$D$5:$I$5,0))-14} -> -14 | T8: =S8-A8 -> -46055 | U8: =IFERROR(VLOOKUP(G8,'Bidding list 26'!$B$2:$P$21,15,0),"") | V8: =S8-U8 -> -14 | W8: =if(A8>V8,"Late", "On time") -> Late | X8: New Buy | Z8: Done | AA8: L10-MP-OR5-MVA2601-103OM | AB8: Done | AC8: 90x 1FSHQ20011 90x 1FSHQ20012 90x 1FSHQ20013 90x 1FSHQ20015 | AD8: Done | AE8: 1FSHQ20012 (PO) 1FSHQ20011 (PO) 1FSHQ20015 (PO) 1FSHQ20013 (PO) | AG8: 20-03-2026 | AH8: EPR2602020010: Done 1 phần | AJ8: =B8&G8&J8&N8&X8&AA8 -> MEMonitor 2360OR5New BuyL10-MP-OR5-MVA2601-103OM | AK8: =if(Z8="Done",$J8,0) -> 360 | AL8: =if(AB8="Done",$J8,0) -> 360 | AM8: =if(AD8="Done",$J8,0) -> 360 | AN8: =if(AG8<>"",$J8,0) -> 360
A9: 46041 | B9: ME | C9: Nguyen Thi Hai | D9: V1516000 | E9: haint2@fih-foxconn.com | F9: 4493 | G9: Barcode Scanner NEWLAND HH220-HD, USB cable | H9: =vlookup(G9,'Bidding list 26'!$B$4:$G$270,6,0) -> NEWLAND HH220-HD, USB cable | I9: 2400000 | J9: 330 | K9: =I9*J9 -> 792000000 | L9: OR5 DVT | N9: OR5 | O9: FATP | P9: DVT | Q9: 46076 | R9: =Q9-A9 -> 35 | S9: {=INDEX('NONG Project Timeline-OPM updat'!$D$8:$I$65,MATCH(1,('NONG Project Timeline-OPM updat'!$B$8:$B$65=N9)*('NONG Project Timeline-OPM updat'!$C$8:$C$65=O9),0),MATCH(P9,'NONG Project Timeline-OPM updat'!$D$5:$I$5,0))-14} -> -14 | T9: =S9-A9 -> -46055 | U9: =IFERROR(VLOOKUP(G9,'Bidding list 26'!$B$2:$P$21,15,0),"") -> 35 | V9: =S9-U9 -> -49 | W9: =if(A9>V9,"Late", "On time") -> Late | X9: New Buy | Z9: Done | AA9: L10-MP-OR5-MVA2601-103OM | AB9: Done | AC9: VNPR202602040113 | AD9: Done | AE9: VNPO202602090105 | AG9: 28-03-2026 | AH9: EPR2602020011 | AJ9: =B9&G9&J9&N9&X9&AA9 -> MEBarcode Scanner NEWLAND HH220-HD, USB cable330OR5New BuyL10-MP-OR5-MVA2601-103OM | AK9: =if(Z9="Done",$J9,0) -> 330 | AL9: =if(AB9="Done",$J9,0) -> 330 | AM9: =if(AD9="Done",$J9,0) -> 330 | AN9: =if(AG9<>"",$J9,0) -> 330
A10: 46041 | B10: ME | C10: Nguyen Thi Hai | D10: V1516000 | E10: haint2@fih-foxconn.com | F10: 4493 | G10: Barcode Printer ZEBRA | H10: =vlookup(G10,'Bidding list 26'!$B$4:$G$270,6,0) -> ZT610, 600dpi | I10: 48800000 | J10: 16 | K10: =I10*J10 -> 780800000 | L10: OR5 DVT | N10: OR5 | O10: FATP | P10: DVT | Q10: 46076 | R10: =Q10-A10 -> 35 | S10: {=INDEX('NONG Project Timeline-OPM updat'!$D$8:$I$65,MATCH(1,('NONG Project Timeline-OPM updat'!$B$8:$B$65=N10)*('NONG Project Timeline-OPM updat'!$C$8:$C$65=O10),0),MATCH(P10,'NONG Project Timeline-OPM updat'!$D$5:$I$5,0))-14} -> -14 | T10: =S10-A10 -> -46055 | U10: =IFERROR(VLOOKUP(G10,'Bidding list 26'!$B$2:$P$21,15,0),"") -> 50 | V10: =S10-U10 -> -64 | W10: =if(A10>V10,"Late", "On time") -> Late | X10: New Buy | Z10: Done | AA10: L10-MP-OR5-MVA2601-103OM | AB10: Done | AC10: 1FSHQ20007 | AD10: Done | AE10: 1FSHQ20007 | AG10: 30-03-2026 | AH10: EPR2602020012: đã out hết r ( PO: 1FSHQ20007 về làm spare ) | AJ10: =B10&G10&J10&N10&X10&AA10 -> MEBarcode Printer ZEBRA16OR5New BuyL10-MP-OR5-MVA2601-103OM | AK10: =if(Z10="Done",$J10,0) -> 16 | AL10: =if(AB10="Done",$J10,0) -> 16 | AM10: =if(AD10="Done",$J10,0) -> 16 | AN10: =if(AG10<>"",$J10,0) -> 16
A11: 46048 | B11: FAE | C11: Vu Xuan Bach | D11: V1521896 | E11: bachvx@fih-foxconn.com | G11: IPC++ | H11: =vlookup(G11,'Bidding list 26'!$B$4:$G$270,6,0) -> #N/A | I11: 19280000 | J11: 4 | K11: =I11*J11 -> 77120000 | L11: OR6 EVT | N11: OR6 | O11: FATP | P11: EVT | Q11: 46082 | R11: =Q11-A11 -> 34 | S11: {=INDEX('NONG Project Timeline-OPM updat'!$D$8:$I$65,MATCH(1,('NONG Project Timeline-OPM updat'!$B$8:$B$65=N11)*('NONG Project Timeline-OPM updat'!$C$8:$C$65=O11),0),MATCH(P11,'NONG Project Timeline-OPM updat'!$D$5:$I$5,0))-14} -> 46074 | T11: =S11-A11 -> 26 | U11: =IFERROR(VLOOKUP(G11,'Bidding list 26'!$B$2:$P$21,15,0),"") | V11: =S11-U11 -> 46074 | W11: =if(A11>V11,"Late", "On time") -> On time | X11: New Buy | Z11: Done | AA11: FATP-NPI-OR6-MVA2601-106OM | AB11: Done | AC11: 1FSHQ20004 | AD11: Done | AE11: 1FSHQ20004 | AG11: 46081 | AH11: EPR2601310004 | AJ11: =B11&G11&J11&N11&X11&AA11 -> FAEIPC++4OR6New BuyFATP-NPI-OR6-MVA2601-106OM | AK11: =if(Z11="Done",$J11,0) -> 4 | AL11: =if(AB11="Done",$J11,0) -> 4 | AM11: =if(AD11="Done",$J11,0) -> 4 | AN11: =if(AG11<>"",$J11,0) -> 4
A12: 46048 | B12: FAE | C12: Vu Xuan Bach | D12: V1521896 | E12: bachvx@fih-foxconn.com | G12: Monitor 1 | H12: =vlookup(G12,'Bidding list 26'!$B$4:$G$270,6,0) -> DELL E2225HM, 21.5 inch HDMI cable, 3Yrs Wty | I12: 1980000 | J12: 4 | K12: =I12*J12 -> 7920000 | L12: OR6 EVT | N12: OR6 | O12: FATP | P12: EVT | Q12: 46082 | R12: =Q12-A12 -> 34 | S12: {=INDEX('NONG Project Timeline-OPM updat'!$D$8:$I$65,MATCH(1,('NONG Project Timeline-OPM updat'!$B$8:$B$65=N12)*('NONG Project Timeline-OPM updat'!$C$8:$C$65=O12),0),MATCH(P12,'NONG Project Timeline-OPM updat'!$D$5:$I$5,0))-14} -> 46074 | T12: =S12-A12 -> 26 | U12: =IFERROR(VLOOKUP(G12,'Bidding list 26'!$B$2:$P$21,15,0),"") | V12: =S12-U12 -> 46074 | W12: =if(A12>V12,"Late", "On time") -> On time | X12: New Buy | Z12: Done | AA12: FATP-NPI-OR6-MVA2601-106OM | AB12: Done | AC12: 1FSHQ20006 | AD12: Done | AE12: 1FSHQ20006 | AG12: 46081 | AH12: EPR2601310005 | AJ12: =B12&G12&J12&N12&X12&AA12 -> FAEMonitor 14OR6New BuyFATP-NPI-OR6-MVA2601-106OM | AK12: =if(Z12="Done",$J12,0) -> 4 | AL12: =if(AB12="Done",$J12,0) -> 4 | AM12: =if(AD12="Done",$J12,0) -> 4 | AN12: =if(AG12<>"",$J12,0) -> 4
A13: 46051 | B13: PQE | C13: Nguyen Thi Phuong | D13: V1544473 | E13: phuongnt18@fih-foxconn.com | F13: 3802 | G13: IPC | H13: =vlookup(G13,'Bidding list 26'!$B$4:$G$270,6,0) -> #N/A | I13: 10870000 | J13: 4 | K13: =I13*J13 -> 43480000 | L13: Order for Q station on Line LD8-NPI | N13: LD8 | Q13: 46082 | R13: =Q13-A13 -> 31 | S13: {=INDEX('NONG Project Timeline-OPM updat'!$D$8:$I$65,MATCH(1,('NONG Project Timeline-OPM updat'!$B$8:$B$65=N13)*('NONG Project Timeline-OPM updat'!$C$8:$C$65=O13),0),MATCH(P13,'NONG Project Timeline-OPM updat'!$D$5:$I$5,0))-14} -> #N/A | T13: =S13-A13 -> #N/A | U13: =IFERROR(VLOOKUP(G13,'Bidding list 26'!$B$2:$P$21,15,0),"") | V13: =S13-U13 -> #N/A | W13: =if(A13>V13,"Late", "On time") -> #N/A | X13: New Buy | Z13: Done | AA13: FATP-NPI-LD8-MVA2601-111OM | AB13: Done | AC13: 1FSHQ20029 | AD13: Done | AE13: 1FSHQ20029 | AG13: 46080 | AH13: EPR2602130001: Done | AJ13: =B13&G13&J13&N13&X13&AA13 -> PQEIPC4LD8New BuyFATP-NPI-LD8-MVA2601-111OM | AK13: =if(Z13="Done",$J13,0) -> 4 | AL13: =if(AB13="Done",$J13,0) -> 4 | AM13: =if(AD13="Done",$J13,0) -> 4 | AN13: =if(AG13<>"",$J13,0) -> 4
A14: 46051 | B14: PQE | C14: Nguyen Thi Phuong | D14: V1544473 | E14: phuongnt18@fih-foxconn.com | F14: 3802 | G14: Monitor 2 | H14: =vlookup(G14,'Bidding list 26'!$B$4:$G$270,6,0) -> VA1903H-2, 19 inch, VGA cable + HDMI cable / Brand: VIEWSONIC | I14: 1240000 | J14: 4 | K14: =I14*J14 -> 4960000 | L14: Order for Q station on Line LD8-NPI | N14: LD8 | Q14: 46082 | R14: =Q14-A14 -> 31 | S14: {=INDEX('NONG Project Timeline-OPM updat'!$D$8:$I$65,MATCH(1,('NONG Project Timeline-OPM updat'!$B$8:$B$65=N14)*('NONG Project Timeline-OPM updat'!$C$8:$C$65=O14),0),MATCH(P14,'NONG Project Timeline-OPM updat'!$D$5:$I$5,0))-14} -> #N/A | T14: =S14-A14 -> #N/A | U14: =IFERROR(VLOOKUP(G14,'Bidding list 26'!$B$2:$P$21,15,0),"") | V14: =S14-U14 -> #N/A | W14: =if(A14>V14,"Late", "On time") -> #N/A | X14: New Buy | Z14: Done | AB14: Done | AD14: Done | AG14: 46080 | AH14: EPR2602130002: Done | AJ14: =B14&G14&J14&N14&X14&AA14 -> PQEMonitor 24LD8New Buy | AK14: =if(Z14="Done",$J14,0) -> 4 | AL14: =if(AB14="Done",$J14,0) -> 4 | AM14: =if(AD14="Done",$J14,0) -> 4 | AN14: =if(AG14<>"",$J14,0) -> 4
A15: 46051 | B15: PQE | C15: Nguyen Thi Phuong | D15: V1544473 | E15: phuongnt18@fih-foxconn.com | F15: 3802 | G15: Barcode Scanner SEUIC HS505HDP-2530 ,USB cable | H15: =vlookup(G15,'Bidding list 26'!$B$4:$G$270,6,0) -> SEUIC HS505HDP-2530 ,USB cable | I15: 3300000 | J15: 3 | K15: =I15*J15 -> 9900000 | L15: Order for Q station on Line LD8-NPI | N15: LD8 | Q15: 46082 | R15: =Q15-A15 -> 31 | S15: {=INDEX('NONG Project Timeline-OPM updat'!$D$8:$I$65,MATCH(1,('NONG Project Timeline-OPM updat'!$B$8:$B$65=N15)*('NONG Project Timeline-OPM updat'!$C$8:$C$65=O15),0),MATCH(P15,'NONG Project Timeline-OPM updat'!$D$5:$I$5,0))-14} -> #N/A | T15: =S15-A15 -> #N/A | U15: =IFERROR(VLOOKUP(G15,'Bidding list 26'!$B$2:$P$21,15,0),"") -> 50 | V15: =S15-U15 -> #N/A | W15: =if(A15>V15,"Late", "On time") -> #N/A | X15: New Buy | Z15: Done | AA15: FATP-NPI-LD8-MVA2601-110OM | AB15: Done | AC15: VNPR202602060073 | AD15: Done | AE15: VNPO202602110021 | AG15: 46097 | AH15: EPR2602130003 | AJ15: =B15&G15&J15&N15&X15&AA15 -> PQEBarcode Scanner SEUIC HS505HDP-2530 ,USB cable3LD8New BuyFATP-NPI-LD8-MVA2601-110OM | AK15: =if(Z15="Done",$J15,0) -> 3 | AL15: =if(AB15="Done",$J15,0) -> 3 | AM15: =if(AD15="Done",$J15,0) -> 3 | AN15: =if(AG15<>"",$J15,0) -> 3
A16: 46052 | B16: TE | C16: Nguyen Hai Yen | D16: V1549748 | E16: yennh@fih-foxconn.com | F16: 4179 | G16: IPC++ | H16: =vlookup(G16,'Bidding list 26'!$B$4:$G$270,6,0) -> #N/A | I16: 19280000 | J16: 8 | K16: =I16*J16 -> 154240000 | L16: Order for test station on Line LD8-NPI | N16: LD8 | O16: FATP | P16: PVT | Q16: 46082 | R16: =Q16-A16 -> 30 | S16: {=INDEX('NONG Project Timeline-OPM updat'!$D$8:$I$65,MATCH(1,('NONG Project Timeline-OPM updat'!$B$8:$B$65=N16)*('NONG Project Timeline-OPM updat'!$C$8:$C$65=O16),0),MATCH(P16,'NONG Project Timeline-OPM updat'!$D$5:$I$5,0))-14} -> 46160 | T16: =S16-A16 -> 108 | U16: =IFERROR(VLOOKUP(G16,'Bidding list 26'!$B$2:$P$21,15,0),"") | V16: =S16-U16 -> 46160 | W16: =if(A16>V16,"Late", "On time") -> On time | X16: New Buy | Z16: Done | AA16: FATP-NPI-LD8-MVA2601-110OM | AB16: Done | AC16: 1FSHQ20039 | AD16: Done | AE16: 1FSHQ20039 | AG16: 46080 | AH16: EPR2602130004 | AJ16: =B16&G16&J16&N16&X16&AA16 -> TEIPC++8LD8New BuyFATP-NPI-LD8-MVA2601-110OM | AK16: =if(Z16="Done",$J16,0) -> 8 | AL16: =if(AB16="Done",$J16,0) -> 8 | AM16: =if(AD16="Done",$J16,0) -> 8 | AN16: =if(AG16<>"",$J16,0) -> 8
A17: 46052 | B17: TE | C17: Nguyen Hai Yen | D17: V1549748 | E17: yennh@fih-foxconn.com | F17: 4179 | G17: Monitor 2 | H17: =vlookup(G17,'Bidding list 26'!$B$4:$G$270,6,0) -> VA1903H-2, 19 inch, VGA cable + HDMI cable / Brand: VIEWSONIC | I17: 1240000 | J17: 8 | K17: =I17*J17 -> 9920000 | L17: Order for test station on Line LD8-NPI | N17: LD8 | O17: FATP | P17: PVT | Q17: 46082 | R17: =Q17-A17 -> 30 | S17: {=INDEX('NONG Project Timeline-OPM updat'!$D$8:$I$65,MATCH(1,('NONG Project Timeline-OPM updat'!$B$8:$B$65=N17)*('NONG Project Timeline-OPM updat'!$C$8:$C$65=O17),0),MATCH(P17,'NONG Project Timeline-OPM updat'!$D$5:$I$5,0))-14} -> 46160 | T17: =S17-A17 -> 108 | U17: =IFERROR(VLOOKUP(G17,'Bidding list 26'!$B$2:$P$21,15,0),"") | V17: =S17-U17 -> 46160 | W17: =if(A17>V17,"Late", "On time") -> On time | X17: New Buy | Z17: Done | AB17: Done | AD17: Done | AG17: 46080 | AH17: EPR2602130005 : Done | AJ17: =B17&G17&J17&N17&X17&AA17 -> TEMonitor 28LD8New Buy | AK17: =if(Z17="Done",$J17,0) -> 8 | AL17: =if(AB17="Done",$J17,0) -> 8 | AM17: =if(AD17="Done",$J17,0) -> 8 | AN17: =if(AG17<>"",$J17,0) -> 8
A18: 46052 | B18: TE | C18: Nguyen Hai Yen | D18: V1549748 | E18: yennh@fih-foxconn.com | F18: 4179 | G18: Barcode Scanner SEUIC HS505DP, USB cable | H18: =vlookup(G18,'Bidding list 26'!$B$4:$G$270,6,0) -> HS505DP, USB cable | I18: 2300000 | J18: 8 | K18: =I18*J18 -> 18400000 | L18: Order for test station on Line LD8-NPI | N18: LD8 | O18: FATP | P18: PVT | Q18: 46082 | R18: =Q18-A18 -> 30 | S18: {=INDEX('NONG Project Timeline-OPM updat'!$D$8:$I$65,MATCH(1,('NONG Project Timeline-OPM updat'!$B$8:$B$65=N18)*('NONG Project Timeline-OPM updat'!$C$8:$C$65=O18),0),MATCH(P18,'NONG Project Timeline-OPM updat'!$D$5:$I$5,0))-14} -> 46160 | T18: =S18-A18 -> 108 | U18: =IFERROR(VLOOKUP(G18,'Bidding list 26'!$B$2:$P$21,15,0),"") -> 50 | V18: =S18-U18 -> 46110 | W18: =if(A18>V18,"Late", "On time") -> On time | X18: New Buy | Z18: Done | AA18: FATP-NPI-LD8-MVA2601-110OM | AB18: Done | AC18: VNPO202602110021 | AD18: Done | AE18: VNPO202602110021 | AG18: 46097 | AH18: EPR2602130006 | AI18: 46098.558 | AJ18: =B18&G18&J18&N18&X18&AA18 -> TEBarcode Scanner SEUIC HS505DP, USB cable8LD8New BuyFATP-NPI-LD8-MVA2601-110OM | AK18: =if(Z18="Done",$J18,0) -> 8 | AL18: =if(AB18="Done",$J18,0) -> 8 | AM18: =if(AD18="Done",$J18,0) -> 8 | AN18: =if(AG18<>"",$J18,0) -> 8
A19: 46052 | B19: WH | C19: Le Thi Lich | D19: V1525678 | E19: lichlt@fih-foxconn.com | F19: 4478 | G19: IPC | H19: =vlookup(G19,'Bidding list 26'!$B$4:$G$270,6,0) -> #N/A | I19: 10870000 | J19: 3 | K19: =I19*J19 -> 32610000 | L19: LD8 | N19: LD8 | O19: FATP | P19: PVT | Q19: 46076 | R19: =Q19-A19 -> 24 | S19: {=INDEX('NONG Project Timeline-OPM updat'!$D$8:$I$65,MATCH(1,('NONG Project Timeline-OPM updat'!$B$8:$B$65=N19)*('NONG Project Timeline-OPM updat'!$C$8:$C$65=O19),0),MATCH(P19,'NONG Project Timeline-OPM updat'!$D$5:$I$5,0))-14} -> 46160 | T19: =S19-A19 -> 108 | U19: =IFERROR(VLOOKUP(G19,'Bidding list 26'!$B$2:$P$21,15,0),"") | V19: =S19-U19 -> 46160 | W19: =if(A19>V19,"Late", "On time") -> On time | X19: Leverage | Z19: Done | AA19: FATP-NPI-LD8-MVA2601-111OM | AB19: Done | AC19: 1FSHQ20029 | AD19: Done | AE19: 1FSHQ20029 | AG19: 46080 | AH19: EPR2602060001: Done | AJ19: =B19&G19&J19&N19&X19&AA19 -> WHIPC3LD8LeverageFATP-NPI-LD8-MVA2601-111OM | AK19: =if(Z19="Done",$J19,0) -> 3 | AL19: =if(AB19="Done",$J19,0) -> 3 | AM19: =if(AD19="Done",$J19,0) -> 3 | AN19: =if(AG19<>"",$J19,0) -> 3
A20: 46052 | B20: WH | C20: Le Thi Lich | D20: V1525678 | E20: lichlt@fih-foxconn.com | F20: 4478 | G20: Monitor 1 | H20: =vlookup(G20,'Bidding list 26'!$B$4:$G$270,6,0) -> DELL E2225HM, 21.5 inch HDMI cable, 3Yrs Wty | I20: 1980000 | J20: 3 | K20: =I20*J20 -> 5940000 | L20: LD8 | N20: LD8 | O20: FATP | P20: PVT | Q20: 46076 | R20: =Q20-A20 -> 24 | S20: {=INDEX('NONG Project Timeline-OPM updat'!$D$8:$I$65,MATCH(1,('NONG Project Timeline-OPM updat'!$B$8:$B$65=N20)*('NONG Project Timeline-OPM updat'!$C$8:$C$65=O20),0),MATCH(P20,'NONG Project Timeline-OPM updat'!$D$5:$I$5,0))-14} -> 46160 | T20: =S20-A20 -> 108 | U20: =IFERROR(VLOOKUP(G20,'Bidding list 26'!$B$2:$P$21,15,0),"") | V20: =S20-U20 -> 46160 | W20: =if(A20>V20,"Late", "On time") -> On time | X20: New Buy | Z20: Done | AA20: FATP-NPI-LD8-MVA2601-110OM | AB20: Done | AC20: 1FSHQ20037 | AD20: Done | AE20: 1FSHQ20037 | AG20: 46080 | AH20: EPR2602070002 | AJ20: =B20&G20&J20&N20&X20&AA20 -> WHMonitor 13LD8New BuyFATP-NPI-LD8-MVA2601-110OM | AK20: =if(Z20="Done",$J20,0) -> 3 | AL20: =if(AB20="Done",$J20,0) -> 3 | AM20: =if(AD20="Done",$J20,0) -> 3 | AN20: =if(AG20<>"",$J20,0) -> 3
A21: 46052 | B21: WH | C21: Le Thi Lich | D21: V1525678 | E21: lichlt@fih-foxconn.com | F21: 4478 | G21: Barcode Printer ZEBRA | H21: =vlookup(G21,'Bidding list 26'!$B$4:$G$270,6,0) -> ZT610, 600dpi | I21: 48800000 | J21: 1 | K21: =I21*J21 -> 48800000 | L21: LD8 | N21: LD8 | O21: FATP | P21: PVT | Q21: 46076 | R21: =Q21-A21 -> 24 | S21: {=INDEX('NONG Project Timeline-OPM updat'!$D$8:$I$65,MATCH(1,('NONG Project Timeline-OPM updat'!$B$8:$B$65=N21)*('NONG Project Timeline-OPM updat'!$C$8:$C$65=O21),0),MATCH(P21,'NONG Project Timeline-OPM updat'!$D$5:$I$5,0))-14} -> 46160 | T21: =S21-A21 -> 108 | U21: =IFERROR(VLOOKUP(G21,'Bidding list 26'!$B$2:$P$21,15,0),"") -> 50 | V21: =S21-U21 -> 46110 | W21: =if(A21>V21,"Late", "On time") -> On time | X21: New Buy | Z21: Done | AA21: FATP-NPI-LD8-MVA2601-110OM | AB21: Done | AC21: 1FSHQ20036 | AD21: Done | AE21: 1FSHQ20036 | AG21: 46104 | AH21: EPR2602070003: Done | AJ21: =B21&G21&J21&N21&X21&AA21 -> WHBarcode Printer ZEBRA1LD8New BuyFATP-NPI-LD8-MVA2601-110OM | AK21: =if(Z21="Done",$J21,0) -> 1 | AL21: =if(AB21="Done",$J21,0) -> 1 | AM21: =if(AD21="Done",$J21,0) -> 1 | AN21: =if(AG21<>"",$J21,0) -> 1
A22: 46052 | B22: WH | C22: Le Thi Lich | D22: V1525678 | E22: lichlt@fih-foxconn.com | F22: 4478 | G22: PDA CHAINWAY C61-4850 | H22: =vlookup(G22,'Bidding list 26'!$B$4:$G$270,6,0) -> C61-4850, Not including RFID module. Includes: 64GB 27-key Android 11, controller with battery, charging dock, charging adapter, glass screen protector | I22: 15500000 | J22: 3 | K22: =I22*J22 -> 46500000 | L22: LD8 | N22: LD8 | O22: FATP | P22: PVT | Q22: 46076 | R22: =Q22-A22 -> 24 | S22: {=INDEX('NONG Project Timeline-OPM updat'!$D$8:$I$65,MATCH(1,('NONG Project Timeline-OPM updat'!$B$8:$B$65=N22)*('NONG Project Timeline-OPM updat'!$C$8:$C$65=O22),0),MATCH(P22,'NONG Project Timeline-OPM updat'!$D$5:$I$5,0))-14} -> 46160 | T22: =S22-A22 -> 108 | U22: =IFERROR(VLOOKUP(G22,'Bidding list 26'!$B$2:$P$21,15,0),"") -> 65 | V22: =S22-U22 -> 46095 | W22: =if(A22>V22,"Late", "On time") -> On time | X22: New Buy | Z22: Done | AA22: FATP-NPI-LD8-MVA2602-113OM | AB22: Done | AC22: VNPR202602050240 | AD22: Done | AE22: VNPO202602110021 | AG22: 46149 | AH22: EPR2602070004 | AI22: đã out chị Lịch tại OM Office 30May | AJ22: =B22&G22&J22&N22&X22&AA22 -> WHPDA CHAINWAY C61-48503LD8New BuyFATP-NPI-LD8-MVA2602-113OM | AK22: =if(Z22="Done",$J22,0) -> 3 | AL22: =if(AB22="Done",$J22,0) -> 3 | AM22: =if(AD22="Done",$J22,0) -> 3 | AN22: =if(AG22<>"",$J22,0) -> 3
A23: 46052 | B23: MFG | C23: Đặng Thị Ban | D23: V1547168 | E23: bandt1@fih-foxconn.com | F23: 4324 | G23: Monitor 2 | H23: =vlookup(G23,'Bidding list 26'!$B$4:$G$270,6,0) -> VA1903H-2, 19 inch, VGA cable + HDMI cable / Brand: VIEWSONIC | I23: 1240000 | J23: 10 | K23: =I23*J23 -> 12400000 | L23: LD8 | N23: LD8 | O23: FATP | P23: PVT | Q23: 46076 | R23: =Q23-A23 -> 24 | S23: {=INDEX('NONG Project Timeline-OPM updat'!$D$8:$I$65,MATCH(1,('NONG Project Timeline-OPM updat'!$B$8:$B$65=N23)*('NONG Project Timeline-OPM updat'!$C$8:$C$65=O23),0),MATCH(P23,'NONG Project Timeline-OPM updat'!$D$5:$I$5,0))-14} -> 46160 | T23: =S23-A23 -> 108 | U23: =IFERROR(VLOOKUP(G23,'Bidding list 26'!$B$2:$P$21,15,0),"") | V23: =S23-U23 -> 46160 | W23: =if(A23>V23,"Late", "On time") -> On time | X23: New Buy | Z23: Done | AB23: Done | AD23: Done | AG23: 46080 | AH23: EPR2602070005 | AJ23: =B23&G23&J23&N23&X23&AA23 -> MFG Monitor 210LD8New Buy | AK23: =if(Z23="Done",$J23,0) -> 10 | AL23: =if(AB23="Done",$J23,0) -> 10 | AM23: =if(AD23="Done",$J23,0) -> 10 | AN23: =if(AG23<>"",$J23,0) -> 10
A24: 46052 | B24: MFG | C24: Đặng Thị Ban | D24: V1547168 | E24: bandt1@fih-foxconn.com | F24: 4324 | G24: IPC+ | H24: =vlookup(G24,'Bidding list 26'!$B$4:$G$270,6,0) -> #N/A | I24: 14200000 | J24: 1 | K24: =I24*J24 -> 14200000 | L24: LD8 | N24: LD8 | O24: FATP | P24: PVT | Q24: 46076 | R24: =Q24-A24 -> 24 | S24: {=INDEX('NONG Project Timeline-OPM updat'!$D$8:$I$65,MATCH(1,('NONG Project Timeline-OPM updat'!$B$8:$B$65=N24)*('NONG Project Timeline-OPM updat'!$C$8:$C$65=O24),0),MATCH(P24,'NONG Project Timeline-OPM updat'!$D$5:$I$5,0))-14} -> 46160 | T24: =S24-A24 -> 108 | U24: =IFERROR(VLOOKUP(G24,'Bidding list 26'!$B$2:$P$21,15,0),"") | V24: =S24-U24 -> 46160 | W24: =if(A24>V24,"Late", "On time") -> On time | X24: New Buy | Z24: Done | AA24: FATP-NPI-LD8-MVA2601-110OM | AB24: Done | AC24: 1FSHQ20040 | AD24: Done | AE24: 1FSHQ20040 | AG24: 46080 | AH24: EPR2602070006 | AJ24: =B24&G24&J24&N24&X24&AA24 -> MFG IPC+1LD8New BuyFATP-NPI-LD8-MVA2601-110OM | AK24: =if(Z24="Done",$J24,0) -> 1 | AL24: =if(AB24="Done",$J24,0) -> 1 | AM24: =if(AD24="Done",$J24,0) -> 1 | AN24: =if(AG24<>"",$J24,0) -> 1
A25: 46052 | B25: MFG | C25: Đặng Thị Ban | D25: V1547168 | E25: bandt1@fih-foxconn.com | F25: 4324 | G25: Barcode Scanner SEUIC HS505DP, USB cable | H25: =vlookup(G25,'Bidding list 26'!$B$4:$G$270,6,0) -> HS505DP, USB cable | I25: 2300000 | J25: 9 | K25: =I25*J25 -> 20700000 | L25: LD8 | N25: LD8 | O25: FATP | P25: PVT | Q25: 46076 | R25: =Q25-A25 -> 24 | S25: {=INDEX('NONG Project Timeline-OPM updat'!$D$8:$I$65,MATCH(1,('NONG Project Timeline-OPM updat'!$B$8:$B$65=N25)*('NONG Project Timeline-OPM updat'!$C$8:$C$65=O25),0),MATCH(P25,'NONG Project Timeline-OPM updat'!$D$5:$I$5,0))-14} -> 46160 | T25: =S25-A25 -> 108 | U25: =IFERROR(VLOOKUP(G25,'Bidding list 26'!$B$2:$P$21,15,0),"") -> 50 | V25: =S25-U25 -> 46110 | W25: =if(A25>V25,"Late", "On time") -> On time | X25: New Buy | Z25: Done | AA25: FATP-NPI-LD8-MVA2601-110OM | AB25: Done | AC25: VNPO202602110021 | AD25: Done | AE25: VNPO202602110021 | AG25: 46112 | AH25: EPR2602070007 | AI25: 46102.452 | AJ25: =B25&G25&J25&N25&X25&AA25 -> MFG Barcode Scanner SEUIC HS505DP, USB cable9LD8New BuyFATP-NPI-LD8-MVA2601-110OM | AK25: =if(Z25="Done",$J25,0) -> 9 | AL25: =if(AB25="Done",$J25,0) -> 9 | AM25: =if(AD25="Done",$J25,0) -> 9 | AN25: =if(AG25<>"",$J25,0) -> 9
A26: 46052 | B26: MFG | C26: Đặng Thị Ban | D26: V1547168 | E26: bandt1@fih-foxconn.com | F26: 4324 | G26: Barcode Printer ZEBRA | H26: =vlookup(G26,'Bidding list 26'!$B$4:$G$270,6,0) -> ZT610, 600dpi | I26: 48800000 | J26: 3 | K26: =I26*J26 -> 146400000 | L26: LD8 | N26: LD8 | O26: FATP | P26: PVT | Q26: 46076 | R26: =Q26-A26 -> 24 | S26: {=INDEX('NONG Project Timeline-OPM updat'!$D$8:$I$65,MATCH(1,('NONG Project Timeline-OPM updat'!$B$8:$B$65=N26)*('NONG Project Timeline-OPM updat'!$C$8:$C$65=O26),0),MATCH(P26,'NONG Project Timeline-OPM updat'!$D$5:$I$5,0))-14} -> 46160 | T26: =S26-A26 -> 108 | U26: =IFERROR(VLOOKUP(G26,'Bidding list 26'!$B$2:$P$21,15,0),"") -> 50 | V26: =S26-U26 -> 46110 | W26: =if(A26>V26,"Late", "On time") -> On time | X26: New Buy | Z26: Done | AA26: FATP-NPI-LD8-MVA2601-110OM | AB26: Done | AC26: 1FSHQ20036 | AD26: Done | AE26: 1FSHQ20036 | AG26: 46080 | AH26: EPR2602070008: Done | AJ26: =B26&G26&J26&N26&X26&AA26 -> MFG Barcode Printer ZEBRA3LD8New BuyFATP-NPI-LD8-MVA2601-110OM | AK26: =if(Z26="Done",$J26,0) -> 3 | AL26: =if(AB26="Done",$J26,0) -> 3 | AM26: =if(AD26="Done",$J26,0) -> 3 | AN26: =if(AG26<>"",$J26,0) -> 3
A27: 46052 | B27: MFG | C27: Đặng Thị Ban | D27: V1547168 | E27: bandt1@fih-foxconn.com | F27: 4324 | G27: IPC | H27: =vlookup(G27,'Bidding list 26'!$B$4:$G$270,6,0) -> #N/A | I27: 10870000 | J27: 10 | K27: =I27*J27 -> 108700000 | L27: LD8 | N27: LD8 | O27: FATP | P27: PVT | Q27: 46076 | R27: =Q27-A27 -> 24 | S27: {=INDEX('NONG Project Timeline-OPM updat'!$D$8:$I$65,MATCH(1,('NONG Project Timeline-OPM updat'!$B$8:$B$65=N27)*('NONG Project Timeline-OPM updat'!$C$8:$C$65=O27),0),MATCH(P27,'NONG Project Timeline-OPM updat'!$D$5:$I$5,0))-14} -> 46160 | T27: =S27-A27 -> 108 | U27: =IFERROR(VLOOKUP(G27,'Bidding list 26'!$B$2:$P$21,15,0),"") | V27: =S27-U27 -> 46160 | W27: =if(A27>V27,"Late", "On time") -> On time | X27: New Buy | Z27: Done | AA27: FATP-NPI-LD8-MVA2601-111OM | AB27: Done | AC27: 1FSHQ20029 | AD27: Done | AE27: 1FSHQ20029 | AG27: 46080 | AH27: EPR2602070009: Done | AJ27: =B27&G27&J27&N27&X27&AA27 -> MFG IPC10LD8New BuyFATP-NPI-LD8-MVA2601-111OM | AK27: =if(Z27="Done",$J27,0) -> 10 | AL27: =if(AB27="Done",$J27,0) -> 10 | AM27: =if(AD27="Done",$J27,0) -> 10 | AN27: =if(AG27<>"",$J27,0) -> 10
A28: 46052 | B28: IQC | C28: Nguyễn Thị Hiền | D28: V1524357 | E28: hiennt3@fih-foxconn.com | F28: 4160 | G28: IPC | H28: =vlookup(G28,'Bidding list 26'!$B$4:$G$270,6,0) -> #N/A | I28: 10870000 | J28: 10 | K28: =I28*J28 -> 108700000 | L28: LD8 | N28: LD8 | Q28: 46076 | R28: =Q28-A28 -> 24 | S28: {=INDEX('NONG Project Timeline-OPM updat'!$D$8:$I$65,MATCH(1,('NONG Project Timeline-OPM updat'!$B$8:$B$65=N28)*('NONG Project Timeline-OPM updat'!$C$8:$C$65=O28),0),MATCH(P28,'NONG Project Timeline-OPM updat'!$D$5:$I$5,0))-14} -> #N/A | T28: =S28-A28 -> #N/A | U28: =IFERROR(VLOOKUP(G28,'Bidding list 26'!$B$2:$P$21,15,0),"") | V28: =S28-U28 -> #N/A | W28: =if(A28>V28,"Late", "On time") -> #N/A | X28: New Buy | Z28: Done | AA28: FATP-NPI-LD8-MVA2601-111OM | AB28: Done | AC28: 1FSHQ20029 | AD28: Done | AE28: 1FSHQ20029 | AG28: 46080 | AH28: EPR2602070010: Done | AJ28: =B28&G28&J28&N28&X28&AA28 -> IQCIPC10LD8New BuyFATP-NPI-LD8-MVA2601-111OM | AK28: =if(Z28="Done",$J28,0) -> 10 | AL28: =if(AB28="Done",$J28,0) -> 10 | AM28: =if(AD28="Done",$J28,0) -> 10 | AN28: =if(AG28<>"",$J28,0) -> 10
A29: 46052 | B29: IQC | C29: Nguyễn Thị Hiền | D29: V1524357 | E29: hiennt3@fih-foxconn.com | F29: 4160 | G29: Monitor 2 | H29: =vlookup(G29,'Bidding list 26'!$B$4:$G$270,6,0) -> VA1903H-2, 19 inch, VGA cable + HDMI cable / Brand: VIEWSONIC | I29: 1240000 | J29: 10 | K29: =I29*J29 -> 12400000 | L29: LD8 | N29: LD8 | Q29: 46076 | R29: =Q29-A29 -> 24 | S29: {=INDEX('NONG Project Timeline-OPM updat'!$D$8:$I$65,MATCH(1,('NONG Project Timeline-OPM updat'!$B$8:$B$65=N29)*('NONG Project Timeline-OPM updat'!$C$8:$C$65=O29),0),MATCH(P29,'NONG Project Timeline-OPM updat'!$D$5:$I$5,0))-14} -> #N/A | T29: =S29-A29 -> #N/A | U29: =IFERROR(VLOOKUP(G29,'Bidding list 26'!$B$2:$P$21,15,0),"") | V29: =S29-U29 -> #N/A | W29: =if(A29>V29,"Late", "On time") -> #N/A | X29: New Buy | Z29: Done | AB29: Done | AD29: Done | AG29: 46080 | AH29: EPR2602070011: Done | AJ29: =B29&G29&J29&N29&X29&AA29 -> IQCMonitor 210LD8New Buy | AK29: =if(Z29="Done",$J29,0) -> 10 | AL29: =if(AB29="Done",$J29,0) -> 10 | AM29: =if(AD29="Done",$J29,0) -> 10 | AN29: =if(AG29<>"",$J29,0) -> 10
A30: 46052 | B30: IQC | C30: Nguyễn Thị Hiền | D30: V1524357 | E30: hiennt3@fih-foxconn.com | F30: 4160 | G30: Barcode Scanner SEUIC HS505DP, USB cable | H30: =vlookup(G30,'Bidding list 26'!$B$4:$G$270,6,0) -> HS505DP, USB cable | I30: 2300000 | J30: 10 | K30: =I30*J30 -> 23000000 | L30: LD8 | N30: LD8 | Q30: 46076 | R30: =Q30-A30 -> 24 | S30: {=INDEX('NONG Project Timeline-OPM updat'!$D$8:$I$65,MATCH(1,('NONG Project Timeline-OPM updat'!$B$8:$B$65=N30)*('NONG Project Timeline-OPM updat'!$C$8:$C$65=O30),0),MATCH(P30,'NONG Project Timeline-OPM updat'!$D$5:$I$5,0))-14} -> #N/A | T30: =S30-A30 -> #N/A | U30: =IFERROR(VLOOKUP(G30,'Bidding list 26'!$B$2:$P$21,15,0),"") -> 50 | V30: =S30-U30 -> #N/A | W30: =if(A30>V30,"Late", "On time") -> #N/A | X30: New Buy | Z30: Done | AA30: FATP-NPI-LD8-MVA2601-110OM | AB30: Done | AC30: VNPO202602110021 | AD30: Done | AE30: VNPO202602110021 | AG30: 46112 | AH30: EPR2602070012 | AI30: 46098.558 | AJ30: =B30&G30&J30&N30&X30&AA30 -> IQCBarcode Scanner SEUIC HS505DP, USB cable10LD8New BuyFATP-NPI-LD8-MVA2601-110OM | AK30: =if(Z30="Done",$J30,0) -> 10 | AL30: =if(AB30="Done",$J30,0) -> 10 | AM30: =if(AD30="Done",$J30,0) -> 10 | AN30: =if(AG30<>"",$J30,0) -> 10
A31: 46062 | B31: MFG | C31: Đặng Thị Ban | D31: V1547168 | E31: bandt1@fih-foxconn.com | F31: 4324 | G31: Monitor 2 | H31: =vlookup(G31,'Bidding list 26'!$B$4:$G$270,6,0) -> VA1903H-2, 19 inch, VGA cable + HDMI cable / Brand: VIEWSONIC | I31: 1240000 | J31: 18 | K31: =I31*J31 -> 22320000 | L31: MH2 | N31: MH2 | O31: FATP | P31: PVT | R31: =Q31-A31 -> -46062 | S31: {=INDEX('NONG Project Timeline-OPM updat'!$D$8:$I$65,MATCH(1,('NONG Project Timeline-OPM updat'!$B$8:$B$65=N31)*('NONG Project Timeline-OPM updat'!$C$8:$C$65=O31),0),MATCH(P31,'NONG Project Timeline-OPM updat'!$D$5:$I$5,0))-14} -> 46178 | T31: =S31-A31 -> 116 | U31: =IFERROR(VLOOKUP(G31,'Bidding list 26'!$B$2:$P$21,15,0),"") | V31: =S31-U31 -> 46178 | W31: =if(A31>V31,"Late", "On time") -> On time | X31: New Buy | Z31: Done | AA31: FATP-NPI-MH2-MVA2602-114OM | AB31: Done | AC31: 1FSHQ20106 | AD31: Done | AE31: 1FSHQ20106 | AG31: 46097 | AH31: EPR2603070001 | AJ31: =B31&G31&J31&N31&X31&AA31 -> MFGMonitor 218MH2New BuyFATP-NPI-MH2-MVA2602-114OM | AK31: =if(Z31="Done",$J31,0) -> 18 | AL31: =if(AB31="Done",$J31,0) -> 18 | AM31: =if(AD31="Done",$J31,0) -> 18 | AN31: =if(AG31<>"",$J31,0) -> 18
A32: 46062 | B32: MFG | C32: Đặng Thị Ban | D32: V1547168 | E32: bandt1@fih-foxconn.com | F32: 4324 | G32: Mini PC (Assy) | H32: =vlookup(G32,'Bidding list 26'!$B$4:$G$270,6,0) -> #N/A | I32: 7800000 | J32: 18 | K32: =I32*J32 -> 140400000 | L32: MH2 | N32: MH2 | O32: FATP | P32: PVT | R32: =Q32-A32 -> -46062 | S32: {=INDEX('NONG Project Timeline-OPM updat'!$D$8:$I$65,MATCH(1,('NONG Project Timeline-OPM updat'!$B$8:$B$65=N32)*('NONG Project Timeline-OPM updat'!$C$8:$C$65=O32),0),MATCH(P32,'NONG Project Timeline-OPM updat'!$D$5:$I$5,0))-14} -> 46178 | T32: =S32-A32 -> 116 | U32: =IFERROR(VLOOKUP(G32,'Bidding list 26'!$B$2:$P$21,15,0),"") | V32: =S32-U32 -> 46178 | W32: =if(A32>V32,"Late", "On time") -> On time | X32: New Buy | Z32: Done | AA32: FATP-NPI-MH2-MVA2602-114OM | AB32: Done | AC32: 1FSHQ20104 | AD32: Done | AE32: 1FSHQ20104 | AF32: pending | AG32: Lấy hết PO 1FSHQ20104 trả cho MFG G // trả đơn Ban MFG thực tế 18x MINI PC ASUS | AH32: EPR2603070002: đã cancel // EPR2606240002 | AJ32: =B32&G32&J32&N32&X32&AA32 -> MFGMini PC (Assy)18MH2New BuyFATP-NPI-MH2-MVA2602-114OM | AK32: =if(Z32="Done",$J32,0) -> 18 | AL32: =if(AB32="Done",$J32,0) -> 18 | AM32: =if(AD32="Done",$J32,0) -> 18 | AN32: =if(AG32<>"",$J32,0) -> 18
A33: 46062 | B33: MFG | C33: Đặng Thị Ban | D33: V1547168 | E33: bandt1@fih-foxconn.com | F33: 4324 | G33: Barcode Scanner SEUIC HS505HDP-2530 ,USB cable | H33: =vlookup(G33,'Bidding list 26'!$B$4:$G$270,6,0) -> SEUIC HS505HDP-2530 ,USB cable | I33: 3300000 | J33: 18 | K33: =I33*J33 -> 59400000 | L33: MH2 | N33: MH2 | O33: FATP | P33: PVT | R33: =Q33-A33 -> -46062 | S33: {=INDEX('NONG Project Timeline-OPM updat'!$D$8:$I$65,MATCH(1,('NONG Project Timeline-OPM updat'!$B$8:$B$65=N33)*('NONG Project Timeline-OPM updat'!$C$8:$C$65=O33),0),MATCH(P33,'NONG Project Timeline-OPM updat'!$D$5:$I$5,0))-14} -> 46178 | T33: =S33-A33 -> 116 | U33: =IFERROR(VLOOKUP(G33,'Bidding list 26'!$B$2:$P$21,15,0),"") -> 50 | V33: =S33-U33 -> 46128 | W33: =if(A33>V33,"Late", "On time") -> On time | X33: New Buy | Z33: Done | AA33: FATP-NPI-MH2-MVA2603-22OM | AB33: Done | AC33: VNPR202603230176 | AD33: Done | AE33: VNPO202603280076 | AG33: 46137 | AH33: EPR2603210001 | AJ33: =B33&G33&J33&N33&X33&AA33 -> MFGBarcode Scanner SEUIC HS505HDP-2530 ,USB cable18MH2New BuyFATP-NPI-MH2-MVA2603-22OM | AK33: =if(Z33="Done",$J33,0) -> 18 | AL33: =if(AB33="Done",$J33,0) -> 18 | AM33: =if(AD33="Done",$J33,0) -> 18 | AN33: =if(AG33<>"",$J33,0) -> 18
A34: 46076 | B34: TE | C34: Nguyen Hai Yen | D34: V1549748 | E34: yennh@fih-foxconn.com | F34: 4179 | G34: IPC+(updated) | H34: =vlookup(G34,'Bidding list 26'!$B$4:$G$270,6,0) -> Pro Tower QCT1250, Ultra 5 235, Ram 16GB DDR5, SSD 512GB, Integrated graphics card, Power 180W, HDMI & DP Port, Keyboard and Mouse, 3Yrs Wty | I34: 18717000 | J34: 3 | K34: =I34*J34 -> 56151000 | L34: MH2 | N34: MH2 | O34: FATP | P34: PVT | Q34: 46090 | R34: =Q34-A34 -> 14 | S34: {=INDEX('NONG Project Timeline-OPM updat'!$D$8:$I$65,MATCH(1,('NONG Project Timeline-OPM updat'!$B$8:$B$65=N34)*('NONG Project Timeline-OPM updat'!$C$8:$C$65=O34),0),MATCH(P34,'NONG Project Timeline-OPM updat'!$D$5:$I$5,0))-14} -> 46178 | T34: =S34-A34 -> 102 | U34: =IFERROR(VLOOKUP(G34,'Bidding list 26'!$B$2:$P$21,15,0),"") -> 70 | V34: =S34-U34 -> 46108 | W34: =if(A34>V34,"Late", "On time") -> On time | X34: New Buy | Y34: G | Z34: Done | AA34: FATP-NPI-MH2-MVA2603-09OM | AB34: Done | AC34: 1FSHQ30126 | AD34: Done | AE34: 1FSHQ30126 | AG34: 46135 | AH34: EPR2603210002 | AJ34: =B34&G34&J34&N34&X34&AA34 -> TEIPC+(updated)3MH2New BuyFATP-NPI-MH2-MVA2603-09OM | AK34: =if(Z34="Done",$J34,0) -> 3 | AL34: =if(AB34="Done",$J34,0) -> 3 | AM34: =if(AD34="Done",$J34,0) -> 3 | AN34: =if(AG34<>"",$J34,0) -> 3
A35: 46076 | B35: TE | C35: Nguyen Hai Yen | D35: V1549748 | E35: yennh@fih-foxconn.com | F35: 4179 | G35: Monitor 2 | H35: =vlookup(G35,'Bidding list 26'!$B$4:$G$270,6,0) -> VA1903H-2, 19 inch, VGA cable + HDMI cable / Brand: VIEWSONIC | I35: 1240000 | J35: 3 | K35: =I35*J35 -> 3720000 | L35: MH2 | N35: MH2 | O35: FATP | P35: PVT | Q35: 46090 | R35: =Q35-A35 -> 14 | S35: {=INDEX('NONG Project Timeline-OPM updat'!$D$8:$I$65,MATCH(1,('NONG Project Timeline-OPM updat'!$B$8:$B$65=N35)*('NONG Project Timeline-OPM updat'!$C$8:$C$65=O35),0),MATCH(P35,'NONG Project Timeline-OPM updat'!$D$5:$I$5,0))-14} -> 46178 | T35: =S35-A35 -> 102 | U35: =IFERROR(VLOOKUP(G35,'Bidding list 26'!$B$2:$P$21,15,0),"") | V35: =S35-U35 -> 46178 | W35: =if(A35>V35,"Late", "On time") -> On time | X35: New Buy | Z35: Done | AA35: FATP-NPI-MH2-MVA2602-116OM | AB35: Done | AC35: 1FSHQ30023 | AD35: Done | AE35: 1FSHQ30023 | AG35: 46097 | AH35: EPR2603070003 | AJ35: =B35&G35&J35&N35&X35&AA35 -> TEMonitor 23MH2New BuyFATP-NPI-MH2-MVA2602-116OM | AK35: =if(Z35="Done",$J35,0) -> 3 | AL35: =if(AB35="Done",$J35,0) -> 3 | AM35: =if(AD35="Done",$J35,0) -> 3 | AN35: =if(AG35<>"",$J35,0) -> 3
A36: 46076 | B36: TE | C36: Nguyen Hai Yen | D36: V1549748 | E36: yennh@fih-foxconn.com | F36: 4179 | G36: Barcode Scanner SEUIC HS505DP, USB cable | H36: =vlookup(G36,'Bidding list 26'!$B$4:$G$270,6,0) -> HS505DP, USB cable | I36: 2300000 | J36: 3 | K36: =I36*J36 -> 6900000 | L36: MH2 | N36: MH2 | O36: FATP | P36: PVT | Q36: 46090 | R36: =Q36-A36 -> 14 | S36: {=INDEX('NONG Project Timeline-OPM updat'!$D$8:$I$65,MATCH(1,('NONG Project Timeline-OPM updat'!$B$8:$B$65=N36)*('NONG Project Timeline-OPM updat'!$C$8:$C$65=O36),0),MATCH(P36,'NONG Project Timeline-OPM updat'!$D$5:$I$5,0))-14} -> 46178 | T36: =S36-A36 -> 102 | U36: =IFERROR(VLOOKUP(G36,'Bidding list 26'!$B$2:$P$21,15,0),"") -> 50 | V36: =S36-U36 -> 46128 | W36: =if(A36>V36,"Late", "On time") -> On time | X36: New Buy | Z36: Done | AA36: FATP-NPI-MH2-MVA2603-22OM | AB36: Done | AC36: VNPR202603230176 | AD36: Done | AE36: VNPO202603280076 | AF36: 46137 | AG36: Lấy 3x từ 35 con VNPO202604150030 MFG G (180/215) trả đơn trước | AH36: EPR2603210004 | AJ36: =B36&G36&J36&N36&X36&AA36 -> TEBarcode Scanner SEUIC HS505DP, USB cable3MH2New BuyFATP-NPI-MH2-MVA2603-22OM | AK36: =if(Z36="Done",$J36,0) -> 3 | AL36: =if(AB36="Done",$J36,0) -> 3 | AM36: =if(AD36="Done",$J36,0) -> 3 | AN36: =if(AG36<>"",$J36,0) -> 3
A37: 46077 | B37: PQE | C37: Vũ Đăng Hoạch | D37: V1546253 | E37: hoachvd@fih-foxconn.com | F37: 4006 | G37: Monitor 2 | H37: =vlookup(G37,'Bidding list 26'!$B$4:$G$270,6,0) -> VA1903H-2, 19 inch, VGA cable + HDMI cable / Brand: VIEWSONIC | I37: 1240000 | J37: 4 | K37: =I37*J37 -> 4960000 | L37: BM2 | N37: BM2 | O37: FATP | P37: PVT | Q37: 46090 | R37: =Q37-A37 -> 13 | S37: {=INDEX('NONG Project Timeline-OPM updat'!$D$8:$I$65,MATCH(1,('NONG Project Timeline-OPM updat'!$B$8:$B$65=N37)*('NONG Project Timeline-OPM updat'!$C$8:$C$65=O37),0),MATCH(P37,'NONG Project Timeline-OPM updat'!$D$5:$I$5,0))-14} -> -14 | T37: =S37-A37 -> -46091 | U37: =IFERROR(VLOOKUP(G37,'Bidding list 26'!$B$2:$P$21,15,0),"") | V37: =S37-U37 -> -14 | W37: =if(A37>V37,"Late", "On time") -> Late | X37: New Buy | Z37: Done | AA37: FATP-NPI-BM2-MVA2602-118OM | AB37: Done | AC37: 1FSHQ30070 | AD37: Done | AE37: 1FSHQ30070 | AG37: 46141 | AH37: EPR2603070004 | AJ37: =B37&G37&J37&N37&X37&AA37 -> PQEMonitor 24BM2New BuyFATP-NPI-BM2-MVA2602-118OM | AK37: =if(Z37="Done",$J37,0) -> 4 | AL37: =if(AB37="Done",$J37,0) -> 4 | AM37: =if(AD37="Done",$J37,0) -> 4 | AN37: =if(AG37<>"",$J37,0) -> 4
A38: 46077 | B38: PQE | C38: Vũ Đăng Hoạch | D38: V1546253 | E38: hoachvd@fih-foxconn.com | F38: 4006 | G38: IPC++(updated) | H38: =vlookup(G38,'Bidding list 26'!$B$4:$G$270,6,0) -> Pro Tower QCT1250, Ultra 7 265, Ram 16GB DDR5, SSD 512GB, Integrated graphics card, Power 180W, HDMI & DP Port, Keyboard and Mouse, 3Yrs Wty | I38: 26752000 | J38: 3 | K38: =I38*J38 -> 80256000 | L38: BM2 | N38: BM2 | O38: FATP | P38: PVT | Q38: 46090 | R38: =Q38-A38 -> 13 | S38: {=INDEX('NONG Project Timeline-OPM updat'!$D$8:$I$65,MATCH(1,('NONG Project Timeline-OPM updat'!$B$8:$B$65=N38)*('NONG Project Timeline-OPM updat'!$C$8:$C$65=O38),0),MATCH(P38,'NONG Project Timeline-OPM updat'!$D$5:$I$5,0))-14} -> -14 | T38: =S38-A38 -> -46091 | U38: =IFERROR(VLOOKUP(G38,'Bidding list 26'!$B$2:$P$21,15,0),"") -> 70 | V38: =S38-U38 -> -84 | W38: =if(A38>V38,"Late", "On time") -> Late | X38: New Buy | Y38: G | Z38: Done | AA38: FATP-NPI-BM2-MVA2603-10OM | AB38: Done | AC38: 1FSHQ30119 | AD38: Done | AE38: 1FSHQ30119 | AG38: 46125 | AH38: EPR2604090001 | AJ38: =B38&G38&J38&N38&X38&AA38 -> PQEIPC++(updated)3BM2New BuyFATP-NPI-BM2-MVA2603-10OM | AK38: =if(Z38="Done",$J38,0) -> 3 | AL38: =if(AB38="Done",$J38,0) -> 3 | AM38: =if(AD38="Done",$J38,0) -> 3 | AN38: =if(AG37<>"",$J38,0) -> 3
A39: 46077 | B39: PQE | C39: Vũ Đăng Hoạch | D39: V1546253 | E39: hoachvd@fih-foxconn.com | F39: 4006 | G39: Mini PC (Assy) | H39: =vlookup(G39,'Bidding list 26'!$B$4:$G$270,6,0) -> #N/A | I39: 7800000 | J39: 14 | K39: =I39*J39 -> 109200000 | L39: BM2 | N39: BM2 | O39: FATP | P39: PVT | Q39: 46090 | R39: =Q39-A39 -> 13 | S39: {=INDEX('NONG Project Timeline-OPM updat'!$D$8:$I$65,MATCH(1,('NONG Project Timeline-OPM updat'!$B$8:$B$65=N39)*('NONG Project Timeline-OPM updat'!$C$8:$C$65=O39),0),MATCH(P39,'NONG Project Timeline-OPM updat'!$D$5:$I$5,0))-14} -> -14 | T39: =S39-A39 -> -46091 | U39: =IFERROR(VLOOKUP(G39,'Bidding list 26'!$B$2:$P$21,15,0),"") | V39: =S39-U39 -> -14 | W39: =if(A39>V39,"Late", "On time") -> Late | X39: New Buy | Z39: Done | AA39: FATP-NPI-BM2-MVA2602-118OM | AB39: Done | AC39: 1FSHQ30071 | AD39: Done | AE39: 1FSHQ30071 | AF39: pending | AG39: Trả 3 PC(ASSY) từ OM-WH trước / lấy hết PO : 1FSHQ30071 cho MFG G | AH39: EPR2603070005 ( 11x Mini PC Lami mua mới + 3x PC(ASSY) Lev ) // EPR2603070005 : 11x Lamitouch : đã cancel // EPR2606240003 | AJ39: =B39&G39&J39&N39&X39&AA39 -> PQEMini PC (Assy)14BM2New BuyFATP-NPI-BM2-MVA2602-118OM | AK39: =if(Z39="Done",$J39,0) -> 14 | AL39: =if(AB39="Done",$J39,0) -> 14 | AM39: =if(AD39="Done",$J39,0) -> 14 | AN39: =if(AG39<>"",$J39,0) -> 14
A40: 46077 | B40: PQE | C40: Vũ Đăng Hoạch | D40: V1546253 | E40: hoachvd@fih-foxconn.com | F40: 4006 | G40: Barcode Scanner SEUIC HS505DP, USB cable | H40: =vlookup(G40,'Bidding list 26'!$B$4:$G$270,6,0) -> HS505DP, USB cable | I40: 2300000 | J40: 16 | K40: =I40*J40 -> 36800000 | L40: BM2 | N40: BM2 | O40: FATP | P40: PVT | Q40: 46090 | R40: =Q40-A40 -> 13 | S40: {=INDEX('NONG Project Timeline-OPM updat'!$D$8:$I$65,MATCH(1,('NONG Project Timeline-OPM updat'!$B$8:$B$65=N40)*('NONG Project Timeline-OPM updat'!$C$8:$C$65=O40),0),MATCH(P40,'NONG Project Timeline-OPM updat'!$D$5:$I$5,0))-14} -> -14 | T40: =S40-A40 -> -46091 | U40: =IFERROR(VLOOKUP(G40,'Bidding list 26'!$B$2:$P$21,15,0),"") -> 50 | V40: =S40-U40 -> -64 | W40: =if(A40>V40,"Late", "On time") -> Late | X40: New Buy | Z40: Done | AA40: FATP-NPI-BM2-MVA2603-23OM | AB40: Done | AC40: VNPR202603230171 | AD40: Done | AE40: VNPO202603280076 | AF40: 46137 | AG40: Lấy 2x từ 35 con VNPO202604150030 MFG G (180/215) trả đơn trước | AH40: EPR2603210007 | AJ40: =B40&G40&J40&N40&X40&AA40 -> PQEBarcode Scanner SEUIC HS505DP, USB cable16BM2New BuyFATP-NPI-BM2-MVA2603-23OM | AK40: =if(Z40="Done",$J40,0) -> 16 | AL40: =if(AB40="Done",$J40,0) -> 16 | AM40: =if(AD40="Done",$J40,0) -> 16 | AN40: =if(AF40<>"",$J40,0) -> 16
A41: 46077 | B41: MFG | C41: Đặng Thị Ban | D41: V1547168 | E41: bandt1@fih-foxconn.com | F41: 4324 | G41: Monitor 2 | H41: =vlookup(G41,'Bidding list 26'!$B$4:$G$270,6,0) -> VA1903H-2, 19 inch, VGA cable + HDMI cable / Brand: VIEWSONIC | I41: 1240000 | J41: 11 | K41: =I41*J41 -> 13640000 | L41: BM2 | N41: BM2 | O41: FATP | P41: PVT | Q41: 46090 | R41: =Q41-A41 -> 13 | S41: {=INDEX('NONG Project Timeline-OPM updat'!$D$8:$I$65,MATCH(1,('NONG Project Timeline-OPM updat'!$B$8:$B$65=N41)*('NONG Project Timeline-OPM updat'!$C$8:$C$65=O41),0),MATCH(P41,'NONG Project Timeline-OPM updat'!$D$5:$I$5,0))-14} -> -14 | T41: =S41-A41 -> -46091 | U41: =IFERROR(VLOOKUP(G41,'Bidding list 26'!$B$2:$P$21,15,0),"") | V41: =S41-U41 -> -14 | W41: =if(A41>V41,"Late", "On time") -> Late | X41: New Buy | Z41: Done | AA41: FATP-NPI-BM2-MVA2602-118OM | AB41: Done | AC41: 1FSHQ30070 | AD41: Done | AE41: 1FSHQ30070 | AG41: 46141 | AH41: EPR2603070006 | AJ41: =B41&G41&J41&N41&X41&AA41 -> MFGMonitor 211BM2New BuyFATP-NPI-BM2-MVA2602-118OM | AK41: =if(Z41="Done",$J41,0) -> 11 | AL41: =if(AB41="Done",$J41,0) -> 11 | AM41: =if(AD41="Done",$J41,0) -> 11 | AN41: =if(AG41<>"",$J41,0) -> 11
A42: 46077 | B42: MFG | C42: Đặng Thị Ban | D42: V1547168 | E42: bandt1@fih-foxconn.com | F42: 4324 | G42: Mini PC (Assy) | H42: =vlookup(G42,'Bidding list 26'!$B$4:$G$270,6,0) -> #N/A | I42: 7800000 | J42: 11 | K42: =I42*J42 -> 85800000 | L42: BM2 | N42: BM2 | O42: FATP | P42: PVT | Q42: 46090 | R42: =Q42-A42 -> 13 | S42: {=INDEX('NONG Project Timeline-OPM updat'!$D$8:$I$65,MATCH(1,('NONG Project Timeline-OPM updat'!$B$8:$B$65=N42)*('NONG Project Timeline-OPM updat'!$C$8:$C$65=O42),0),MATCH(P42,'NONG Project Timeline-OPM updat'!$D$5:$I$5,0))-14} -> -14 | T42: =S42-A42 -> -46091 | U42: =IFERROR(VLOOKUP(G42,'Bidding list 26'!$B$2:$P$21,15,0),"") | V42: =S42-U42 -> -14 | W42: =if(A42>V42,"Late", "On time") -> Late | X42: New Buy | Z42: Done | AA42: FATP-NPI-BM2-MVA2602-118OM | AB42: Done | AC42: 1FSHQ30071 | AD42: Done | AE42: 1FSHQ30071 | AF42: pending | AG42: Lấy hết PO: 1FSHQ30071 cho MFG G // Trả đơn Ban MFG MINI PC ASUS | AH42: EPR2603070007: đã cancel // EPR2606240004 | AJ42: =B42&G42&J42&N42&X42&AA42 -> MFGMini PC (Assy)11BM2New BuyFATP-NPI-BM2-MVA2602-118OM | AK42: =if(Z42="Done",$J42,0) -> 11 | AL42: =if(AB42="Done",$J42,0) -> 11 | AM42: =if(AD42="Done",$J42,0) -> 11 | AN42: =if(AG42<>"",$J42,0) -> 11
A43: 46077 | B43: MFG | C43: Đặng Thị Ban | D43: V1547168 | E43: bandt1@fih-foxconn.com | F43: 4324 | G43: Barcode Scanner SEUIC HS505DP, USB cable | H43: =vlookup(G43,'Bidding list 26'!$B$4:$G$270,6,0) -> HS505DP, USB cable | I43: 2300000 | J43: 10 | K43: =I43*J43 -> 23000000 | L43: BM2 | N43: BM2 | O43: FATP | P43: PVT | Q43: 46090 | R43: =Q43-A43 -> 13 | S43: {=INDEX('NONG Project Timeline-OPM updat'!$D$8:$I$65,MATCH(1,('NONG Project Timeline-OPM updat'!$B$8:$B$65=N43)*('NONG Project Timeline-OPM updat'!$C$8:$C$65=O43),0),MATCH(P43,'NONG Project Timeline-OPM updat'!$D$5:$I$5,0))-14} -> -14 | T43: =S43-A43 -> -46091 | U43: =IFERROR(VLOOKUP(G43,'Bidding list 26'!$B$2:$P$21,15,0),"") -> 50 | V43: =S43-U43 -> -64 | W43: =if(A43>V43,"Late", "On time") -> Late | X43: New Buy | Z43: Done | AA43: FATP-NPI-BM2-MVA2603-23OM | AB43: Done | AC43: VNPR202603230171 | AD43: Done | AE43: VNPO202603280076 | AG43: 46167 | AH43: EPR2603210008 | AI43: Wed 3:09 PM | AJ43: =B43&G43&J43&N43&X43&AA43 -> MFGBarcode Scanner SEUIC HS505DP, USB cable10BM2New BuyFATP-NPI-BM2-MVA2603-23OM | AK43: =if(Z43="Done",$J43,0) -> 10 | AL43: =if(AB43="Done",$J43,0) -> 10 | AM43: =if(AD43="Done",$J43,0) -> 10 | AN43: =if(AG43<>"",$J43,0) -> 10
A44: 46077 | B44: MFG | C44: Đặng Thị Ban | D44: V1547168 | E44: bandt1@fih-foxconn.com | F44: 4324 | G44: Barcode Printer ZEBRA | H44: =vlookup(G44,'Bidding list 26'!$B$4:$G$270,6,0) -> ZT610, 600dpi | I44: 48800000 | J44: 4 | K44: =I44*J44 -> 195200000 | L44: BM2 | N44: BM2 | O44: FATP | P44: PVT | Q44: 46090 | R44: =Q44-A44 -> 13 | S44: {=INDEX('NONG Project Timeline-OPM updat'!$D$8:$I$65,MATCH(1,('NONG Project Timeline-OPM updat'!$B$8:$B$65=N44)*('NONG Project Timeline-OPM updat'!$C$8:$C$65=O44),0),MATCH(P44,'NONG Project Timeline-OPM updat'!$D$5:$I$5,0))-14} -> -14 | T44: =S44-A44 -> -46091 | U44: =IFERROR(VLOOKUP(G44,'Bidding list 26'!$B$2:$P$21,15,0),"") -> 50 | V44: =S44-U44 -> -64 | W44: =if(A44>V44,"Late", "On time") -> Late | X44: New Buy | Z44: Done | AA44: FATP-NPI-BM2-MVA2602-118OM | AB44: Done | AC44: 1FSHQ30072 | AD44: Done | AE44: 1FSHQ30072 | AG44: 46114 | AH44: EPR2603070008: Đã out | AI44: ( Đã out trước đó / 1FSHQ30072x: PO này về làm spare) | AJ44: =B44&G44&J44&N44&X44&AA44 -> MFGBarcode Printer ZEBRA4BM2New BuyFATP-NPI-BM2-MVA2602-118OM | AK44: =if(Z44="Done",$J44,0) -> 4 | AL44: =if(AB44="Done",$J44,0) -> 4 | AM44: =if(AD44="Done",$J44,0) -> 4 | AN44: =if(AG44<>"",$J44,0) -> 4
A45: 46078 | B45: PQE | C45: Nguyen Van Than | D45: V1550929 | E45: thannv@fih-foxconn.com | F45: 3802 | G45: IPC | H45: =vlookup(G45,'Bidding list 26'!$B$4:$G$270,6,0) -> #N/A | I45: 10870000 | J45: 6 | K45: =I45*J45 -> 65220000 | L45: MH2 | N45: MH2 | O45: FATP | P45: PVT | Q45: 46113 | R45: =Q45-A45 -> 35 | S45: {=INDEX('NONG Project Timeline-OPM updat'!$D$8:$I$65,MATCH(1,('NONG Project Timeline-OPM updat'!$B$8:$B$65=N45)*('NONG Project Timeline-OPM updat'!$C$8:$C$65=O45),0),MATCH(P45,'NONG Project Timeline-OPM updat'!$D$5:$I$5,0))-14} -> 46178 | T45: =S45-A45 -> 100 | U45: =IFERROR(VLOOKUP(G45,'Bidding list 26'!$B$2:$P$21,15,0),"") | V45: =S45-U45 -> 46178 | W45: =if(A45>V45,"Late", "On time") -> On time | X45: New Buy | Y45: G | Z45: Done | AA45: FATP-NPI-MH2-MVA2603-09OM | AB45: Done | AC45: 1FSHQ30125 | AD45: Done | AE45: 1FSHQ30125 : Lấy hàng trong kho trước ( Hàng trong kho: 1FSHQ10101) / Hàng về làm spare sau | AG45: 46107 | AH45: EPR2603070009 | AJ45: =B45&G45&J45&N45&X45&AA45 -> PQEIPC6MH2New BuyFATP-NPI-MH2-MVA2603-09OM | AK45: =if(Z45="Done",$J45,0) -> 6 | AL45: =if(AB45="Done",$J45,0) -> 6 | AM45: =if(AD45="Done",$J45,0) -> 6 | AN45: =if(AG45<>"",$J45,0) -> 6
A46: 46078 | B46: PQE | C46: Nguyen Van Than | D46: V1550929 | E46: thannv@fih-foxconn.com | F46: 3802 | G46: Monitor 2 | H46: =vlookup(G46,'Bidding list 26'!$B$4:$G$270,6,0) -> VA1903H-2, 19 inch, VGA cable + HDMI cable / Brand: VIEWSONIC | I46: 1240000 | J46: 6 | K46: =I46*J46 -> 7440000 | L46: MH2 | N46: MH2 | O46: FATP | P46: PVT | Q46: 46113 | R46: =Q46-A46 -> 35 | S46: {=INDEX('NONG Project Timeline-OPM updat'!$D$8:$I$65,MATCH(1,('NONG Project Timeline-OPM updat'!$B$8:$B$65=N46)*('NONG Project Timeline-OPM updat'!$C$8:$C$65=O46),0),MATCH(P46,'NONG Project Timeline-OPM updat'!$D$5:$I$5,0))-14} -> 46178 | T46: =S46-A46 -> 100 | U46: =IFERROR(VLOOKUP(G46,'Bidding list 26'!$B$2:$P$21,15,0),"") | V46: =S46-U46 -> 46178 | W46: =if(A46>V46,"Late", "On time") -> On time | X46: New Buy | Z46: Done | AA46: FATP-NPI-MH2-MVA2602-119OM | AB46: Done | AC46: 1FSHQ30029 | AD46: Done | AE46: 1FSHQ30029 | AG46: Đã nhận 16.03.2026 | AH46: EPR2603070010 | AJ46: =B46&G46&J46&N46&X46&AA46 -> PQEMonitor 26MH2New BuyFATP-NPI-MH2-MVA2602-119OM | AK46: =if(Z46="Done",$J46,0) -> 6 | AL46: =if(AB46="Done",$J46,0) -> 6 | AM46: =if(AD46="Done",$J46,0) -> 6 | AN46: =if(AG46<>"",$J46,0) -> 6
A47: 46078 | B47: PQE | C47: Nguyen Van Than | D47: V1550929 | E47: thannv@fih-foxconn.com | F47: 3802 | G47: Barcode Scanner SEUIC HS505DP, USB cable | H47: =vlookup(G47,'Bidding list 26'!$B$4:$G$270,6,0) -> HS505DP, USB cable | I47: 2300000 | J47: 5 | K47: =I47*J47 -> 11500000 | L47: MH2 | N47: MH2 | O47: FATP | P47: PVT | Q47: 46113 | R47: =Q47-A47 -> 35 | S47: {=INDEX('NONG Project Timeline-OPM updat'!$D$8:$I$65,MATCH(1,('NONG Project Timeline-OPM updat'!$B$8:$B$65=N47)*('NONG Project Timeline-OPM updat'!$C$8:$C$65=O47),0),MATCH(P47,'NONG Project Timeline-OPM updat'!$D$5:$I$5,0))-14} -> 46178 | T47: =S47-A47 -> 100 | U47: =IFERROR(VLOOKUP(G47,'Bidding list 26'!$B$2:$P$21,15,0),"") -> 50 | V47: =S47-U47 -> 46128 | W47: =if(A47>V47,"Late", "On time") -> On time | X47: New Buy | Z47: Done | AA47: FATP-NPI-MH2-MVA2603-22OM | AB47: Done | AC47: VNPR202603230176 | AD47: Done | AE47: VNPO202603280076 | AG47: 46137 | AH47: EPR2603210005 | AI47: 46157.614 | AJ47: =B47&G47&J47&N47&X47&AA47 -> PQEBarcode Scanner SEUIC HS505DP, USB cable5MH2New BuyFATP-NPI-MH2-MVA2603-22OM | AK47: =if(Z47="Done",$J47,0) -> 5 | AL47: =if(AB47="Done",$J47,0) -> 5 | AM47: =if(AD47="Done",$J47,0) -> 5 | AN47: =if(AG47<>"",$J47,0) -> 5
A48: 46083 | B48: TE | C48: Nguyễn Đức Mạnh | D48: V1536673 | E48: manhnd6@fih-foxconn.com | G48: IPC+(updated) | H48: =vlookup(G48,'Bidding list 26'!$B$4:$G$270,6,0) -> Pro Tower QCT1250, Ultra 5 235, Ram 16GB DDR5, SSD 512GB, Integrated graphics card, Power 180W, HDMI & DP Port, Keyboard and Mouse, 3Yrs Wty | I48: 18717000 | J48: 13 | K48: =I48*J48 -> 243321000 | L48: OR6 EVT | N48: OR6 | O48: FATP | P48: EVT | Q48: 46113 | R48: =Q48-A48 -> 30 | S48: {=INDEX('NONG Project Timeline-OPM updat'!$D$8:$I$65,MATCH(1,('NONG Project Timeline-OPM updat'!$B$8:$B$65=N48)*('NONG Project Timeline-OPM updat'!$C$8:$C$65=O48),0),MATCH(P48,'NONG Project Timeline-OPM updat'!$D$5:$I$5,0))-14} -> 46074 | T48: =S48-A48 -> -9 | U48: =IFERROR(VLOOKUP(G48,'Bidding list 26'!$B$2:$P$21,15,0),"") -> 70 | V48: =S48-U48 -> 46004 | W48: =if(A48>V48,"Late", "On time") -> Late | X48: New Buy | Z48: Done | AA48: FATP-NPI-OR6-MVA2603-02OM / SMT-NPI-OR6-MVA2603-15OM | AB48: Done | AC48: 1FSHQ30093 & 1FSHQ30116 | AD48: Done | AE48: 1FSHQ30093 & 1FSHQ30116 | AG48: 46135 | AH48: EPR2603210042 | AJ48: =B48&G48&J48&N48&X48&AA48 -> TEIPC+(updated)13OR6New BuyFATP-NPI-OR6-MVA2603-02OM / SMT-NPI-OR6-MVA2603-15OM | AK48: =if(Z48="Done",$J48,0) -> 13 | AL48: =if(AB48="Done",$J48,0) -> 13 | AM48: =if(AD48="Done",$J48,0) -> 13 | AN48: =if(AG48<>"",$J48,0) -> 13
A49: 46083 | B49: TE | C49: Nguyen Duc Manh | D49: V1536673 | E49: manhnd6@fih-foxconn.com | G49: Monitor 2 | H49: =vlookup(G49,'Bidding list 26'!$B$4:$G$270,6,0) -> VA1903H-2, 19 inch, VGA cable + HDMI cable / Brand: VIEWSONIC | I49: 1240000 | J49: 14 | K49: =I49*J49 -> 17360000 | L49: OR6 EVT | N49: OR6 | O49: FATP | P49: EVT | Q49: 46113 | R49: =Q49-A49 -> 30 | S49: {=INDEX('NONG Project Timeline-OPM updat'!$D$8:$I$65,MATCH(1,('NONG Project Timeline-OPM updat'!$B$8:$B$65=N49)*('NONG Project Timeline-OPM updat'!$C$8:$C$65=O49),0),MATCH(P49,'NONG Project Timeline-OPM updat'!$D$5:$I$5,0))-14} -> 46074 | T49: =S49-A49 -> -9 | U49: =IFERROR(VLOOKUP(G49,'Bidding list 26'!$B$2:$P$21,15,0),"") | V49: =S49-U49 -> 46074 | W49: =if(A49>V49,"Late", "On time") -> Late | X49: New Buy | Z49: Done | AA49: FATP-NPI-OR6-MVA2603-02OM / SMT-NPI-OR6-MVA2603-15OM | AB49: Done | AC49: 1FSHQ30094 / 1FSHQ30117 | AD49: Done | AE49: 1FSHQ30094 / 1FSHQ30117 | AG49: 46154 | AH49: EPR2603070021 | AI49: 1FSHQ30094 / 1FSHQ30117 ( Lấy hàng trong kho trước 2 PO về làm spare part) | AJ49: =B49&G49&J49&N49&X49&AA49 -> TEMonitor 214OR6New BuyFATP-NPI-OR6-MVA2603-02OM / SMT-NPI-OR6-MVA2603-15OM | AK49: =if(Z49="Done",$J49,0) -> 14 | AL49: =if(AB49="Done",$J49,0) -> 14 | AM49: =if(AD49="Done",$J49,0) -> 14 | AN49: =if(AG49<>"",$J49,0) -> 14
A50: 46083 | B50: TE | C50: Nguyen Duc Manh | D50: V1536673 | E50: manhnd6@fih-foxconn.com | G50: Mini PC ASUS NUC 15 (TE only) | H50: =vlookup(G50,'Bidding list 26'!$B$4:$G$270,6,0) -> NUC 15 PRO Tall/ U7-255H/16GB DDR5/512GB NVMe SSD, 3Yrs Wty | I50: 20870000 | J50: 1 | K50: =I50*J50 -> 20870000 | L50: OR6 EVT | N50: OR6 | O50: FATP | P50: EVT | Q50: 46113 | R50: =Q50-A50 -> 30 | S50: {=INDEX('NONG Project Timeline-OPM updat'!$D$8:$I$65,MATCH(1,('NONG Project Timeline-OPM updat'!$B$8:$B$65=N50)*('NONG Project Timeline-OPM updat'!$C$8:$C$65=O50),0),MATCH(P50,'NONG Project Timeline-OPM updat'!$D$5:$I$5,0))-14} -> 46074 | T50: =S50-A50 -> -9 | U50: =IFERROR(VLOOKUP(G50,'Bidding list 26'!$B$2:$P$21,15,0),"") -> 50 | V50: =S50-U50 -> 46024 | W50: =if(A50>V50,"Late", "On time") -> Late | X50: New Buy | Z50: Done | AA50: FATP-NPI-OR6-MVA2603-02OM | AB50: Done | AC50: 1FSHQ30095 | AD50: Done | AE50: 1FSHQ30095 | AG50: 46106 | AH50: EPR2603210003 | AJ50: =B50&G50&J50&N50&X50&AA50 -> TEMini PC ASUS NUC 15 (TE only)1OR6New BuyFATP-NPI-OR6-MVA2603-02OM | AK50: =if(Z50="Done",$J50,0) -> 1 | AL50: =if(AB50="Done",$J50,0) -> 1 | AM50: =if(AD50="Done",$J50,0) -> 1 | AN50: =if(AG50<>"",$J50,0) -> 1
A51: 46083 | B51: TE | C51: Nguyễn Đức Mạnh | D51: V1536673 | E51: manhnd6@fih-foxconn.com | G51: Barcode Scanner SEUIC HS505DP, USB cable | H51: =vlookup(G51,'Bidding list 26'!$B$4:$G$270,6,0) -> HS505DP, USB cable | I51: 2300000 | J51: 13 | K51: =I51*J51 -> 29900000 | L51: OR6 EVT | N51: OR6 | O51: FATP | P51: EVT | Q51: 46113 | R51: =Q51-A51 -> 30 | S51: {=INDEX('NONG Project Timeline-OPM updat'!$D$8:$I$65,MATCH(1,('NONG Project Timeline-OPM updat'!$B$8:$B$65=N51)*('NONG Project Timeline-OPM updat'!$C$8:$C$65=O51),0),MATCH(P51,'NONG Project Timeline-OPM updat'!$D$5:$I$5,0))-14} -> 46074 | T51: =S51-A51 -> -9 | U51: =IFERROR(VLOOKUP(G51,'Bidding list 26'!$B$2:$P$21,15,0),"") -> 50 | V51: =S51-U51 -> 46024 | W51: =if(A51>V51,"Late", "On time") -> Late | X51: New Buy | Z51: Done | AA51: FATP-NPI-OR6-MVA2603-24OM | AB51: Done | AC51: VNPR202604040090 | AD51: Done | AE51: VNPO202604100231 | AF51: 46137 | AG51: 46146 | AH51: EPR2603210014 | AI51: 46146.427 | AJ51: =B51&G51&J51&N51&X51&AA51 -> TEBarcode Scanner SEUIC HS505DP, USB cable13OR6New BuyFATP-NPI-OR6-MVA2603-24OM | AK51: =if(Z51="Done",$J51,0) -> 13 | AL51: =if(AB51="Done",$J51,0) -> 13 | AM51: =if(AD51="Done",$J51,0) -> 13 | AN51: =if(AF51<>"",$J51,0) -> 13
A52: 46083 | B52: WH | C52: Le Thi Lich | D52: V1525678 | E52: lichlt@fih-foxconn.com | F52: 4478 | G52: IPC(updated) | H52: =vlookup(G52,'Bidding list 26'!$B$4:$G$270,6,0) -> Pro Tower QCT1250, Core i3-14100, Ram 8GB DDR5, SSD 512GB, Integrated graphics card, Power 180W, HDMI & DP Port, Keyboard and Mouse, 3Yrs Wty | I52: 13888000 | J52: 3 | K52: =I52*J52 -> 41664000 | L52: MH2 | N52: MH2 | O52: FATP | P52: PVT | R52: =Q52-A52 -> -46083 | S52: {=INDEX('NONG Project Timeline-OPM updat'!$D$8:$I$65,MATCH(1,('NONG Project Timeline-OPM updat'!$B$8:$B$65=N52)*('NONG Project Timeline-OPM updat'!$C$8:$C$65=O52),0),MATCH(P52,'NONG Project Timeline-OPM updat'!$D$5:$I$5,0))-14} -> 46178 | T52: =S52-A52 -> 95 | U52: =IFERROR(VLOOKUP(G52,'Bidding list 26'!$B$2:$P$21,15,0),"") -> 50 | V52: =S52-U52 -> 46128 | W52: =if(A52>V52,"Late", "On time") -> On time | X52: New Buy | Z52: Done | AA52: FATP-NPI-MH2-MVA2603-06OM | AB52: Done | AC52: 1FSHQ30127 | AD52: Done | AE52: 1FSHQ30127: Lấy hàng trong kho trước ( Hàng trong kho: 1FSHQ10101) / Hàng về làm spare sau | AG52: 46107 | AH52: EPR2603070022: Done | AJ52: =B52&G52&J52&N52&X52&AA52 -> WHIPC(updated)3MH2New BuyFATP-NPI-MH2-MVA2603-06OM | AK52: =if(Z52="Done",$J52,0) -> 3 | AL52: =if(AB52="Done",$J52,0) -> 3 | AM52: =if(AD52="Done",$J52,0) -> 3 | AN52: =if(AG52<>"",$J52,0) -> 3
A53: 46083 | B53: WH | C53: Le Thi Lich | D53: V1525678 | E53: lichlt@fih-foxconn.com | F53: 4478 | G53: Monitor 1 | H53: =vlookup(G53,'Bidding list 26'!$B$4:$G$270,6,0) -> DELL E2225HM, 21.5 inch HDMI cable, 3Yrs Wty | I53: 1980000 | J53: 3 | K53: =I53*J53 -> 5940000 | L53: MH2 | N53: MH2 | O53: FATP | P53: PVT | R53: =Q53-A53 -> -46083 | S53: {=INDEX('NONG Project Timeline-OPM updat'!$D$8:$I$65,MATCH(1,('NONG Project Timeline-OPM updat'!$B$8:$B$65=N53)*('NONG Project Timeline-OPM updat'!$C$8:$C$65=O53),0),MATCH(P53,'NONG Project Timeline-OPM updat'!$D$5:$I$5,0))-14} -> 46178 | T53: =S53-A53 -> 95 | U53: =IFERROR(VLOOKUP(G53,'Bidding list 26'!$B$2:$P$21,15,0),"") | V53: =S53-U53 -> 46178 | W53: =if(A53>V53,"Late", "On time") -> On time | X53: New Buy | Z53: Done | AA53: FATP-NPI-MH2-MVA2603-06OM | AB53: Done | AC53: 1FSHQ30124 | AD53: Done | AE53: 1FSHQ30124 | AG53: 46254 | AH53: EPR2603070023 | AJ53: =B53&G53&J53&N53&X53&AA53 -> WHMonitor 13MH2New BuyFATP-NPI-MH2-MVA2603-06OM | AK53: =if(Z53="Done",$J53,0) -> 3 | AL53: =if(AB53="Done",$J53,0) -> 3 | AM53: =if(AD53="Done",$J53,0) -> 3 | AN53: =if(AG53<>"",$J53,0) -> 3
A54: 46083 | B54: WH | C54: Le Thi Lich | D54: V1525678 | E54: lichlt@fih-foxconn.com | F54: 4478 | G54: Barcode Scanner ZEBRA DS8178,USB cable | H54: =vlookup(G54,'Bidding list 26'!$B$4:$G$270,6,0) -> ZEBRA DS8178,USB cable PCS Wireless Scanner | I54: 5800000 | J54: 2 | K54: =I54*J54 -> 11600000 | L54: MH2 | N54: MH2 | O54: FATP | P54: PVT | R54: =Q54-A54 -> -46083 | S54: {=INDEX('NONG Project Timeline-OPM updat'!$D$8:$I$65,MATCH(1,('NONG Project Timeline-OPM updat'!$B$8:$B$65=N54)*('NONG Project Timeline-OPM updat'!$C$8:$C$65=O54),0),MATCH(P54,'NONG Project Timeline-OPM updat'!$D$5:$I$5,0))-14} -> 46178 | T54: =S54-A54 -> 95 | U54: =IFERROR(VLOOKUP(G54,'Bidding list 26'!$B$2:$P$21,15,0),"") -> 65 | V54: =S54-U54 -> 46113 | W54: =if(A54>V54,"Late", "On time") -> On time | X54: New Buy | Z54: Done | AA54: FATP-NPI-MH2-MVA2603-11OM | AB54: Done | AC54: VNPR202603130176 | AD54: Done | AE54: VNPO202603190072 | AG54: 46259 | AH54: EPR2603070024 | AJ54: =B54&G54&J54&N54&X54&AA54 -> WH Barcode Scanner ZEBRA DS8178,USB cable2MH2New BuyFATP-NPI-MH2-MVA2603-11OM | AK54: =if(Z54="Done",$J54,0) -> 2 | AL54: =if(AB54="Done",$J54,0) -> 2 | AM54: =if(AD54="Done",$J54,0) -> 2 | AN54: =if(AG54<>"",$J54,0) -> 2
A55: 46083 | B55: WH | C55: Le Thi Lich | D55: V1525678 | E55: lichlt@fih-foxconn.com | F55: 4478 | G55: Barcode Printer ZEBRA | H55: =vlookup(G55,'Bidding list 26'!$B$4:$G$270,6,0) -> ZT610, 600dpi | I55: 48800000 | J55: 1 | K55: =I55*J55 -> 48800000 | L55: MH2 | N55: MH2 | O55: FATP | P55: PVT | R55: =Q55-A55 -> -46083 | S55: {=INDEX('NONG Project Timeline-OPM updat'!$D$8:$I$65,MATCH(1,('NONG Project Timeline-OPM updat'!$B$8:$B$65=N55)*('NONG Project Timeline-OPM updat'!$C$8:$C$65=O55),0),MATCH(P55,'NONG Project Timeline-OPM updat'!$D$5:$I$5,0))-14} -> 46178 | T55: =S55-A55 -> 95 | U55: =IFERROR(VLOOKUP(G55,'Bidding list 26'!$B$2:$P$21,15,0),"") -> 50 | V55: =S55-U55 -> 46128 | W55: =if(A55>V55,"Late", "On time") -> On time | X55: New Buy | Z55: Done | AA55: FATP-NPI-MH2-MVA2603-06OM | AB55: Done | AC55: 1FSHQ30128 | AD55: Done | AE55: 1FSHQ30128 | AG55: 46162 | AH55: EPR2603070025 | AI55: ( Lây 1x máy ở 1FSHPC0092 trước / hàng về làm spare ) | AJ55: =B55&G55&J55&N55&X55&AA55 -> WHBarcode Printer ZEBRA1MH2New BuyFATP-NPI-MH2-MVA2603-06OM | AK55: =if(Z55="Done",$J55,0) -> 1 | AL55: =if(AB55="Done",$J55,0) -> 1 | AM55: =if(AD55="Done",$J55,0) -> 1 | AN55: =if(AG55<>"",$J55,0) -> 1
A56: 46083 | B56: WH | C56: Le Thi Lich | D56: V1525678 | E56: lichlt@fih-foxconn.com | F56: 4478 | G56: PDA CHAINWAY C61-4850 | H56: =vlookup(G56,'Bidding list 26'!$B$4:$G$270,6,0) -> C61-4850, Not including RFID module. Includes: 64GB 27-key Android 11, controller with battery, charging dock, charging adapter, glass screen protector | I56: 15500000 | J56: 5 | K56: =I56*J56 -> 77500000 | L56: MH2 | N56: MH2 | O56: FATP | P56: PVT | R56: =Q56-A56 -> -46083 | S56: {=INDEX('NONG Project Timeline-OPM updat'!$D$8:$I$65,MATCH(1,('NONG Project Timeline-OPM updat'!$B$8:$B$65=N56)*('NONG Project Timeline-OPM updat'!$C$8:$C$65=O56),0),MATCH(P56,'NONG Project Timeline-OPM updat'!$D$5:$I$5,0))-14} -> 46178 | T56: =S56-A56 -> 95 | U56: =IFERROR(VLOOKUP(G56,'Bidding list 26'!$B$2:$P$21,15,0),"") -> 65 | V56: =S56-U56 -> 46113 | W56: =if(A56>V56,"Late", "On time") -> On time | X56: New Buy | Z56: Done | AA56: FATP-NPI-MH2-MVA2603-06OM | AB56: Done | AC56: VNPR202603130196 | AD56: Done | AE56: VNPO202603200118 | AG56: 46149 | AH56: EPR2603070026 | AI56: đã out 20may tại vp OM - chị Việt | AJ56: =B56&G56&J56&N56&X56&AA56 -> WHPDA CHAINWAY C61-48505MH2New BuyFATP-NPI-MH2-MVA2603-06OM | AK56: =if(Z56="Done",$J56,0) -> 5 | AL56: =if(AB56="Done",$J56,0) -> 5 | AM56: =if(AD56="Done",$J56,0) -> 5 | AN56: =if(AG56<>"",$J56,0) -> 5
A57: 46083 | B57: WH | C57: Le Thi Lich | D57: V1525678 | E57: lichlt@fih-foxconn.com | F57: 4478 | G57: IPC(updated) | H57: =vlookup(G57,'Bidding list 26'!$B$4:$G$270,6,0) -> Pro Tower QCT1250, Core i3-14100, Ram 8GB DDR5, SSD 512GB, Integrated graphics card, Power 180W, HDMI & DP Port, Keyboard and Mouse, 3Yrs Wty | I57: 13888000 | J57: 3 | K57: =I57*J57 -> 41664000 | L57: AS3 | N57: AS3 | O57: FATP | P57: MP | R57: =Q57-A57 -> -46083 | S57: {=INDEX('NONG Project Timeline-OPM updat'!$D$8:$I$65,MATCH(1,('NONG Project Timeline-OPM updat'!$B$8:$B$65=N57)*('NONG Project Timeline-OPM updat'!$C$8:$C$65=O57),0),MATCH(P57,'NONG Project Timeline-OPM updat'!$D$5:$I$5,0))-14} -> -14 | T57: =S57-A57 -> -46097 | U57: =IFERROR(VLOOKUP(G57,'Bidding list 26'!$B$2:$P$21,15,0),"") -> 50 | V57: =S57-U57 -> -64 | W57: =if(A57>V57,"Late", "On time") -> Late | X57: New Buy | Z57: Done | AA57: FATP-MP-AS3-MVA2603-07OM | AB57: Done | AC57: 1FSHQ30074 | AD57: Done | AE57: 1FSHQ30074 | AG57: 26/03/2026 | AH57: EPR2603070027: Done | AJ57: =B57&G57&J57&N57&X57&AA57 -> WHIPC(updated)3AS3New BuyFATP-MP-AS3-MVA2603-07OM | AK57: =if(Z57="Done",$J57,0) -> 3 | AL57: =if(AB57="Done",$J57,0) -> 3 | AM57: =if(AD57="Done",$J57,0) -> 3 | AN57: =if(AG57<>"",$J57,0) -> 3
A58: 46083 | B58: WH | C58: Le Thi Lich | D58: V1525678 | E58: lichlt@fih-foxconn.com | F58: 4478 | G58: Monitor 1 | H58: =vlookup(G58,'Bidding list 26'!$B$4:$G$270,6,0) -> DELL E2225HM, 21.5 inch HDMI cable, 3Yrs Wty | I58: 1980000 | J58: 3 | K58: =I58*J58 -> 5940000 | L58: AS3 | N58: AS3 | O58: FATP | P58: MP | R58: =Q58-A58 -> -46083 | S58: {=INDEX('NONG Project Timeline-OPM updat'!$D$8:$I$65,MATCH(1,('NONG Project Timeline-OPM updat'!$B$8:$B$65=N58)*('NONG Project Timeline-OPM updat'!$C$8:$C$65=O58),0),MATCH(P58,'NONG Project Timeline-OPM updat'!$D$5:$I$5,0))-14} -> -14 | T58: =S58-A58 -> -46097 | U58: =IFERROR(VLOOKUP(G58,'Bidding list 26'!$B$2:$P$21,15,0),"") | V58: =S58-U58 -> -14 | W58: =if(A58>V58,"Late", "On time") -> Late | X58: New Buy | Z58: Done | AA58: FATP-MP-AS3-MVA2603-07OM | AB58: Done | AC58: 1FSHQ30077 | AD58: Done | AE58: 1FSHQ30077 | AG58: Đã nhận 20.04 | AH58: EPR2603070028 | AJ58: =B58&G58&J58&N58&X58&AA58 -> WHMonitor 13AS3New BuyFATP-MP-AS3-MVA2603-07OM | AK58: =if(Z58="Done",$J58,0) -> 3 | AL58: =if(AB58="Done",$J58,0) -> 3 | AM58: =if(AD58="Done",$J58,0) -> 3 | AN58: =if(AG58<>"",$J58,0) -> 3
A59: 46083 | B59: WH | C59: Le Thi Lich | D59: V1525678 | E59: lichlt@fih-foxconn.com | F59: 4478 | G59: Barcode Scanner ZEBRA DS8178,USB cable | H59: =vlookup(G59,'Bidding list 26'!$B$4:$G$270,6,0) -> ZEBRA DS8178,USB cable PCS Wireless Scanner | I59: 5800000 | J59: 2 | K59: =I59*J59 -> 11600000 | L59: AS3 | N59: AS3 | O59: FATP | P59: MP | R59: =Q59-A59 -> -46083 | S59: {=INDEX('NONG Project Timeline-OPM updat'!$D$8:$I$65,MATCH(1,('NONG Project Timeline-OPM updat'!$B$8:$B$65=N59)*('NONG Project Timeline-OPM updat'!$C$8:$C$65=O59),0),MATCH(P59,'NONG Project Timeline-OPM updat'!$D$5:$I$5,0))-14} -> -14 | T59: =S59-A59 -> -46097 | U59: =IFERROR(VLOOKUP(G59,'Bidding list 26'!$B$2:$P$21,15,0),"") -> 65 | V59: =S59-U59 -> -79 | W59: =if(A59>V59,"Late", "On time") -> Late | X59: New Buy | Z59: Done | AA59: FATP-MP-AS3-MVA2603-12OM | AB59: Done | AC59: VNPR202603130186 | AD59: Done | AE59: VNPO202603230130 | AG59: 46137 | AH59: EPR2603070029 | AJ59: =B59&G59&J59&N59&X59&AA59 -> WH Barcode Scanner ZEBRA DS8178,USB cable2AS3New BuyFATP-MP-AS3-MVA2603-12OM | AK59: =if(Z59="Done",$J59,0) -> 2 | AL59: =if(AB59="Done",$J59,0) -> 2 | AM59: =if(AD59="Done",$J59,0) -> 2 | AN59: =if(AG59<>"",$J59,0) -> 2
A60: 46083 | B60: WH | C60: Le Thi Lich | D60: V1525678 | E60: lichlt@fih-foxconn.com | F60: 4478 | G60: PDA CHAINWAY C61-4850 | H60: =vlookup(G60,'Bidding list 26'!$B$4:$G$270,6,0) -> C61-4850, Not including RFID module. Includes: 64GB 27-key Android 11, controller with battery, charging dock, charging adapter, glass screen protector | I60: 15500000 | J60: 2 | K60: =I60*J60 -> 31000000 | L60: AS3 | N60: AS3 | O60: FATP | P60: MP | R60: =Q60-A60 -> -46083 | S60: {=INDEX('NONG Project Timeline-OPM updat'!$D$8:$I$65,MATCH(1,('NONG Project Timeline-OPM updat'!$B$8:$B$65=N60)*('NONG Project Timeline-OPM updat'!$C$8:$C$65=O60),0),MATCH(P60,'NONG Project Timeline-OPM updat'!$D$5:$I$5,0))-14} -> -14 | T60: =S60-A60 -> -46097 | U60: =IFERROR(VLOOKUP(G60,'Bidding list 26'!$B$2:$P$21,15,0),"") -> 65 | V60: =S60-U60 -> -79 | W60: =if(A60>V60,"Late", "On time") -> Late | X60: New Buy | Z60: Done | AA60: FATP-MP-AS3-MVA2603-07OM | AB60: Done | AC60: VNPR202603110208 | AD60: Done | AE60: VNPO202603160180 | AG60: 46149 | AH60: EPR2603070030 | AI60: đã out tại OM office 30 May | AJ60: =B60&G60&J60&N60&X60&AA60 -> WHPDA CHAINWAY C61-48502AS3New BuyFATP-MP-AS3-MVA2603-07OM | AK60: =if(Z60="Done",$J60,0) -> 2 | AL60: =if(AB60="Done",$J60,0) -> 2 | AM60: =if(AD60="Done",$J60,0) -> 2 | AN60: =if(AG60<>"",$J60,0) -> 2
